Workbook

Sheet 00_투자판단
C2: 그날의 류 투자 검토 요약
C4: 선택 시나리오 | F4: ='01_가정'!H4 -> 보수
C5: 현재 판단은 조건부 검증 투자입니다. 본 제품의 생리주기 개선 효과, 양산 견적, 실매출은 아직 입증되지 않았습니다. 100일 검증 결과에 따라 후속 집행을 결정합니다.
C8: 주요 결과 | D8: 단위 | F8: 1년차 | G8: 2년차 | H8: 3년차
C9: 본체 출고 | D9: 개 | F9: ='03_월별손익'!F19 -> 56 | G9: ='03_월별손익'!G19 -> 804 | H9: ='03_월별손익'!H19 -> 1680
C10: 총 순매출 | D10: 원 | F10: ='03_월별손익'!F33 -> 5612169.8 | G10: ='03_월별손익'!G33 -> 85304202 | H10: ='03_월별손익'!H33 -> 1.8472419e+08
C11: 리필 순매출 | D11: 원 | F11: ='03_월별손익'!F32 -> 29988 | G11: ='03_월별손익'!G32 -> 2331401.6 | H11: ='03_월별손익'!H32 -> 7407828.8
C12: 광고 후 공헌이익 | D12: 원 | F12: ='03_월별손익'!F48 -> -2364339.8 | G12: ='03_월별손익'!G48 -> -15451930 | H12: ='03_월별손익'!H48 -> -3555650.7
C13: 경제적 인건비 | D13: 원 | F13: ='03_월별손익'!F49 -> 162000000 | G13: ='03_월별손익'!G49 -> 169200000 | H13: ='03_월별손익'!H49 -> 180000000
C14: EBITDA | D14: 원 | F14: ='03_월별손익'!F52 -> -2.4336434e+08 | G14: ='03_월별손익'!G52 -> -2.3265193e+08 | H14: ='03_월별손익'!H52 -> -2.3755565e+08
C15: 영업이익 | D15: 원 | F15: ='03_월별손익'!F54 -> -2.4683656e+08 | G15: ='03_월별손익'!G54 -> -2.4098526e+08 | H15: ='03_월별손익'!H54 -> -2.4588898e+08
C16: 기말 현금 | D16: 원 | F16: ='04_재고현금'!F43 -> -8513773.8 | G16: ='04_재고현금'!G43 -> -2.5232793e+08 | H16: ='04_재고현금'!H43 -> -4.7188363e+08
C17: 연중 최대 추가자금 필요 | D17: 원 | F17: ='04_재고현금'!F44 -> 38513774 | G17: ='04_재고현금'!G44 -> 2.8232793e+08 | H17: ='04_재고현금'!H44 -> 5.0188363e+08
C20: 출시 첫해 본체 유료 CAC | D20: 원 | F20: ='02_단위경제'!F19 -> 80000
C21: 출시 첫해 본체 CM2 | D21: 원 | F21: ='02_단위경제'!F20 -> -62007.682
C22: CM2 목표 달성 허용 CAC | D22: 원 | F22: ='02_단위경제'!F23 -> -2007.6818
C23: 36개월 최대 추가자금 필요 | D23: 원 | F23: =MAX('04_재고현금'!J44:AS44) -> 5.0188363e+08
C24: 36개월 최저 현금 | D24: 원 | F24: =MIN('04_재고현금'!J43:AS43) -> -4.7188363e+08
C25: 첫 현금 부족 월 | D25: 월 | F25: =IF(MIN('04_재고현금'!J43:AS43)>=0,"없음",MATCH(1,J52:AS52,0)) -> 12
C28: 첫 화면의 손익은 독립 사업 기준입니다. 회사 인건비 지원은 현금에만 반영합니다. 기본 시나리오에는 확정되지 않은 올리브영 및 기타 리테일 매출이 포함되지 않습니다.
C31: 투자 결정을 바꾸는 세 가지 증거
C33: 고객 가격 제시 후 실제 지불과 재사용이 발생하는가. 예약금은 관심 신호이며 실제 출고와 환불을 확인하기 전 판매 전환율로 사용하지 않습니다.
C35: 제품 발목 착용과 지압이 기존 온열 또는 간단한 밴드보다 고객에게 추가 가치를 주는가. 온열 압박의 안전 범위를 먼저 정합니다.
C37: 경제성 검수 원가와 물류 AS 및 광고를 뺀 본체 이익이 양수인가. 리필 구매를 0으로 바꿔도 사업이 버틸 수 있는지 확인합니다.
C40: 사용 순서 01 가정에서 시나리오 선택과 노란 입력 수정 → 00 요약 확인 → 02 단위경제와 04 재고현금 확인. 실제 데이터는 08 실측입력에 기록합니다.
J44: 연도 | K44: 순매출 백만원 | L44: 영업이익 백만원 | M44: 기말현금 백만원
J45: 1년차 | K45: =F10/1000000 -> 5.6121698 | L45: =F15/1000000 -> -246.83656 | M45: =F16/1000000 -> -8.5137738
J46: 2년차 | K46: =G10/1000000 -> 85.304202 | L46: =G15/1000000 -> -240.98526 | M46: =G16/1000000 -> -252.32793
J47: 3년차 | K47: =H10/1000000 -> 184.72419 | L47: =H15/1000000 -> -245.88898 | M47: =H16/1000000 -> -471.88363
J51: 1 | K51: 2 | L51: 3 | M51: 4 | N51: 5 | O51: 6 | P51: 7 | Q51: 8 | R51: 9 | S51: 10 | T51: 11 | U51: 12 | V51: 13 | W51: 14 | X51: 15 | Y51: 16 | Z51: 17 | AA51: 18 | AB51: 19 | AC51: 20 | AD51: 21 | AE51: 22 | AF51: 23 | AG51: 24 | AH51: 25 | AI51: 26 | AJ51: 27 | AK51: 28 | AL51: 29 | AM51: 30 | AN51: 31 | AO51: 32 | AP51: 33 | AQ51: 34 | AR51: 35 | AS51: 36
J52: =IF('04_재고현금'!J43<0,1,0) -> 0 | K52: =IF('04_재고현금'!K43<0,1,0) -> 0 | L52: =IF('04_재고현금'!L43<0,1,0) -> 0 | M52: =IF('04_재고현금'!M43<0,1,0) -> 0 | N52: =IF('04_재고현금'!N43<0,1,0) -> 0 | O52: =IF('04_재고현금'!O43<0,1,0) -> 0 | P52: =IF('04_재고현금'!P43<0,1,0) -> 0 | Q52: =IF('04_재고현금'!Q43<0,1,0) -> 0 | ... AS52: =IF('04_재고현금'!AS43<0,1,0) -> 1

Sheet 01_가정
C2: 사업 가정 · 숫자를 바꾸면 매출과 현금이 달라지는 설정표
F4: 1 | G4: 선택 결과 | H4: =CHOOSE(F4,"보수","기준","확장") -> 보수
C5: 모델 시작월 | F5: 46388
C6: ① F4에서 1 보수 / 2 기준 / 3 확장 선택 → ② 노란 칸의 가정 수정 → ③ 00_투자판단에서 결과 확인. 파란 숫자는 입력, 적용 행은 자동 계산입니다. 1~3년차는 시작월부터 12개월씩이며 출시 후 경과연도가 아닙니다. 확정 실적·견적이 없는 숫자는 기존 시험값을 유지했습니다.
C8: 가정 항목 | D8: 구분 | E8: 단위 | F8: 1년차 | G8: 2년차 | H8: 3년차 | J8: 뜻 · 기존 숫자의 근거 · 수정 기준
C10: 본체 실결제가 | D10: 적용 | E10: 원 | F10: =IF(CHOOSE($F$4,COUNT(F11),COUNT(F12),COUNT(F13))=0,"미입력",CHOOSE($F$4,F11,F12,F13)) -> 129000 | G10: =IF(CHOOSE($F$4,COUNT(G11),COUNT(G12),COUNT(G13))=0,"미입력",CHOOSE($F$4,G11,G12,G13)) -> 129000 | H10: =IF(CHOOSE($F$4,COUNT(H11),COUNT(H12),COUNT(H13))=0,"미입력",CHOOSE($F$4,H11,H12,H13)) -> 129000 | J10: 고객이 본체 키트 1개에 실제 결제하는 금액(VAT 포함). 기준 149,000원은 종전 모델 S05의 시험값이며 가격조사 결과가 아닙니다. 보수는 할인 판매, 확장은 높은 가격 수용을 가정합니다. 실제 할인 후 판매가로 교체하세요. A01
D11: 보수 | F11: 129000 | G11: 129000 | H11: 129000
D12: 기준 | F12: 149000 | G12: 149000 | H12: 149000
D13: 확장 | F13: 169000 | G13: 169000 | H13: 169000
C14: 완제품 키트 제조원가 | D14: 적용 | E14: 원 | F14: =IF(CHOOSE($F$4,COUNT(F15),COUNT(F16),COUNT(F17))=0,"미입력",CHOOSE($F$4,F15,F16,F17)) -> 70000 | G14: =IF(CHOOSE($F$4,COUNT(G15),COUNT(G16),COUNT(G17))=0,"미입력",CHOOSE($F$4,G15,G16,G17)) -> 65000 | H14: =IF(CHOOSE($F$4,COUNT(H15),COUNT(H16),COUNT(H17))=0,"미입력",CHOOSE($F$4,H15,H16,H17)) -> 60000 | J14: 본체 1개+동봉 패치 12개의 제조·포장 원가(VAT 제외). 55,000→50,000→46,000원은 양산 효율 개선을 미리 넣은 가정이며 견적이 없습니다. 원가 하락이 확인되지 않으면 2·3년차도 같은 금액으로 두세요. A02
D15: 보수 | F15: 70000 | G15: 65000 | H15: 60000
D16: 기준 | F16: 55000 | G16: 50000 | H16: 46000
D17: 확장 | F17: 45000 | G17: 40000 | H17: 37000
C18: 유료 유입 클릭당 비용 | D18: 적용 | E18: 원 | F18: =IF(CHOOSE($F$4,COUNT(F19),COUNT(F20),COUNT(F21))=0,"미입력",CHOOSE($F$4,F19,F20,F21)) -> 1200 | G18: =IF(CHOOSE($F$4,COUNT(G19),COUNT(G20),COUNT(G21))=0,"미입력",CHOOSE($F$4,G19,G20,G21)) -> 1100 | H18: =IF(CHOOSE($F$4,COUNT(H19),COUNT(H20),COUNT(H21))=0,"미입력",CHOOSE($F$4,H19,H20,H21)) -> 1000 | J18: 광고로 방문 1회를 얻는 비용(CPC). 기준 900원은 광고 실적이 없는 시험값입니다. 광고비÷유효 클릭수로 확인하세요. 800원·750원으로 내려가는 것은 광고 효율이 개선된다는 추가 가정입니다. A03
D19: 보수 | F19: 1200 | G19: 1100 | H19: 1000
D20: 기준 | F20: 900 | G20: 800 | H20: 750
D21: 확장 | F21: 700 | G21: 650 | H21: 600
C22: 유효 클릭의 출고 전환율 | D22: 적용 | E22: % | F22: =IF(CHOOSE($F$4,COUNT(F23),COUNT(F24),COUNT(F25))=0,"미입력",CHOOSE($F$4,F23,F24,F25)) -> 0.015 | G22: =IF(CHOOSE($F$4,COUNT(G23),COUNT(G24),COUNT(G25))=0,"미입력",CHOOSE($F$4,G23,G24,G25)) -> 0.018 | H22: =IF(CHOOSE($F$4,COUNT(H23),COUNT(H24),COUNT(H25))=0,"미입력",CHOOSE($F$4,H23,H24,H25)) -> 0.02 | J22: 방문 중 결제 후 실제 출고까지 이어지는 비율. 2.5%는 방문 1,000회당 출고 25건을 뜻합니다. 예약자 비율이 아닙니다. 현재 자연 유입에도 같은 비율을 적용합니다. 3.0%·3.5% 개선은 미검증입니다. A04
D23: 보수 | F23: 0.015 | G23: 0.018 | H23: 0.02
D24: 기준 | F24: 0.025 | G24: 0.03 | H24: 0.035
D25: 확장 | F25: 0.04 | G25: 0.045 | H25: 0.05
C26: 본체 DTC 전액 환불률 | D26: 적용 | E26: % | F26: =IF(CHOOSE($F$4,COUNT(F27),COUNT(F28),COUNT(F29))=0,"미입력",CHOOSE($F$4,F27,F28,F29)) -> 0.15 | G26: =IF(CHOOSE($F$4,COUNT(G27),COUNT(G28),COUNT(G29))=0,"미입력",CHOOSE($F$4,G27,G28,G29)) -> 0.12 | H26: =IF(CHOOSE($F$4,COUNT(H27),COUNT(H28),COUNT(H29))=0,"미입력",CHOOSE($F$4,H27,H28,H29)) -> 0.1 | J26: 출고한 본체 중 전액 환불되는 비율. 8%이면 100대 출고 중 8대 환불을 예상합니다. 환불된 제품의 제조원가·배송비도 이미 발생한 비용이며 회수품 재판매 수입은 0으로 둡니다. 동일 출고집단의 실적으로 교체하세요. A05
D27: 보수 | F27: 0.15 | G27: 0.12 | H27: 0.1
D28: 기준 | F28: 0.08 | G28: 0.07 | H28: 0.06
D29: 확장 | F29: 0.05 | G29: 0.04 | H29: 0.03
C30: 첫 리필 유료 참여율 | D30: 적용 | E30: % | F30: =IF(CHOOSE($F$4,COUNT(F31),COUNT(F32),COUNT(F33))=0,"미입력",CHOOSE($F$4,F31,F32,F33)) -> 0.1 | G30: =IF(CHOOSE($F$4,COUNT(G31),COUNT(G32),COUNT(G33))=0,"미입력",CHOOSE($F$4,G31,G32,G33)) -> 0.12 | H30: =IF(CHOOSE($F$4,COUNT(H31),COUNT(H32),COUNT(H33))=0,"미입력",CHOOSE($F$4,H31,H32,H33)) -> 0.15 | J30: 환불하지 않은 본체 고객 중 다음 달 처음 리필을 유료 구매하는 비율. 25%는 고객 100명 중 25명입니다. 구독 계약이나 확정 매출이 아닙니다. 구매 후 한 달을 지난 고객의 첫 리필 구매율로 확인하세요. A06
D31: 보수 | F31: 0.1 | G31: 0.12 | H31: 0.15
D32: 기준 | F32: 0.25 | G32: 0.3 | H32: 0.35
D33: 확장 | F33: 0.4 | G33: 0.45 | H33: 0.5
C34: 리필 구매자 월 유지율 | D34: 적용 | E34: % | F34: =IF(CHOOSE($F$4,COUNT(F35),COUNT(F36),COUNT(F37))=0,"미입력",CHOOSE($F$4,F35,F36,F37)) -> 0.75 | G34: =IF(CHOOSE($F$4,COUNT(G35),COUNT(G36),COUNT(G37))=0,"미입력",CHOOSE($F$4,G35,G36,G37)) -> 0.78 | H34: =IF(CHOOSE($F$4,COUNT(H35),COUNT(H36),COUNT(H37))=0,"미입력",CHOOSE($F$4,H35,H36,H37)) -> 0.8 | J34: 지난달 리필을 산 사람이 이번 달에도 사는 비율. 90%이면 100명→90명→81명으로 줄어듭니다. 모든 본체 고객의 90%가 매달 산다는 뜻이 아닙니다. 구매 간격이 한 달보다 길면 이 모델의 월 반복구매 가정을 재검토하세요. A07
D35: 보수 | F35: 0.75 | G35: 0.78 | H35: 0.8
D36: 기준 | F36: 0.9 | G36: 0.91 | H36: 0.92
D37: 확장 | F37: 0.94 | G37: 0.95 | H37: 0.96
C38: 성숙 월 자연 유입 | D38: 적용 | E38: 명 | F38: =IF(CHOOSE($F$4,COUNT(F39),COUNT(F40),COUNT(F41))=0,"미입력",CHOOSE($F$4,F39,F40,F41)) -> 500 | G38: =IF(CHOOSE($F$4,COUNT(G39),COUNT(G40),COUNT(G41))=0,"미입력",CHOOSE($F$4,G39,G40,G41)) -> 1000 | H38: =IF(CHOOSE($F$4,COUNT(H39),COUNT(H40),COUNT(H41))=0,"미입력",CHOOSE($F$4,H39,H40,H41)) -> 2000 | J38: 광고 외 검색·콘텐츠·추천으로 오는 월 방문 수. 기준 1,000→3,000→5,000회는 유입 확대 계획이며 관측값이 아닙니다. 출시 첫 달 50%, 둘째 달 75%만 적용합니다. 콘텐츠 인건비·운영비는 별도 지출입니다. A08
D39: 보수 | F39: 500 | G39: 1000 | H39: 2000
D40: 기준 | F40: 1000 | G40: 3000 | H40: 5000
D41: 확장 | F41: 1500 | G41: 5000 | H41: 10000
C42: 성숙 월 광고비 | D42: 적용 | E42: 원 | F42: =IF(CHOOSE($F$4,COUNT(F43),COUNT(F44),COUNT(F45))=0,"미입력",CHOOSE($F$4,F43,F44,F45)) -> 1500000 | G42: =IF(CHOOSE($F$4,COUNT(G43),COUNT(G44),COUNT(G45))=0,"미입력",CHOOSE($F$4,G43,G44,G45)) -> 3000000 | H42: =IF(CHOOSE($F$4,COUNT(H43),COUNT(H44),COUNT(H45))=0,"미입력",CHOOSE($F$4,H43,H44,H45)) -> 5000000 | J42: 판매가 안정된 달에 쓸 광고비. 기준 월 200만→600만→1,200만원은 예산 확대 계획입니다. 첫 출시월 50%, 다음 달 75%, 이후 100% 집행. 광고비÷CPC×전환율로 유료 출고를 계산하므로 판매량을 보장하지 않습니다. A09
D43: 보수 | F43: 1500000 | G43: 3000000 | H43: 5000000
D44: 기준 | F44: 2000000 | G44: 6000000 | H44: 12000000
D45: 확장 | F45: 3000000 | G45: 10000000 | H45: 25000000
C46: 첫 출시월 번호 | D46: 적용 | E46: 월 | F46: =IF(CHOOSE($F$4,COUNT(F47),COUNT(F48),COUNT(F49))=0,"미입력",CHOOSE($F$4,F47,F48,F49)) -> 10 | G46: =IF(CHOOSE($F$4,COUNT(G47),COUNT(G48),COUNT(G49))=0,"미입력",CHOOSE($F$4,G47,G48,G49)) -> 10 | H46: =IF(CHOOSE($F$4,COUNT(H47),COUNT(H48),COUNT(H49))=0,"미입력",CHOOSE($F$4,H47,H48,H49)) -> 10 | J46: 시작월을 1로 세었을 때 처음 판매하는 달. 시작월 2027년 1월, 입력 7이면 2027년 7월 출시입니다. 보수 10 / 기준 7 / 확장 5는 일정 가정입니다. F열만 수정하며 G·H는 연결값입니다. 개발·인허가 완료를 확인하세요. A10
D47: 보수 | F47: 10 | G47: =F47 -> 10 | H47: =F47 -> 10
D48: 기준 | F48: 7 | G48: =F48 -> 7 | H48: =F48 -> 7
D49: 확장 | F49: 5 | G49: =F49 -> 5 | H49: =F49 -> 5
C50: 리테일 성숙 월 잠재 출고 | D50: 적용 | E50: 개 | F50: =IF(CHOOSE($F$4,COUNT(F51),COUNT(F52),COUNT(F53))=0,"미입력",CHOOSE($F$4,F51,F52,F53)) -> 0 | G50: =IF(CHOOSE($F$4,COUNT(G51),COUNT(G52),COUNT(G53))=0,"미입력",CHOOSE($F$4,G51,G52,G53)) -> 0 | H50: =IF(CHOOSE($F$4,COUNT(H51),COUNT(H52),COUNT(H53))=0,"미입력",CHOOSE($F$4,H51,H52,H53)) -> 100 | J50: 매장·유통사에 월 납품할 잠재 수량. 아래 F95가 0이면 이 숫자가 있어도 출고·매출은 0입니다. F95=1일 때만 초기 집행 비중을 곱해 반영합니다. 계약 전 수량은 판매 확정치가 아닙니다. A11
D51: 보수 | F51: 0 | G51: 0 | H51: 100
D52: 기준 | F52: 0 | G52: 100 | H52: 300
D53: 확장 | F53: 0 | G53: 200 | H53: 800
C54: 리테일 공급가 비율 | D54: 적용 | E54: % | F54: =IF(CHOOSE($F$4,COUNT(F55),COUNT(F56),COUNT(F57))=0,"미입력",CHOOSE($F$4,F55,F56,F57)) -> 0.55 | G54: =IF(CHOOSE($F$4,COUNT(G55),COUNT(G56),COUNT(G57))=0,"미입력",CHOOSE($F$4,G55,G56,G57)) -> 0.55 | H54: =IF(CHOOSE($F$4,COUNT(H55),COUNT(H56),COUNT(H57))=0,"미입력",CHOOSE($F$4,H55,H56,H57)) -> 0.55 | J54: VAT 제외 본체 판매가 중 당사가 납품 대금으로 받는 비율. 기준 60%이면 149,000÷1.1×60%=약 81,273원입니다. 매장 소비자가를 당사 매출로 잡지 않습니다. 유통 계약의 실제 공급가로 확인하세요. A12
D55: 보수 | F55: 0.55 | G55: 0.55 | H55: 0.55
D56: 기준 | F56: 0.6 | G56: 0.6 | H56: 0.6
D57: 확장 | F57: 0.65 | G57: 0.65 | H57: 0.65
C58: 경제적 인력 규모 | D58: 적용 | E58: 명 | F58: =IF(CHOOSE($F$4,COUNT(F59),COUNT(F60),COUNT(F61))=0,"미입력",CHOOSE($F$4,F59,F60,F61)) -> 3 | G58: =IF(CHOOSE($F$4,COUNT(G59),COUNT(G60),COUNT(G61))=0,"미입력",CHOOSE($F$4,G59,G60,G61)) -> 3 | H58: =IF(CHOOSE($F$4,COUNT(H59),COUNT(H60),COUNT(H61))=0,"미입력",CHOOSE($F$4,H59,H60,H61)) -> 3 | J58: 사업에 투입할 인원 수. 기준 3명·3명·4명은 채용 계획이지 확정 인원이 아닙니다. 판매 전 준비기간에도 매달 인건비를 계산합니다. 실제 전담 인원과 투입 계획으로 바꾸세요. A13
D59: 보수 | F59: 3 | G59: 3 | H59: 3
D60: 기준 | F60: 3 | G60: 3 | H60: 4
D61: 확장 | F61: 3 | G61: 4 | H61: 6
C62: 인당 월 총인건비 | D62: 적용 | E62: 원 | F62: =IF(CHOOSE($F$4,COUNT(F63),COUNT(F64),COUNT(F65))=0,"미입력",CHOOSE($F$4,F63,F64,F65)) -> 4500000 | G62: =IF(CHOOSE($F$4,COUNT(G63),COUNT(G64),COUNT(G65))=0,"미입력",CHOOSE($F$4,G63,G64,G65)) -> 4700000 | H62: =IF(CHOOSE($F$4,COUNT(H63),COUNT(H64),COUNT(H65))=0,"미입력",CHOOSE($F$4,H63,H64,H65)) -> 5000000 | J62: 1명에게 한 달 동안 드는 회사 총인건비. 450만·470만·500만원은 급여 실측이 아닌 계획값입니다. 3명×450만원=월 1,350만원입니다. 회사가 지원해도 손익에는 전액, 현금에는 F107의 지원 비율을 반영합니다. A14
D63: 보수 | F63: 4500000 | G63: 4700000 | H63: 5000000
D64: 기준 | F64: 4500000 | G64: 4700000 | H64: 5000000
D65: 확장 | F65: 4500000 | G65: 4700000 | H65: 5000000
C66: 월 고정 운영비 | D66: 적용 | E66: 원 | F66: =IF(CHOOSE($F$4,COUNT(F67),COUNT(F68),COUNT(F69))=0,"미입력",CHOOSE($F$4,F67,F68,F69)) -> 2000000 | G66: =IF(CHOOSE($F$4,COUNT(G67),COUNT(G68),COUNT(G69))=0,"미입력",CHOOSE($F$4,G67,G68,G69)) -> 2500000 | H66: =IF(CHOOSE($F$4,COUNT(H67),COUNT(H68),COUNT(H69))=0,"미입력",CHOOSE($F$4,H67,H68,H69)) -> 3000000 | J66: 판매량과 별개로 매달 발생하는 공간·시스템·회계·콘텐츠 등 비용. 기준 월 200만·300만·400만원은 예산입니다. 광고비·배송비·인건비·R&D는 별도이므로 중복 포함하지 마세요. 실제 항목별 예산 합계로 교체하세요. A15
D67: 보수 | F67: 2000000 | G67: 2500000 | H67: 3000000
D68: 기준 | F68: 2000000 | G68: 3000000 | H68: 4000000
D69: 확장 | F69: 2000000 | G69: 4000000 | H69: 6000000
C70: 리필 24개팩 실결제가 | D70: 적용 | E70: 원 | F70: =IF(CHOOSE($F$4,COUNT(F71),COUNT(F72),COUNT(F73))=0,"미입력",CHOOSE($F$4,F71,F72,F73)) -> 9900 | G70: =IF(CHOOSE($F$4,COUNT(G71),COUNT(G72),COUNT(G73))=0,"미입력",CHOOSE($F$4,G71,G72,G73)) -> 9900 | H70: =IF(CHOOSE($F$4,COUNT(H71),COUNT(H72),COUNT(H73))=0,"미입력",CHOOSE($F$4,H71,H72,H73)) -> 9900 | J70: 리필 한 팩(24개)에 고객이 실제 결제하는 가격(VAT 포함). 기준 12,900원은 검증 전 가격입니다. 한쪽 발목에 3개 사용하면 8회분입니다. 실제 사용 빈도·재사용 여부가 월 구매를 뒷받침하는지 확인해야 합니다. A16
D71: 보수 | F71: 9900 | G71: 9900 | H71: 9900
D72: 기준 | F72: 12900 | G72: 12900 | H72: 12900
D73: 확장 | F73: 14900 | G73: 14900 | H73: 14900
C74: 리필 24개팩 원가 | D74: 적용 | E74: 원 | F74: =IF(CHOOSE($F$4,COUNT(F75),COUNT(F76),COUNT(F77))=0,"미입력",CHOOSE($F$4,F75,F76,F77)) -> 4500 | G74: =IF(CHOOSE($F$4,COUNT(G75),COUNT(G76),COUNT(G77))=0,"미입력",CHOOSE($F$4,G75,G76,G77)) -> 4300 | H74: =IF(CHOOSE($F$4,COUNT(H75),COUNT(H76),COUNT(H77))=0,"미입력",CHOOSE($F$4,H75,H76,H77)) -> 4000 | J74: 리필 한 팩의 제조·포장 원가(VAT 제외). 기준 3,500→3,200→3,000원은 미확인 견적 가정이며 배송비 3,000원은 별도입니다. 실제 공급 견적과 패치·볼 재사용 정책을 확정한 뒤 수정하세요. A17
D75: 보수 | F75: 4500 | G75: 4300 | H75: 4000
D76: 기준 | F76: 3500 | G76: 3200 | H76: 3000
D77: 확장 | F77: 2800 | G77: 2500 | H77: 2300
C80: 공통 입력 · 선택한 시나리오와 관계없이 적용
C82: 직접 정하거나 확인할 조건 | D82: 단위 | F82: 값 | J82: 입력 의미와 확인할 자료
C83: 아래 값도 확정 계약·실적이 없는 기존 가정입니다. 금액은 별도 표시가 없으면 VAT 제외 비용입니다. 0과 빈칸은 다릅니다. 리테일 0=매출 제외, 회사 인건비 부담률 0%=사업이 전액 부담. 숫자를 낮춰 수익을 맞추기보다 견적·계약·실측으로 교체하세요.
C85: VAT 계산율 | D85: % | F85: 0.1 | J85: 매출·과세 매입의 세액 계산 비율. 현재 10% 단순 가정이며 실제 거래별 과세·공제 여부는 별도 확인해야 합니다.
C86: DTC 결제 수수료율 | D86: % | F86: 0.033 | J86: 환불 후 고객 결제액 대비 VAT 포함 결제 수수료율 가정. 환불 수수료도 반환된다고 봅니다. 실제 결제대행사 정산 조건으로 확인하세요.
C87: 본체 출고 물류비 | D87: 원 | F87: 4500 | J87: 본체 1대 출고 때 드는 포장·배송 등 비용. 환불돼도 최초 배송비는 발생합니다. 물류 견적으로 교체하세요.
C88: 반품 회수 처리비 | D88: 원 | F88: 6000 | J88: 반품 1건의 회수·검수·처리 비용. 환불률 8%일 때 출고 1대당 기대비용은 6,000×8%=480원입니다.
C89: 본체 출고당 AS 기대비용 | D89: 원 | F89: 2000 | J89: 출고 1대당 평균 수리·보증 비용. 예: AS 발생률 5%×건당 40,000원=2,000원. 예시는 산식 설명이며 실제 근거가 아닙니다.
C90: 본체 출고당 변동 상담비 | D90: 원 | F90: 1000 | J90: 본체 출고 1대에 추가로 드는 고객 상담 비용. 고정 인건비에 같은 업무를 이미 포함했다면 중복 여부를 확인하세요.
C91: 리필 주문당 배송비 | D91: 원 | F91: 3000 | J91: 리필 주문 1건 배송비. 현재 주문당 1팩·판매자 부담을 가정합니다. 묶음배송이나 고객 부담 배송비는 별도 반영하지 않습니다.
C92: 리필 결제 수수료율 | D92: % | F92: 0.033 | J92: 리필 결제액의 수수료율. F86과 같은 VAT 포함·환불 시 반환 가정입니다. 본체와 리필의 실제 정산 수수료를 확인하세요.
C93: 리필 환불률 | D93: % | F93: 0.02 | J93: 리필 출고 중 환불 비율. 100팩 중 2팩 환불 가정. 제품 원가·배송비는 남고, 회수 처리비가 추가됩니다.
C94: 리필 구매자당 월 주문 | D94: 팩 | F94: 1 | J94: 당월 리필 구매자 1명이 사는 팩 수. 현재 1명×1팩=1주문으로 처리합니다. 고객 전체가 매월 1팩을 산다는 뜻은 아닙니다.
C95: 리테일 계약 가정 적용 | D95: 0 또는 1 | F95: 0 | J95: 0=매장 납품 출고·매출 제외 / 1=위 리테일 잠재 수량 적용. 계약 확인 전에는 0을 유지하세요.
C96: 리테일 대금 회수 지연 | D96: 개월 | F96: 2 | J96: 납품 후 대금이 들어오기까지 개월 수. 2이면 7월 납품 대금을 9월에 받습니다. 실제 유통사 정산 계약으로 확인하세요.
... C107: 회사 인건비 현금 부담률 | D107: % | F107: 0 | J107: 인건비 중 모회사가 사업 밖에서 대신 부담하는 비율. 0%=사업 전액 부담, 100%=사업 현금지출 0. 손익상 인건비는 유지합니다.
C108: 추가 R&D 월 비용 | D108: 원 | F108: 15000000 | G108: 1500000 | H108: 1500000 | J108: F열은 1년차 M4~M6에 매월 집행, G·H열은 2·3년차 매월 집행합니다. 100일 검증비·금형 투자와 별도인 추가 개발비입니다.
C109: 100일 검증 예산 | D109: 원 | F109: =SUM('05_100일검증'!F8:F17) -> 10000000 | J109: 05_100일검증의 항목별 합계를 자동 연결합니다. 바꾸려면 해당 탭의 수량·단가를 수정하세요. F109는 직접 입력하지 않습니다.
C110: 잠재 적합고객 모수 가정 | D110: 명 | F110: 1000000 | J110: 시장 규모를 시험 계산하기 위한 잠재 고객 수. 100만명은 통계로 확인된 값이 아닙니다. 월별 판매량을 제한하지도 않습니다.
C111: 문제 및 사용상황 적합률 | D111: % | F111: 0.2 | J111: 잠재 고객 중 문제·사용 상황이 맞는 비율. 20%는 고객조사 전 가정입니다. 06_시장경쟁의 조건부 시장규모에만 사용합니다.
C112: 적합군의 유료 수용률 | D112: % | F112: 0.3 | J112: 적합 고객 중 유료 구매를 수용할 비율. 30%는 검증 전 가정입니다. 온라인 방문→출고 전환율(F22)과는 다른 모집단입니다.
C113: 연간 신규 도입률 | D113: % | F113: 0.1 | J113: 조건부 시장 고객 중 한 해 신규 구매하는 비율. 10%는 시장규모 참고값이며 월별 매출에 직접 곱하지 않습니다.
C114: 본체 교체주기 참고 | D114: 년 | F114: 3 | J114: 본체 교체 시점에 대한 참고 입력. 현재 36개월 매출에는 교체구매를 자동으로 더하지 않습니다. 실제 제품 수명은 미확정입니다.
C115: 본체 CM2 관리 목표 | D115: 원 | F115: 20000 | J115: 본체 1대에서 광고비까지 뺀 뒤 남기려는 금액. 2만원은 내부 목표입니다. 인건비·고정비를 뺀 최종 순이익이 아닙니다.
C116: 키트 동봉 패치 수 | D116: 개 | F116: 12 | J116: 본체 키트에 넣을 패치 개수. 원가 견적의 구성 확인용이며 숫자를 바꿔도 제조원가는 자동 변경되지 않습니다.
C117: 리필 1팩 패치 수 | D117: 개 | F117: 24 | J117: 리필 1팩의 패치 개수. 구성 참고값입니다. 변경하면 리필 판매가·원가·월 주문량도 별도로 검토해야 합니다.
C118: 한쪽 발목 1회 패치 수 | D118: 개 | F118: 3 | J118: 한쪽 발목에 한 번 사용할 패치 수. 24개÷3개=8회분. 양쪽 동시 사용·재사용 여부에 따라 실제 소모량이 달라집니다.
...

Sheet 02_단위경제
C2: 본체와 리필에서 실제로 남는 금액
C4: 선택 시나리오 | F4: ='01_가정'!H4 -> 보수
C6: 지표 | D6: 단위 | F6: 1년차 | G6: 2년차 | H6: 3년차
C7: DTC 본체 한 대 기준
C8: DTC 실결제가 | D8: 원 | F8: ='01_가정'!F10 -> 129000 | G8: ='01_가정'!G10 -> 129000 | H8: ='01_가정'!H10 -> 129000
C9: 환불 전 VAT 제외 매출 | D9: 원 | F9: =F8/(1+'01_가정'!$F$85) -> 117272.73 | G9: =G8/(1+'01_가정'!$F$85) -> 117272.73 | H9: =H8/(1+'01_가정'!$F$85) -> 117272.73
C10: 비환불 비율 | D10: % | F10: =1-'01_가정'!F26 -> 0.85 | G10: =1-'01_가정'!G26 -> 0.88 | H10: =1-'01_가정'!H26 -> 0.9
C11: 출고당 순매출 | D11: 원 | F11: =F9*F10 -> 99681.818 | G11: =G9*G10 -> 103200 | H11: =H9*H10 -> 105545.45
C12: 완제품 키트 원가 | D12: 원 | F12: ='01_가정'!F14 -> 70000 | G12: ='01_가정'!G14 -> 65000 | H12: ='01_가정'!H14 -> 60000
C13: 결제 수수료 | D13: 원 | F13: =F11*'01_가정'!$F$86 -> 3289.5 | G13: =G11*'01_가정'!$F$86 -> 3405.6 | H13: =H11*'01_가정'!$F$86 -> 3483
C14: 출고 물류비 | D14: 원 | F14: ='01_가정'!$F$87 -> 4500 | G14: ='01_가정'!$F$87 -> 4500 | H14: ='01_가정'!$F$87 -> 4500
C15: 기대 반품 처리비 | D15: 원 | F15: =(1-F10)*'01_가정'!$F$88 -> 900 | G15: =(1-G10)*'01_가정'!$F$88 -> 720 | H15: =(1-H10)*'01_가정'!$F$88 -> 600
C16: AS 기대비용 | D16: 원 | F16: ='01_가정'!$F$89 -> 2000 | G16: ='01_가정'!$F$89 -> 2000 | H16: ='01_가정'!$F$89 -> 2000
C17: 변동 상담비 | D17: 원 | F17: ='01_가정'!$F$90 -> 1000 | G17: ='01_가정'!$F$90 -> 1000 | H17: ='01_가정'!$F$90 -> 1000
C18: 광고 전 공헌이익 CM1 | D18: 원 | F18: =F11-SUM(F12:F17) -> 17992.318 | G18: =G11-SUM(G12:G17) -> 26574.4 | H18: =H11-SUM(H12:H17) -> 33962.455
C19: 유료 신규 출고 CAC | D19: 원 | F19: =IF('01_가정'!F22>0,'01_가정'!F18/'01_가정'!F22,"n.a.") -> 80000 | G19: =IF('01_가정'!G22>0,'01_가정'!G18/'01_가정'!G22,"n.a.") -> 61111.111 | H19: =IF('01_가정'!H22>0,'01_가정'!H18/'01_가정'!H22,"n.a.") -> 50000
C20: 광고 후 공헌이익 CM2 | D20: 원 | F20: =IF(ISNUMBER(F19),F18-F19,"n.a.") -> -62007.682 | G20: =IF(ISNUMBER(G19),G18-G19,"n.a.") -> -34536.711 | H20: =IF(ISNUMBER(H19),H18-H19,"n.a.") -> -16037.545
C21: CM2 순매출 비율 | D21: % | F21: =IF(AND(ISNUMBER(F20),F11>0),F20/F11,"n.a.") -> -0.62205609 | G21: =IF(AND(ISNUMBER(G20),G11>0),G20/G11,"n.a.") -> -0.33465805 | H21: =IF(AND(ISNUMBER(H20),H11>0),H20/H11,"n.a.") -> -0.15194918
C22: CM2 관리 목표 | D22: 원 | F22: ='01_가정'!$F$115 -> 20000 | G22: ='01_가정'!$F$115 -> 20000 | H22: ='01_가정'!$F$115 -> 20000
C23: 허용 가능한 CAC | D23: 원 | F23: =F18-F22 -> -2007.6818 | G23: =G18-G22 -> 6574.4 | H23: =H18-H22 -> 13962.455
C24: 목표 CM2에 필요한 전환율 | D24: % | F24: =IF(F23>0,'01_가정'!F18/F23,"n.a.") -> n.a. | G24: =IF(G23>0,'01_가정'!G18/G23,"n.a.") -> 0.16731565 | H24: =IF(H23>0,'01_가정'!H18/H23,"n.a.") -> 0.071620645
C25: 월 고정 인건비와 운영비 | D25: 원 | F25: ='01_가정'!F58*'01_가정'!F62+'01_가정'!F66 -> 15500000 | G25: ='01_가정'!G58*'01_가정'!G62+'01_가정'!G66 -> 16600000 | H25: ='01_가정'!H58*'01_가정'!H62+'01_가정'!H66 -> 18000000
C26: 인건비·운영비 회수 출고량 | D26: 개 | F26: =IF(AND(ISNUMBER(F20),F20>0),ROUNDUP(F25/F20,0),"n.a.") -> n.a. | G26: =IF(AND(ISNUMBER(G20),G20>0),ROUNDUP(G25/G20,0),"n.a.") -> n.a. | H26: =IF(AND(ISNUMBER(H20),H20>0),ROUNDUP(H25/H20,0),"n.a.") -> n.a.
C29: 납품 채널은 공급가로 매출 인식
C30: 리테일 VAT 제외 공급가 | D30: 원 | F30: ='01_가정'!F10/(1+'01_가정'!$F$85)*'01_가정'!F54 -> 64500 | G30: ='01_가정'!G10/(1+'01_가정'!$F$85)*'01_가정'!G54 -> 64500 | H30: ='01_가정'!H10/(1+'01_가정'!$F$85)*'01_가정'!H54 -> 64500
C31: 리테일 비반품 비율 | D31: % | F31: =1-'01_가정'!$F$98 -> 0.97 | G31: =1-'01_가정'!$F$98 -> 0.97 | H31: =1-'01_가정'!$F$98 -> 0.97
C32: 리테일 출고당 순매출 | D32: 원 | F32: =F30*F31 -> 62565 | G32: =G30*G31 -> 62565 | H32: =H30*H31 -> 62565
C33: 리테일 제품 원가 | D33: 원 | F33: ='01_가정'!F14 -> 70000 | G33: ='01_가정'!G14 -> 65000 | H33: ='01_가정'!H14 -> 60000
C34: 리테일 물류비 | D34: 원 | F34: ='01_가정'!$F$97 -> 2000 | G34: ='01_가정'!$F$97 -> 2000 | H34: ='01_가정'!$F$97 -> 2000
C35: 리테일 기대 반품 처리비 | D35: 원 | F35: =(1-F31)*'01_가정'!$F$88 -> 180 | G35: =(1-G31)*'01_가정'!$F$88 -> 180 | H35: =(1-H31)*'01_가정'!$F$88 -> 180
C36: 리테일 AS 기대비용 | D36: 원 | F36: ='01_가정'!$F$89 -> 2000 | G36: ='01_가정'!$F$89 -> 2000 | H36: ='01_가정'!$F$89 -> 2000
C37: 리테일 상담비 | D37: 원 | F37: ='01_가정'!$F$90 -> 1000 | G37: ='01_가정'!$F$90 -> 1000 | H37: ='01_가정'!$F$90 -> 1000
C38: 리테일 출고당 공헌이익 | D38: 원 | F38: =F32-SUM(F33:F37) -> -12615 | G38: =G32-SUM(G33:G37) -> -7615 | H38: =H32-SUM(H33:H37) -> -2615
C42: 리필은 실제 유료 재구매만 반영
C43: 리필 24개팩 실결제가 | D43: 원 | F43: ='01_가정'!F70 -> 9900 | G43: ='01_가정'!G70 -> 9900 | H43: ='01_가정'!H70 -> 9900
C44: 리필 주문당 순매출 | D44: 원 | F44: =F43/(1+'01_가정'!$F$85)*(1-'01_가정'!$F$93) -> 8820 | G44: =G43/(1+'01_가정'!$F$85)*(1-'01_가정'!$F$93) -> 8820 | H44: =H43/(1+'01_가정'!$F$85)*(1-'01_가정'!$F$93) -> 8820
C45: 리필 제품 원가 | D45: 원 | F45: ='01_가정'!F74 -> 4500 | G45: ='01_가정'!G74 -> 4300 | H45: ='01_가정'!H74 -> 4000
C46: 리필 결제 수수료 | D46: 원 | F46: =F44*'01_가정'!$F$92 -> 291.06 | G46: =G44*'01_가정'!$F$92 -> 291.06 | H46: =H44*'01_가정'!$F$92 -> 291.06
C47: 리필 출고 물류비 | D47: 원 | F47: ='01_가정'!$F$91 -> 3000 | G47: ='01_가정'!$F$91 -> 3000 | H47: ='01_가정'!$F$91 -> 3000
C48: 리필 반품 처리 기대비용 | D48: 원 | F48: ='01_가정'!$F$93*'01_가정'!$F$88 -> 120 | G48: ='01_가정'!$F$93*'01_가정'!$F$88 -> 120 | H48: ='01_가정'!$F$93*'01_가정'!$F$88 -> 120
C49: 리필 주문당 공헌이익 | D49: 원 | F49: =F44-SUM(F45:F48) -> 908.94 | G49: =G44-SUM(G45:G48) -> 1108.94 | H49: =H44-SUM(H45:H48) -> 1408.94
C50: 첫 리필 참여율 | D50: % | F50: ='01_가정'!F30 -> 0.1 | G50: ='01_가정'!G30 -> 0.12 | H50: ='01_가정'!H30 -> 0.15
C51: 월 리필 유지율 | D51: % | F51: ='01_가정'!F34 -> 0.75 | G51: ='01_가정'!G34 -> 0.78 | H51: ='01_가정'!H34 -> 0.8
C52: 첫 출고당 12개월 리필 주문 | D52: 팩 | F52: =F10*F50*'01_가정'!$F$94*IF(F51=1,11,(1-F51^11)/(1-F51)) -> 0.32564005 | G52: =G10*G50*'01_가정'!$F$94*IF(G51=1,11,(1-G51^11)/(1-G51)) -> 0.44879086 | H52: =H10*H50*'01_가정'!$F$94*IF(H51=1,11,(1-H51^11)/(1-H51)) -> 0.61701794
C53: 12개월 추가 리필 공헌이익 | D53: 원 | F53: =F52*F49 -> 295.98727 | G53: =G52*G49 -> 497.68213 | H53: =H52*H49 -> 869.34126
C54: 12개월 광고 전 공헌이익 | D54: 원 | F54: =F18+F53 -> 18288.305 | G54: =G18+G53 -> 27072.082 | H54: =H18+H53 -> 34831.796
C55: 12개월 광고 후 공헌이익 | D55: 원 | F55: =IF(ISNUMBER(F19),F54-F19,"n.a.") -> -61711.695 | G55: =IF(ISNUMBER(G19),G54-G19,"n.a.") -> -34039.029 | H55: =IF(ISNUMBER(H19),H54-H19,"n.a.") -> -15168.204
C56: 12개월 광고 전 이익 대 CAC | D56: 배 | F56: =IF(AND(ISNUMBER(F19),F19>0),F54/F19,"n.a.") -> 0.22860382 | G56: =IF(AND(ISNUMBER(G19),G19>0),G54/G19,"n.a.") -> 0.44299771 | H56: =IF(AND(ISNUMBER(H19),H19>0),H54/H19,"n.a.") -> 0.69663592
C59: CM2는 고정비 차감 전입니다. 본체 원가와 반품 손실을 모두 반영했습니다. 리필 12개월 계산은 첫 구매 다음 달부터 11회 기회를 가정한 유한 기간 계산입니다.
C61: 손익분기 출고량은 리필과 자연 유입을 제외한 유료 유입만의 보수적 참고선이며, R&D와 감가상각은 추가 회수가 필요합니다.

Sheet 03_월별손익
C2: 고객 유입에서 계산한 36개월 손익
C4: 선택 시나리오 | F4: ='01_가정'!H4 -> 보수
F5: 1년차 | G5: 2년차 | H5: 3년차 | J5: =EDATE('01_가정'!$F$5,0) -> 46388 | K5: =EDATE('01_가정'!$F$5,1) -> 46419 | L5: =EDATE('01_가정'!$F$5,2) -> 46447 | M5: =EDATE('01_가정'!$F$5,3) -> 46478 | N5: =EDATE('01_가정'!$F$5,4) -> 46508 | O5: =EDATE('01_가정'!$F$5,5) -> 46539 | P5: =EDATE('01_가정'!$F$5,6) -> 46569 | Q5: =EDATE('01_가정'!$F$5,7) -> 46600 | R5: =EDATE('01_가정'!$F$5,8) -> 46631 | S5: =EDATE('01_가정'!$F$5,9) -> 46661 | T5: =EDATE('01_가정'!$F$5,10) -> 46692 | U5: =EDATE('01_가정'!$F$5,11) -> 46722 | V5: =EDATE('01_가정'!$F$5,12) -> 46753 | W5: =EDATE('01_가정'!$F$5,13) -> 46784 | X5: =EDATE('01_가정'!$F$5,14) -> 46813 | Y5: =EDATE('01_가정'!$F$5,15) -> 46844 | Z5: =EDATE('01_가정'!$F$5,16) -> 46874 | AA5: =EDATE('01_가정'!$F$5,17) -> 46905 | AB5: =EDATE('01_가정'!$F$5,18) -> 46935 | AC5: =EDATE('01_가정'!$F$5,19) -> 46966 | AD5: =EDATE('01_가정'!$F$5,20) -> 46997 | AE5: =EDATE('01_가정'!$F$5,21) -> 47027 | AF5: =EDATE('01_가정'!$F$5,22) -> 47058 | AG5: =EDATE('01_가정'!$F$5,23) -> 47088 | AH5: =EDATE('01_가정'!$F$5,24) -> 47119 | AI5: =EDATE('01_가정'!$F$5,25) -> 47150 | AJ5: =EDATE('01_가정'!$F$5,26) -> 47178 | AK5: =EDATE('01_가정'!$F$5,27) -> 47209 | AL5: =EDATE('01_가정'!$F$5,28) -> 47239 | AM5: =EDATE('01_가정'!$F$5,29) -> 47270 | AN5: =EDATE('01_가정'!$F$5,30) -> 47300 | AO5: =EDATE('01_가정'!$F$5,31) -> 47331 | AP5: =EDATE('01_가정'!$F$5,32) -> 47362 | AQ5: =EDATE('01_가정'!$F$5,33) -> 47392 | AR5: =EDATE('01_가정'!$F$5,34) -> 47423 | AS5: =EDATE('01_가정'!$F$5,35) -> 47453
J6: 1 | K6: 2 | L6: 3 | M6: 4 | N6: 5 | O6: 6 | P6: 7 | Q6: 8 | R6: 9 | S6: 10 | T6: 11 | U6: 12 | V6: 13 | W6: 14 | X6: 15 | Y6: 16 | Z6: 17 | AA6: 18 | AB6: 19 | AC6: 20 | AD6: 21 | AE6: 22 | AF6: 23 | AG6: 24 | AH6: 25 | AI6: 26 | AJ6: 27 | AK6: 28 | AL6: 29 | AM6: 30 | AN6: 31 | AO6: 32 | AP6: 33 | AQ6: 34 | AR6: 35 | AS6: 36
C8: 판매 가능 일정 가정 | D8: 0 또는 1 | J8: =IF(J$6>='01_가정'!F46,1,0) -> 0 | K8: =IF(K$6>='01_가정'!F46,1,0) -> 0 | L8: =IF(L$6>='01_가정'!F46,1,0) -> 0 | M8: =IF(M$6>='01_가정'!F46,1,0) -> 0 | N8: =IF(N$6>='01_가정'!F46,1,0) -> 0 | O8: =IF(O$6>='01_가정'!F46,1,0) -> 0 | P8: =IF(P$6>='01_가정'!F46,1,0) -> 0 | Q8: =IF(Q$6>='01_가정'!F46,1,0) -> 0 | R8: =IF(R$6>='01_가정'!F46,1,0) -> 0 | S8: =IF(S$6>='01_가정'!F46,1,0) -> 1 | T8: =IF(T$6>='01_가정'!F46,1,0) -> 1 | U8: =IF(U$6>='01_가정'!F46,1,0) -> 1 | V8: =IF(V$6>='01_가정'!F46,1,0) -> 1 | W8: =IF(W$6>='01_가정'!F46,1,0) -> 1 | X8: =IF(X$6>='01_가정'!F46,1,0) -> 1 | Y8: =IF(Y$6>='01_가정'!F46,1,0) -> 1 | Z8: =IF(Z$6>='01_가정'!F46,1,0) -> 1 | AA8: =IF(AA$6>='01_가정'!F46,1,0) -> 1 | AB8: =IF(AB$6>='01_가정'!F46,1,0) -> 1 | AC8: =IF(AC$6>='01_가정'!F46,1,0) -> 1 | AD8: =IF(AD$6>='01_가정'!F46,1,0) -> 1 | AE8: =IF(AE$6>='01_가정'!F46,1,0) -> 1 | AF8: =IF(AF$6>='01_가정'!F46,1,0) -> 1 | AG8: =IF(AG$6>='01_가정'!F46,1,0) -> 1 | AH8: =IF(AH$6>='01_가정'!F46,1,0) -> 1 | AI8: =IF(AI$6>='01_가정'!F46,1,0) -> 1 | AJ8: =IF(AJ$6>='01_가정'!F46,1,0) -> 1 | AK8: =IF(AK$6>='01_가정'!F46,1,0) -> 1 | AL8: =IF(AL$6>='01_가정'!F46,1,0) -> 1 | AM8: =IF(AM$6>='01_가정'!F46,1,0) -> 1 | AN8: =IF(AN$6>='01_가정'!F46,1,0) -> 1 | AO8: =IF(AO$6>='01_가정'!F46,1,0) -> 1 | AP8: =IF(AP$6>='01_가정'!F46,1,0) -> 1 | AQ8: =IF(AQ$6>='01_가정'!F46,1,0) -> 1 | AR8: =IF(AR$6>='01_가정'!F46,1,0) -> 1 | AS8: =IF(AS$6>='01_가정'!F46,1,0) -> 1
C9: 출시 초기 집행 비중 | D9: % | J9: =IF(J8=0,0,IF(J$6='01_가정'!F46,0.5,IF(J$6='01_가정'!F46+1,0.75,1))) -> 0 | K9: =IF(K8=0,0,IF(K$6='01_가정'!F46,0.5,IF(K$6='01_가정'!F46+1,0.75,1))) -> 0 | L9: =IF(L8=0,0,IF(L$6='01_가정'!F46,0.5,IF(L$6='01_가정'!F46+1,0.75,1))) -> 0 | M9: =IF(M8=0,0,IF(M$6='01_가정'!F46,0.5,IF(M$6='01_가정'!F46+1,0.75,1))) -> 0 | N9: =IF(N8=0,0,IF(N$6='01_가정'!F46,0.5,IF(N$6='01_가정'!F46+1,0.75,1))) -> 0 | O9: =IF(O8=0,0,IF(O$6='01_가정'!F46,0.5,IF(O$6='01_가정'!F46+1,0.75,1))) -> 0 | P9: =IF(P8=0,0,IF(P$6='01_가정'!F46,0.5,IF(P$6='01_가정'!F46+1,0.75,1))) -> 0 | Q9: =IF(Q8=0,0,IF(Q$6='01_가정'!F46,0.5,IF(Q$6='01_가정'!F46+1,0.75,1))) -> 0 | R9: =IF(R8=0,0,IF(R$6='01_가정'!F46,0.5,IF(R$6='01_가정'!F46+1,0.75,1))) -> 0 | S9: =IF(S8=0,0,IF(S$6='01_가정'!F46,0.5,IF(S$6='01_가정'!F46+1,0.75,1))) -> 0.5 | T9: =IF(T8=0,0,IF(T$6='01_가정'!F46,0.5,IF(T$6='01_가정'!F46+1,0.75,1))) -> 0.75 | U9: =IF(U8=0,0,IF(U$6='01_가정'!F46,0.5,IF(U$6='01_가정'!F46+1,0.75,1))) -> 1 | V9: =IF(V8=0,0,IF(V$6='01_가정'!F46,0.5,IF(V$6='01_가정'!F46+1,0.75,1))) -> 1 | W9: =IF(W8=0,0,IF(W$6='01_가정'!F46,0.5,IF(W$6='01_가정'!F46+1,0.75,1))) -> 1 | X9: =IF(X8=0,0,IF(X$6='01_가정'!F46,0.5,IF(X$6='01_가정'!F46+1,0.75,1))) -> 1 | Y9: =IF(Y8=0,0,IF(Y$6='01_가정'!F46,0.5,IF(Y$6='01_가정'!F46+1,0.75,1))) -> 1 | Z9: =IF(Z8=0,0,IF(Z$6='01_가정'!F46,0.5,IF(Z$6='01_가정'!F46+1,0.75,1))) -> 1 | AA9: =IF(AA8=0,0,IF(AA$6='01_가정'!F46,0.5,IF(AA$6='01_가정'!F46+1,0.75,1))) -> 1 | AB9: =IF(AB8=0,0,IF(AB$6='01_가정'!F46,0.5,IF(AB$6='01_가정'!F46+1,0.75,1))) -> 1 | AC9: =IF(AC8=0,0,IF(AC$6='01_가정'!F46,0.5,IF(AC$6='01_가정'!F46+1,0.75,1))) -> 1 | AD9: =IF(AD8=0,0,IF(AD$6='01_가정'!F46,0.5,IF(AD$6='01_가정'!F46+1,0.75,1))) -> 1 | AE9: =IF(AE8=0,0,IF(AE$6='01_가정'!F46,0.5,IF(AE$6='01_가정'!F46+1,0.75,1))) -> 1 | AF9: =IF(AF8=0,0,IF(AF$6='01_가정'!F46,0.5,IF(AF$6='01_가정'!F46+1,0.75,1))) -> 1 | AG9: =IF(AG8=0,0,IF(AG$6='01_가정'!F46,0.5,IF(AG$6='01_가정'!F46+1,0.75,1))) -> 1 | AH9: =IF(AH8=0,0,IF(AH$6='01_가정'!F46,0.5,IF(AH$6='01_가정'!F46+1,0.75,1))) -> 1 | AI9: =IF(AI8=0,0,IF(AI$6='01_가정'!F46,0.5,IF(AI$6='01_가정'!F46+1,0.75,1))) -> 1 | AJ9: =IF(AJ8=0,0,IF(AJ$6='01_가정'!F46,0.5,IF(AJ$6='01_가정'!F46+1,0.75,1))) -> 1 | AK9: =IF(AK8=0,0,IF(AK$6='01_가정'!F46,0.5,IF(AK$6='01_가정'!F46+1,0.75,1))) -> 1 | AL9: =IF(AL8=0,0,IF(AL$6='01_가정'!F46,0.5,IF(AL$6='01_가정'!F46+1,0.75,1))) -> 1 | AM9: =IF(AM8=0,0,IF(AM$6='01_가정'!F46,0.5,IF(AM$6='01_가정'!F46+1,0.75,1))) -> 1 | AN9: =IF(AN8=0,0,IF(AN$6='01_가정'!F46,0.5,IF(AN$6='01_가정'!F46+1,0.75,1))) -> 1 | AO9: =IF(AO8=0,0,IF(AO$6='01_가정'!F46,0.5,IF(AO$6='01_가정'!F46+1,0.75,1))) -> 1 | AP9: =IF(AP8=0,0,IF(AP$6='01_가정'!F46,0.5,IF(AP$6='01_가정'!F46+1,0.75,1))) -> 1 | AQ9: =IF(AQ8=0,0,IF(AQ$6='01_가정'!F46,0.5,IF(AQ$6='01_가정'!F46+1,0.75,1))) -> 1 | AR9: =IF(AR8=0,0,IF(AR$6='01_가정'!F46,0.5,IF(AR$6='01_가정'!F46+1,0.75,1))) -> 1 | AS9: =IF(AS8=0,0,IF(AS$6='01_가정'!F46,0.5,IF(AS$6='01_가정'!F46+1,0.75,1))) -> 1
C10: 광고비 계획 | D10: 원 | F10: =SUM(J10:U10) -> 3375000 | G10: =SUM(V10:AG10) -> 36000000 | H10: =SUM(AH10:AS10) -> 60000000 | J10: ='01_가정'!F42*J9 -> 0 | K10: ='01_가정'!F42*K9 -> 0 | L10: ='01_가정'!F42*L9 -> 0 | M10: ='01_가정'!F42*M9 -> 0 | N10: ='01_가정'!F42*N9 -> 0 | O10: ='01_가정'!F42*O9 -> 0 | P10: ='01_가정'!F42*P9 -> 0 | Q10: ='01_가정'!F42*Q9 -> 0 | R10: ='01_가정'!F42*R9 -> 0 | S10: ='01_가정'!F42*S9 -> 750000 | T10: ='01_가정'!F42*T9 -> 1125000 | U10: ='01_가정'!F42*U9 -> 1500000 | V10: ='01_가정'!G42*V9 -> 3000000 | W10: ='01_가정'!G42*W9 -> 3000000 | X10: ='01_가정'!G42*X9 -> 3000000 | Y10: ='01_가정'!G42*Y9 -> 3000000 | Z10: ='01_가정'!G42*Z9 -> 3000000 | AA10: ='01_가정'!G42*AA9 -> 3000000 | AB10: ='01_가정'!G42*AB9 -> 3000000 | AC10: ='01_가정'!G42*AC9 -> 3000000 | AD10: ='01_가정'!G42*AD9 -> 3000000 | AE10: ='01_가정'!G42*AE9 -> 3000000 | AF10: ='01_가정'!G42*AF9 -> 3000000 | AG10: ='01_가정'!G42*AG9 -> 3000000 | AH10: ='01_가정'!H42*AH9 -> 5000000 | AI10: ='01_가정'!H42*AI9 -> 5000000 | AJ10: ='01_가정'!H42*AJ9 -> 5000000 | AK10: ='01_가정'!H42*AK9 -> 5000000 | AL10: ='01_가정'!H42*AL9 -> 5000000 | AM10: ='01_가정'!H42*AM9 -> 5000000 | AN10: ='01_가정'!H42*AN9 -> 5000000 | AO10: ='01_가정'!H42*AO9 -> 5000000 | AP10: ='01_가정'!H42*AP9 -> 5000000 | AQ10: ='01_가정'!H42*AQ9 -> 5000000 | AR10: ='01_가정'!H42*AR9 -> 5000000 | AS10: ='01_가정'!H42*AS9 -> 5000000
C11: 클릭당 비용 | D11: 원 | J11: ='01_가정'!F18 -> 1200 | K11: ='01_가정'!F18 -> 1200 | L11: ='01_가정'!F18 -> 1200 | M11: ='01_가정'!F18 -> 1200 | N11: ='01_가정'!F18 -> 1200 | O11: ='01_가정'!F18 -> 1200 | P11: ='01_가정'!F18 -> 1200 | Q11: ='01_가정'!F18 -> 1200 | R11: ='01_가정'!F18 -> 1200 | S11: ='01_가정'!F18 -> 1200 | T11: ='01_가정'!F18 -> 1200 | U11: ='01_가정'!F18 -> 1200 | V11: ='01_가정'!G18 -> 1100 | W11: ='01_가정'!G18 -> 1100 | X11: ='01_가정'!G18 -> 1100 | Y11: ='01_가정'!G18 -> 1100 | Z11: ='01_가정'!G18 -> 1100 | AA11: ='01_가정'!G18 -> 1100 | AB11: ='01_가정'!G18 -> 1100 | AC11: ='01_가정'!G18 -> 1100 | AD11: ='01_가정'!G18 -> 1100 | AE11: ='01_가정'!G18 -> 1100 | AF11: ='01_가정'!G18 -> 1100 | AG11: ='01_가정'!G18 -> 1100 | AH11: ='01_가정'!H18 -> 1000 | AI11: ='01_가정'!H18 -> 1000 | AJ11: ='01_가정'!H18 -> 1000 | AK11: ='01_가정'!H18 -> 1000 | AL11: ='01_가정'!H18 -> 1000 | AM11: ='01_가정'!H18 -> 1000 | AN11: ='01_가정'!H18 -> 1000 | AO11: ='01_가정'!H18 -> 1000 | AP11: ='01_가정'!H18 -> 1000 | AQ11: ='01_가정'!H18 -> 1000 | AR11: ='01_가정'!H18 -> 1000 | AS11: ='01_가정'!H18 -> 1000
C12: 유료 클릭 | D12: 회 | F12: =SUM(J12:U12) -> 2812.5 | G12: =SUM(V12:AG12) -> 32727.273 | H12: =SUM(AH12:AS12) -> 60000 | J12: =IF(J11>0,J10/J11,0) -> 0 | K12: =IF(K11>0,K10/K11,0) -> 0 | L12: =IF(L11>0,L10/L11,0) -> 0 | M12: =IF(M11>0,M10/M11,0) -> 0 | N12: =IF(N11>0,N10/N11,0) -> 0 | O12: =IF(O11>0,O10/O11,0) -> 0 | P12: =IF(P11>0,P10/P11,0) -> 0 | Q12: =IF(Q11>0,Q10/Q11,0) -> 0 | ... AS12: =IF(AS11>0,AS10/AS11,0) -> 5000
C13: 자연 유입 | D13: 회 | F13: =SUM(J13:U13) -> 1125 | G13: =SUM(V13:AG13) -> 12000 | H13: =SUM(AH13:AS13) -> 24000 | J13: ='01_가정'!F38*J9 -> 0 | K13: ='01_가정'!F38*K9 -> 0 | L13: ='01_가정'!F38*L9 -> 0 | M13: ='01_가정'!F38*M9 -> 0 | N13: ='01_가정'!F38*N9 -> 0 | O13: ='01_가정'!F38*O9 -> 0 | P13: ='01_가정'!F38*P9 -> 0 | Q13: ='01_가정'!F38*Q9 -> 0 | R13: ='01_가정'!F38*R9 -> 0 | S13: ='01_가정'!F38*S9 -> 250 | T13: ='01_가정'!F38*T9 -> 375 | U13: ='01_가정'!F38*U9 -> 500 | V13: ='01_가정'!G38*V9 -> 1000 | W13: ='01_가정'!G38*W9 -> 1000 | X13: ='01_가정'!G38*X9 -> 1000 | Y13: ='01_가정'!G38*Y9 -> 1000 | Z13: ='01_가정'!G38*Z9 -> 1000 | AA13: ='01_가정'!G38*AA9 -> 1000 | AB13: ='01_가정'!G38*AB9 -> 1000 | AC13: ='01_가정'!G38*AC9 -> 1000 | AD13: ='01_가정'!G38*AD9 -> 1000 | AE13: ='01_가정'!G38*AE9 -> 1000 | AF13: ='01_가정'!G38*AF9 -> 1000 | AG13: ='01_가정'!G38*AG9 -> 1000 | AH13: ='01_가정'!H38*AH9 -> 2000 | AI13: ='01_가정'!H38*AI9 -> 2000 | AJ13: ='01_가정'!H38*AJ9 -> 2000 | AK13: ='01_가정'!H38*AK9 -> 2000 | AL13: ='01_가정'!H38*AL9 -> 2000 | AM13: ='01_가정'!H38*AM9 -> 2000 | AN13: ='01_가정'!H38*AN9 -> 2000 | AO13: ='01_가정'!H38*AO9 -> 2000 | AP13: ='01_가정'!H38*AP9 -> 2000 | AQ13: ='01_가정'!H38*AQ9 -> 2000 | AR13: ='01_가정'!H38*AR9 -> 2000 | AS13: ='01_가정'!H38*AS9 -> 2000
C14: 출고 전환율 | D14: % | J14: ='01_가정'!F22 -> 0.015 | K14: ='01_가정'!F22 -> 0.015 | L14: ='01_가정'!F22 -> 0.015 | M14: ='01_가정'!F22 -> 0.015 | N14: ='01_가정'!F22 -> 0.015 | O14: ='01_가정'!F22 -> 0.015 | P14: ='01_가정'!F22 -> 0.015 | Q14: ='01_가정'!F22 -> 0.015 | R14: ='01_가정'!F22 -> 0.015 | S14: ='01_가정'!F22 -> 0.015 | T14: ='01_가정'!F22 -> 0.015 | U14: ='01_가정'!F22 -> 0.015 | V14: ='01_가정'!G22 -> 0.018 | W14: ='01_가정'!G22 -> 0.018 | X14: ='01_가정'!G22 -> 0.018 | Y14: ='01_가정'!G22 -> 0.018 | Z14: ='01_가정'!G22 -> 0.018 | AA14: ='01_가정'!G22 -> 0.018 | AB14: ='01_가정'!G22 -> 0.018 | AC14: ='01_가정'!G22 -> 0.018 | AD14: ='01_가정'!G22 -> 0.018 | AE14: ='01_가정'!G22 -> 0.018 | AF14: ='01_가정'!G22 -> 0.018 | AG14: ='01_가정'!G22 -> 0.018 | AH14: ='01_가정'!H22 -> 0.02 | AI14: ='01_가정'!H22 -> 0.02 | AJ14: ='01_가정'!H22 -> 0.02 | AK14: ='01_가정'!H22 -> 0.02 | AL14: ='01_가정'!H22 -> 0.02 | AM14: ='01_가정'!H22 -> 0.02 | AN14: ='01_가정'!H22 -> 0.02 | AO14: ='01_가정'!H22 -> 0.02 | AP14: ='01_가정'!H22 -> 0.02 | AQ14: ='01_가정'!H22 -> 0.02 | AR14: ='01_가정'!H22 -> 0.02 | AS14: ='01_가정'!H22 -> 0.02
C15: 유료 신규 출고 | D15: 개 | F15: =SUM(J15:U15) -> 41 | G15: =SUM(V15:AG15) -> 588 | H15: =SUM(AH15:AS15) -> 1200 | J15: =ROUNDDOWN(J12*J14,0) -> 0 | K15: =ROUNDDOWN(K12*K14,0) -> 0 | L15: =ROUNDDOWN(L12*L14,0) -> 0 | M15: =ROUNDDOWN(M12*M14,0) -> 0 | N15: =ROUNDDOWN(N12*N14,0) -> 0 | O15: =ROUNDDOWN(O12*O14,0) -> 0 | P15: =ROUNDDOWN(P12*P14,0) -> 0 | Q15: =ROUNDDOWN(Q12*Q14,0) -> 0 | ... AS15: =ROUNDDOWN(AS12*AS14,0) -> 100
C16: 자연 유입 신규 출고 | D16: 개 | F16: =SUM(J16:U16) -> 15 | G16: =SUM(V16:AG16) -> 216 | H16: =SUM(AH16:AS16) -> 480 | J16: =ROUNDDOWN(J13*J14,0) -> 0 | K16: =ROUNDDOWN(K13*K14,0) -> 0 | L16: =ROUNDDOWN(L13*L14,0) -> 0 | M16: =ROUNDDOWN(M13*M14,0) -> 0 | N16: =ROUNDDOWN(N13*N14,0) -> 0 | O16: =ROUNDDOWN(O13*O14,0) -> 0 | P16: =ROUNDDOWN(P13*P14,0) -> 0 | Q16: =ROUNDDOWN(Q13*Q14,0) -> 0 | ... AS16: =ROUNDDOWN(AS13*AS14,0) -> 40
C17: DTC 총 출고 | D17: 개 | F17: =SUM(J17:U17) -> 56 | G17: =SUM(V17:AG17) -> 804 | H17: =SUM(AH17:AS17) -> 1680 | J17: =SUM(J15:J16) -> 0 | K17: =SUM(K15:K16) -> 0 | L17: =SUM(L15:L16) -> 0 | M17: =SUM(M15:M16) -> 0 | N17: =SUM(N15:N16) -> 0 | O17: =SUM(O15:O16) -> 0 | P17: =SUM(P15:P16) -> 0 | Q17: =SUM(Q15:Q16) -> 0 | ... AS17: =SUM(AS15:AS16) -> 140
C18: 리테일 총 출고 | D18: 개 | F18: =SUM(J18:U18) -> 0 | G18: =SUM(V18:AG18) -> 0 | H18: =SUM(AH18:AS18) -> 0 | J18: =ROUNDDOWN('01_가정'!F50*J9*'01_가정'!$F$95,0) -> 0 | K18: =ROUNDDOWN('01_가정'!F50*K9*'01_가정'!$F$95,0) -> 0 | L18: =ROUNDDOWN('01_가정'!F50*L9*'01_가정'!$F$95,0) -> 0 | M18: =ROUNDDOWN('01_가정'!F50*M9*'01_가정'!$F$95,0) -> 0 | N18: =ROUNDDOWN('01_가정'!F50*N9*'01_가정'!$F$95,0) -> 0 | O18: =ROUNDDOWN('01_가정'!F50*O9*'01_가정'!$F$95,0) -> 0 | P18: =ROUNDDOWN('01_가정'!F50*P9*'01_가정'!$F$95,0) -> 0 | Q18: =ROUNDDOWN('01_가정'!F50*Q9*'01_가정'!$F$95,0) -> 0 | R18: =ROUNDDOWN('01_가정'!F50*R9*'01_가정'!$F$95,0) -> 0 | S18: =ROUNDDOWN('01_가정'!F50*S9*'01_가정'!$F$95,0) -> 0 | T18: =ROUNDDOWN('01_가정'!F50*T9*'01_가정'!$F$95,0) -> 0 | U18: =ROUNDDOWN('01_가정'!F50*U9*'01_가정'!$F$95,0) -> 0 | V18: =ROUNDDOWN('01_가정'!G50*V9*'01_가정'!$F$95,0) -> 0 | W18: =ROUNDDOWN('01_가정'!G50*W9*'01_가정'!$F$95,0) -> 0 | X18: =ROUNDDOWN('01_가정'!G50*X9*'01_가정'!$F$95,0) -> 0 | Y18: =ROUNDDOWN('01_가정'!G50*Y9*'01_가정'!$F$95,0) -> 0 | Z18: =ROUNDDOWN('01_가정'!G50*Z9*'01_가정'!$F$95,0) -> 0 | AA18: =ROUNDDOWN('01_가정'!G50*AA9*'01_가정'!$F$95,0) -> 0 | AB18: =ROUNDDOWN('01_가정'!G50*AB9*'01_가정'!$F$95,0) -> 0 | AC18: =ROUNDDOWN('01_가정'!G50*AC9*'01_가정'!$F$95,0) -> 0 | AD18: =ROUNDDOWN('01_가정'!G50*AD9*'01_가정'!$F$95,0) -> 0 | AE18: =ROUNDDOWN('01_가정'!G50*AE9*'01_가정'!$F$95,0) -> 0 | AF18: =ROUNDDOWN('01_가정'!G50*AF9*'01_가정'!$F$95,0) -> 0 | AG18: =ROUNDDOWN('01_가정'!G50*AG9*'01_가정'!$F$95,0) -> 0 | AH18: =ROUNDDOWN('01_가정'!H50*AH9*'01_가정'!$F$95,0) -> 0 | AI18: =ROUNDDOWN('01_가정'!H50*AI9*'01_가정'!$F$95,0) -> 0 | AJ18: =ROUNDDOWN('01_가정'!H50*AJ9*'01_가정'!$F$95,0) -> 0 | AK18: =ROUNDDOWN('01_가정'!H50*AK9*'01_가정'!$F$95,0) -> 0 | AL18: =ROUNDDOWN('01_가정'!H50*AL9*'01_가정'!$F$95,0) -> 0 | AM18: =ROUNDDOWN('01_가정'!H50*AM9*'01_가정'!$F$95,0) -> 0 | AN18: =ROUNDDOWN('01_가정'!H50*AN9*'01_가정'!$F$95,0) -> 0 | AO18: =ROUNDDOWN('01_가정'!H50*AO9*'01_가정'!$F$95,0) -> 0 | AP18: =ROUNDDOWN('01_가정'!H50*AP9*'01_가정'!$F$95,0) -> 0 | AQ18: =ROUNDDOWN('01_가정'!H50*AQ9*'01_가정'!$F$95,0) -> 0 | AR18: =ROUNDDOWN('01_가정'!H50*AR9*'01_가정'!$F$95,0) -> 0 | AS18: =ROUNDDOWN('01_가정'!H50*AS9*'01_가정'!$F$95,0) -> 0
C19: 본체 총 출고 | D19: 개 | F19: =SUM(J19:U19) -> 56 | G19: =SUM(V19:AG19) -> 804 | H19: =SUM(AH19:AS19) -> 1680 | J19: =SUM(J17:J18) -> 0 | K19: =SUM(K17:K18) -> 0 | L19: =SUM(L17:L18) -> 0 | M19: =SUM(M17:M18) -> 0 | N19: =SUM(N17:N18) -> 0 | O19: =SUM(O17:O18) -> 0 | P19: =SUM(P17:P18) -> 0 | Q19: =SUM(Q17:Q18) -> 0 | ... AS19: =SUM(AS17:AS18) -> 140
C20: DTC 환불 기대 건수 | D20: 개 | F20: =SUM(J20:U20) -> 8.4 | G20: =SUM(V20:AG20) -> 96.48 | H20: =SUM(AH20:AS20) -> 168 | J20: =J17*'01_가정'!F26 -> 0 | K20: =K17*'01_가정'!F26 -> 0 | L20: =L17*'01_가정'!F26 -> 0 | M20: =M17*'01_가정'!F26 -> 0 | N20: =N17*'01_가정'!F26 -> 0 | O20: =O17*'01_가정'!F26 -> 0 | P20: =P17*'01_가정'!F26 -> 0 | Q20: =Q17*'01_가정'!F26 -> 0 | R20: =R17*'01_가정'!F26 -> 0 | S20: =S17*'01_가정'!F26 -> 1.8 | T20: =T17*'01_가정'!F26 -> 2.85 | U20: =U17*'01_가정'!F26 -> 3.75 | V20: =V17*'01_가정'!G26 -> 8.04 | W20: =W17*'01_가정'!G26 -> 8.04 | X20: =X17*'01_가정'!G26 -> 8.04 | Y20: =Y17*'01_가정'!G26 -> 8.04 | Z20: =Z17*'01_가정'!G26 -> 8.04 | AA20: =AA17*'01_가정'!G26 -> 8.04 | AB20: =AB17*'01_가정'!G26 -> 8.04 | AC20: =AC17*'01_가정'!G26 -> 8.04 | AD20: =AD17*'01_가정'!G26 -> 8.04 | AE20: =AE17*'01_가정'!G26 -> 8.04 | AF20: =AF17*'01_가정'!G26 -> 8.04 | AG20: =AG17*'01_가정'!G26 -> 8.04 | AH20: =AH17*'01_가정'!H26 -> 14 | AI20: =AI17*'01_가정'!H26 -> 14 | AJ20: =AJ17*'01_가정'!H26 -> 14 | AK20: =AK17*'01_가정'!H26 -> 14 | AL20: =AL17*'01_가정'!H26 -> 14 | AM20: =AM17*'01_가정'!H26 -> 14 | AN20: =AN17*'01_가정'!H26 -> 14 | AO20: =AO17*'01_가정'!H26 -> 14 | AP20: =AP17*'01_가정'!H26 -> 14 | AQ20: =AQ17*'01_가정'!H26 -> 14 | AR20: =AR17*'01_가정'!H26 -> 14 | AS20: =AS17*'01_가정'!H26 -> 14
C21: DTC 비환불 고객 | D21: 명 | F21: =SUM(J21:U21) -> 47.6 | G21: =SUM(V21:AG21) -> 707.52 | H21: =SUM(AH21:AS21) -> 1512 | J21: =J17-J20 -> 0 | K21: =K17-K20 -> 0 | L21: =L17-L20 -> 0 | M21: =M17-M20 -> 0 | N21: =N17-N20 -> 0 | O21: =O17-O20 -> 0 | P21: =P17-P20 -> 0 | Q21: =Q17-Q20 -> 0 | ... AS21: =AS17-AS20 -> 126
C22: 리테일 반품 기대 건수 | D22: 개 | F22: =SUM(J22:U22) -> 0 | G22: =SUM(V22:AG22) -> 0 | H22: =SUM(AH22:AS22) -> 0 | J22: =J18*'01_가정'!$F$98 -> 0 | K22: =K18*'01_가정'!$F$98 -> 0 | L22: =L18*'01_가정'!$F$98 -> 0 | M22: =M18*'01_가정'!$F$98 -> 0 | N22: =N18*'01_가정'!$F$98 -> 0 | O22: =O18*'01_가정'!$F$98 -> 0 | P22: =P18*'01_가정'!$F$98 -> 0 | Q22: =Q18*'01_가정'!$F$98 -> 0 | ... AS22: =AS18*'01_가정'!$F$98 -> 0
C23: 총 비반품 구매자 | D23: 명 | F23: =SUM(J23:U23) -> 47.6 | G23: =SUM(V23:AG23) -> 707.52 | H23: =SUM(AH23:AS23) -> 1512 | J23: =J21+J18-J22 -> 0 | K23: =K21+K18-K22 -> 0 | L23: =L21+L18-L22 -> 0 | M23: =M21+M18-M22 -> 0 | N23: =N21+N18-N22 -> 0 | O23: =O21+O18-O22 -> 0 | P23: =P21+P18-P22 -> 0 | Q23: =Q21+Q18-Q22 -> 0 | ... AS23: =AS21+AS18-AS22 -> 126
C24: 해당 월 리필 참여율 | D24: % | J24: ='01_가정'!F30 -> 0.1 | K24: ='01_가정'!F30 -> 0.1 | L24: ='01_가정'!F30 -> 0.1 | M24: ='01_가정'!F30 -> 0.1 | N24: ='01_가정'!F30 -> 0.1 | O24: ='01_가정'!F30 -> 0.1 | P24: ='01_가정'!F30 -> 0.1 | Q24: ='01_가정'!F30 -> 0.1 | R24: ='01_가정'!F30 -> 0.1 | S24: ='01_가정'!F30 -> 0.1 | T24: ='01_가정'!F30 -> 0.1 | U24: ='01_가정'!F30 -> 0.1 | V24: ='01_가정'!G30 -> 0.12 | W24: ='01_가정'!G30 -> 0.12 | X24: ='01_가정'!G30 -> 0.12 | Y24: ='01_가정'!G30 -> 0.12 | Z24: ='01_가정'!G30 -> 0.12 | AA24: ='01_가정'!G30 -> 0.12 | AB24: ='01_가정'!G30 -> 0.12 | AC24: ='01_가정'!G30 -> 0.12 | AD24: ='01_가정'!G30 -> 0.12 | AE24: ='01_가정'!G30 -> 0.12 | AF24: ='01_가정'!G30 -> 0.12 | AG24: ='01_가정'!G30 -> 0.12 | AH24: ='01_가정'!H30 -> 0.15 | AI24: ='01_가정'!H30 -> 0.15 | AJ24: ='01_가정'!H30 -> 0.15 | AK24: ='01_가정'!H30 -> 0.15 | AL24: ='01_가정'!H30 -> 0.15 | AM24: ='01_가정'!H30 -> 0.15 | AN24: ='01_가정'!H30 -> 0.15 | AO24: ='01_가정'!H30 -> 0.15 | AP24: ='01_가정'!H30 -> 0.15 | AQ24: ='01_가정'!H30 -> 0.15 | AR24: ='01_가정'!H30 -> 0.15 | AS24: ='01_가정'!H30 -> 0.15
C25: 해당 월 리필 유지율 | D25: % | J25: ='01_가정'!F34 -> 0.75 | K25: ='01_가정'!F34 -> 0.75 | L25: ='01_가정'!F34 -> 0.75 | M25: ='01_가정'!F34 -> 0.75 | N25: ='01_가정'!F34 -> 0.75 | O25: ='01_가정'!F34 -> 0.75 | P25: ='01_가정'!F34 -> 0.75 | Q25: ='01_가정'!F34 -> 0.75 | R25: ='01_가정'!F34 -> 0.75 | S25: ='01_가정'!F34 -> 0.75 | T25: ='01_가정'!F34 -> 0.75 | U25: ='01_가정'!F34 -> 0.75 | V25: ='01_가정'!G34 -> 0.78 | W25: ='01_가정'!G34 -> 0.78 | X25: ='01_가정'!G34 -> 0.78 | Y25: ='01_가정'!G34 -> 0.78 | Z25: ='01_가정'!G34 -> 0.78 | AA25: ='01_가정'!G34 -> 0.78 | AB25: ='01_가정'!G34 -> 0.78 | AC25: ='01_가정'!G34 -> 0.78 | AD25: ='01_가정'!G34 -> 0.78 | AE25: ='01_가정'!G34 -> 0.78 | AF25: ='01_가정'!G34 -> 0.78 | AG25: ='01_가정'!G34 -> 0.78 | AH25: ='01_가정'!H34 -> 0.8 | AI25: ='01_가정'!H34 -> 0.8 | AJ25: ='01_가정'!H34 -> 0.8 | AK25: ='01_가정'!H34 -> 0.8 | AL25: ='01_가정'!H34 -> 0.8 | AM25: ='01_가정'!H34 -> 0.8 | AN25: ='01_가정'!H34 -> 0.8 | AO25: ='01_가정'!H34 -> 0.8 | AP25: ='01_가정'!H34 -> 0.8 | AQ25: ='01_가정'!H34 -> 0.8 | AR25: ='01_가정'!H34 -> 0.8 | AS25: ='01_가정'!H34 -> 0.8
C26: 신규 리필 구매자 | D26: 명 | F26: =SUM(J26:U26) -> 2.635 | G26: =SUM(V26:AG26) -> 79.9522 | H26: =SUM(AH26:AS26) -> 214.9752 | J26: =0 -> 0 | K26: =J21*J24 -> 0 | L26: =K21*K24 -> 0 | M26: =L21*L24 -> 0 | N26: =M21*M24 -> 0 | O26: =N21*N24 -> 0 | P26: =O21*O24 -> 0 | Q26: =P21*P24 -> 0 | R26: =Q21*Q24 -> 0 | ... AS26: =AR21*AR24 -> 18.9
C27: 전월 구매자 중 재구매 | D27: 명 | F27: =SUM(J27:U27) -> 0.765 | G27: =SUM(V27:AG27) -> 184.37904 | H27: =SUM(AH27:AS27) -> 624.91469 | J27: =0 -> 0 | K27: =J28*K25 -> 0 | L27: =K28*L25 -> 0 | M27: =L28*M25 -> 0 | N27: =M28*N25 -> 0 | O27: =N28*O25 -> 0 | P27: =O28*P25 -> 0 | Q27: =P28*Q25 -> 0 | R27: =Q28*R25 -> 0 | ... AS27: =AR28*AS25 -> 70.174381
C28: 당월 리필 구매자(연간=연말) | D28: 명 | F28: =U28 -> 2.38 | G28: =AG28 -> 30.327854 | H28: =AS28 -> 89.074381 | J28: =SUM(J26:J27) -> 0 | K28: =SUM(K26:K27) -> 0 | L28: =SUM(L26:L27) -> 0 | M28: =SUM(M26:M27) -> 0 | N28: =SUM(N26:N27) -> 0 | O28: =SUM(O26:O27) -> 0 | P28: =SUM(P26:P27) -> 0 | Q28: =SUM(Q26:Q27) -> 0 | ... AS28: =SUM(AS26:AS27) -> 89.074381
C29: 리필 출고 주문 | D29: 팩 | F29: =SUM(J29:U29) -> 3.4 | G29: =SUM(V29:AG29) -> 264.33124 | H29: =SUM(AH29:AS29) -> 839.88989 | J29: =J28*'01_가정'!$F$94 -> 0 | K29: =K28*'01_가정'!$F$94 -> 0 | L29: =L28*'01_가정'!$F$94 -> 0 | M29: =M28*'01_가정'!$F$94 -> 0 | N29: =N28*'01_가정'!$F$94 -> 0 | O29: =O28*'01_가정'!$F$94 -> 0 | P29: =P28*'01_가정'!$F$94 -> 0 | Q29: =Q28*'01_가정'!$F$94 -> 0 | ... AS29: =AS28*'01_가정'!$F$94 -> 89.074381
C30: DTC 본체 순매출 | D30: 원 | F30: =SUM(J30:U30) -> 5582181.8 | G30: =SUM(V30:AG30) -> 82972800 | H30: =SUM(AH30:AS30) -> 1.7731636e+08 | J30: =J21*'01_가정'!F10/(1+'01_가정'!$F$85) -> 0 | K30: =K21*'01_가정'!F10/(1+'01_가정'!$F$85) -> 0 | L30: =L21*'01_가정'!F10/(1+'01_가정'!$F$85) -> 0 | M30: =M21*'01_가정'!F10/(1+'01_가정'!$F$85) -> 0 | N30: =N21*'01_가정'!F10/(1+'01_가정'!$F$85) -> 0 | O30: =O21*'01_가정'!F10/(1+'01_가정'!$F$85) -> 0 | P30: =P21*'01_가정'!F10/(1+'01_가정'!$F$85) -> 0 | Q30: =Q21*'01_가정'!F10/(1+'01_가정'!$F$85) -> 0 | R30: =R21*'01_가정'!F10/(1+'01_가정'!$F$85) -> 0 | S30: =S21*'01_가정'!F10/(1+'01_가정'!$F$85) -> 1196181.8 | T30: =T21*'01_가정'!F10/(1+'01_가정'!$F$85) -> 1893954.5 | U30: =U21*'01_가정'!F10/(1+'01_가정'!$F$85) -> 2492045.5 | V30: =V21*'01_가정'!G10/(1+'01_가정'!$F$85) -> 6914400 | W30: =W21*'01_가정'!G10/(1+'01_가정'!$F$85) -> 6914400 | X30: =X21*'01_가정'!G10/(1+'01_가정'!$F$85) -> 6914400 | Y30: =Y21*'01_가정'!G10/(1+'01_가정'!$F$85) -> 6914400 | Z30: =Z21*'01_가정'!G10/(1+'01_가정'!$F$85) -> 6914400 | AA30: =AA21*'01_가정'!G10/(1+'01_가정'!$F$85) -> 6914400 | AB30: =AB21*'01_가정'!G10/(1+'01_가정'!$F$85) -> 6914400 | AC30: =AC21*'01_가정'!G10/(1+'01_가정'!$F$85) -> 6914400 | AD30: =AD21*'01_가정'!G10/(1+'01_가정'!$F$85) -> 6914400 | AE30: =AE21*'01_가정'!G10/(1+'01_가정'!$F$85) -> 6914400 | AF30: =AF21*'01_가정'!G10/(1+'01_가정'!$F$85) -> 6914400 | AG30: =AG21*'01_가정'!G10/(1+'01_가정'!$F$85) -> 6914400 | AH30: =AH21*'01_가정'!H10/(1+'01_가정'!$F$85) -> 14776364 | AI30: =AI21*'01_가정'!H10/(1+'01_가정'!$F$85) -> 14776364 | AJ30: =AJ21*'01_가정'!H10/(1+'01_가정'!$F$85) -> 14776364 | AK30: =AK21*'01_가정'!H10/(1+'01_가정'!$F$85) -> 14776364 | AL30: =AL21*'01_가정'!H10/(1+'01_가정'!$F$85) -> 14776364 | AM30: =AM21*'01_가정'!H10/(1+'01_가정'!$F$85) -> 14776364 | AN30: =AN21*'01_가정'!H10/(1+'01_가정'!$F$85) -> 14776364 | AO30: =AO21*'01_가정'!H10/(1+'01_가정'!$F$85) -> 14776364 | AP30: =AP21*'01_가정'!H10/(1+'01_가정'!$F$85) -> 14776364 | AQ30: =AQ21*'01_가정'!H10/(1+'01_가정'!$F$85) -> 14776364 | AR30: =AR21*'01_가정'!H10/(1+'01_가정'!$F$85) -> 14776364 | AS30: =AS21*'01_가정'!H10/(1+'01_가정'!$F$85) -> 14776364
C31: 리테일 본체 순매출 | D31: 원 | F31: =SUM(J31:U31) -> 0 | G31: =SUM(V31:AG31) -> 0 | H31: =SUM(AH31:AS31) -> 0 | J31: =(J18-J22)*'01_가정'!F10/(1+'01_가정'!$F$85)*'01_가정'!F54 -> 0 | K31: =(K18-K22)*'01_가정'!F10/(1+'01_가정'!$F$85)*'01_가정'!F54 -> 0 | L31: =(L18-L22)*'01_가정'!F10/(1+'01_가정'!$F$85)*'01_가정'!F54 -> 0 | M31: =(M18-M22)*'01_가정'!F10/(1+'01_가정'!$F$85)*'01_가정'!F54 -> 0 | N31: =(N18-N22)*'01_가정'!F10/(1+'01_가정'!$F$85)*'01_가정'!F54 -> 0 | O31: =(O18-O22)*'01_가정'!F10/(1+'01_가정'!$F$85)*'01_가정'!F54 -> 0 | P31: =(P18-P22)*'01_가정'!F10/(1+'01_가정'!$F$85)*'01_가정'!F54 -> 0 | Q31: =(Q18-Q22)*'01_가정'!F10/(1+'01_가정'!$F$85)*'01_가정'!F54 -> 0 | R31: =(R18-R22)*'01_가정'!F10/(1+'01_가정'!$F$85)*'01_가정'!F54 -> 0 | S31: =(S18-S22)*'01_가정'!F10/(1+'01_가정'!$F$85)*'01_가정'!F54 -> 0 | T31: =(T18-T22)*'01_가정'!F10/(1+'01_가정'!$F$85)*'01_가정'!F54 -> 0 | U31: =(U18-U22)*'01_가정'!F10/(1+'01_가정'!$F$85)*'01_가정'!F54 -> 0 | V31: =(V18-V22)*'01_가정'!G10/(1+'01_가정'!$F$85)*'01_가정'!G54 -> 0 | W31: =(W18-W22)*'01_가정'!G10/(1+'01_가정'!$F$85)*'01_가정'!G54 -> 0 | X31: =(X18-X22)*'01_가정'!G10/(1+'01_가정'!$F$85)*'01_가정'!G54 -> 0 | Y31: =(Y18-Y22)*'01_가정'!G10/(1+'01_가정'!$F$85)*'01_가정'!G54 -> 0 | Z31: =(Z18-Z22)*'01_가정'!G10/(1+'01_가정'!$F$85)*'01_가정'!G54 -> 0 | AA31: =(AA18-AA22)*'01_가정'!G10/(1+'01_가정'!$F$85)*'01_가정'!G54 -> 0 | AB31: =(AB18-AB22)*'01_가정'!G10/(1+'01_가정'!$F$85)*'01_가정'!G54 -> 0 | AC31: =(AC18-AC22)*'01_가정'!G10/(1+'01_가정'!$F$85)*'01_가정'!G54 -> 0 | AD31: =(AD18-AD22)*'01_가정'!G10/(1+'01_가정'!$F$85)*'01_가정'!G54 -> 0 | AE31: =(AE18-AE22)*'01_가정'!G10/(1+'01_가정'!$F$85)*'01_가정'!G54 -> 0 | AF31: =(AF18-AF22)*'01_가정'!G10/(1+'01_가정'!$F$85)*'01_가정'!G54 -> 0 | AG31: =(AG18-AG22)*'01_가정'!G10/(1+'01_가정'!$F$85)*'01_가정'!G54 -> 0 | AH31: =(AH18-AH22)*'01_가정'!H10/(1+'01_가정'!$F$85)*'01_가정'!H54 -> 0 | AI31: =(AI18-AI22)*'01_가정'!H10/(1+'01_가정'!$F$85)*'01_가정'!H54 -> 0 | AJ31: =(AJ18-AJ22)*'01_가정'!H10/(1+'01_가정'!$F$85)*'01_가정'!H54 -> 0 | AK31: =(AK18-AK22)*'01_가정'!H10/(1+'01_가정'!$F$85)*'01_가정'!H54 -> 0 | AL31: =(AL18-AL22)*'01_가정'!H10/(1+'01_가정'!$F$85)*'01_가정'!H54 -> 0 | AM31: =(AM18-AM22)*'01_가정'!H10/(1+'01_가정'!$F$85)*'01_가정'!H54 -> 0 | AN31: =(AN18-AN22)*'01_가정'!H10/(1+'01_가정'!$F$85)*'01_가정'!H54 -> 0 | AO31: =(AO18-AO22)*'01_가정'!H10/(1+'01_가정'!$F$85)*'01_가정'!H54 -> 0 | AP31: =(AP18-AP22)*'01_가정'!H10/(1+'01_가정'!$F$85)*'01_가정'!H54 -> 0 | AQ31: =(AQ18-AQ22)*'01_가정'!H10/(1+'01_가정'!$F$85)*'01_가정'!H54 -> 0 | AR31: =(AR18-AR22)*'01_가정'!H10/(1+'01_가정'!$F$85)*'01_가정'!H54 -> 0 | AS31: =(AS18-AS22)*'01_가정'!H10/(1+'01_가정'!$F$85)*'01_가정'!H54 -> 0
C32: 리필 순매출 | D32: 원 | F32: =SUM(J32:U32) -> 29988 | G32: =SUM(V32:AG32) -> 2331401.6 | H32: =SUM(AH32:AS32) -> 7407828.8 | J32: =J29*'02_단위경제'!F44 -> 0 | K32: =K29*'02_단위경제'!F44 -> 0 | L32: =L29*'02_단위경제'!F44 -> 0 | M32: =M29*'02_단위경제'!F44 -> 0 | N32: =N29*'02_단위경제'!F44 -> 0 | O32: =O29*'02_단위경제'!F44 -> 0 | P32: =P29*'02_단위경제'!F44 -> 0 | Q32: =Q29*'02_단위경제'!F44 -> 0 | R32: =R29*'02_단위경제'!F44 -> 0 | S32: =S29*'02_단위경제'!F44 -> 0 | T32: =T29*'02_단위경제'!F44 -> 8996.4 | U32: =U29*'02_단위경제'!F44 -> 20991.6 | V32: =V29*'02_단위경제'!G44 -> 35115.948 | W32: =W29*'02_단위경제'!G44 -> 89793.703 | X32: =X29*'02_단위경제'!G44 -> 132442.35 | Y32: =Y29*'02_단위경제'!G44 -> 165708.3 | Z32: =Z29*'02_단위경제'!G44 -> 191655.74 | AA32: =AA29*'02_단위경제'!G44 -> 211894.74 | AB32: =AB29*'02_단위경제'!G44 -> 227681.16 | AC32: =AC29*'02_단위경제'!G44 -> 239994.57 | AD32: =AD29*'02_단위경제'!G44 -> 249599.03 | AE32: =AE29*'02_단위경제'!G44 -> 257090.51 | AF32: =AF29*'02_단위경제'!G44 -> 262933.86 | AG32: =AG29*'02_단위경제'!G44 -> 267491.67 | AH32: =AH29*'02_단위경제'!H44 -> 276396.6 | AI32: =AI29*'02_단위경제'!H44 -> 387815.28 | AJ32: =AJ29*'02_단위경제'!H44 -> 476950.23 | AK32: =AK29*'02_단위경제'!H44 -> 548258.18 | AL32: =AL29*'02_단위경제'!H44 -> 605304.54 | AM32: =AM29*'02_단위경제'!H44 -> 650941.64 | AN32: =AN29*'02_단위경제'!H44 -> 687451.31 | AO32: =AO29*'02_단위경제'!H44 -> 716659.05 | AP32: =AP29*'02_단위경제'!H44 -> 740025.24 | AQ32: =AQ29*'02_단위경제'!H44 -> 758718.19 | AR32: =AR29*'02_단위경제'!H44 -> 773672.55 | AS32: =AS29*'02_단위경제'!H44 -> 785636.04
C33: 총 순매출 | D33: 원 | F33: =SUM(J33:U33) -> 5612169.8 | G33: =SUM(V33:AG33) -> 85304202 | H33: =SUM(AH33:AS33) -> 1.8472419e+08 | J33: =SUM(J30:J32) -> 0 | K33: =SUM(K30:K32) -> 0 | L33: =SUM(L30:L32) -> 0 | M33: =SUM(M30:M32) -> 0 | N33: =SUM(N30:N32) -> 0 | O33: =SUM(O30:O32) -> 0 | P33: =SUM(P30:P32) -> 0 | Q33: =SUM(Q30:Q32) -> 0 | ... AS33: =SUM(AS30:AS32) -> 15562000
C34: 본체 매출원가 | D34: 원 | F34: =SUM(J34:U34) -> 3920000 | G34: =SUM(V34:AG34) -> 53370875 | H34: =SUM(AH34:AS34) -> 1.0259593e+08 | J34: ='04_재고현금'!J16 -> 0 | K34: ='04_재고현금'!K16 -> 0 | L34: ='04_재고현금'!L16 -> 0 | M34: ='04_재고현금'!M16 -> 0 | N34: ='04_재고현금'!N16 -> 0 | O34: ='04_재고현금'!O16 -> 0 | P34: ='04_재고현금'!P16 -> 0 | Q34: ='04_재고현금'!Q16 -> 0 | ... AS34: ='04_재고현금'!AS16 -> 8411547
C35: 리필 매출원가 | D35: 원 | F35: =SUM(J35:U35) -> 15300 | G35: =SUM(V35:AG35) -> 1136624.4 | H35: =SUM(AH35:AS35) -> 3359559.6 | J35: =J29*'01_가정'!F74 -> 0 | K35: =K29*'01_가정'!F74 -> 0 | L35: =L29*'01_가정'!F74 -> 0 | M35: =M29*'01_가정'!F74 -> 0 | N35: =N29*'01_가정'!F74 -> 0 | O35: =O29*'01_가정'!F74 -> 0 | P35: =P29*'01_가정'!F74 -> 0 | Q35: =Q29*'01_가정'!F74 -> 0 | R35: =R29*'01_가정'!F74 -> 0 | S35: =S29*'01_가정'!F74 -> 0 | T35: =T29*'01_가정'!F74 -> 4590 | U35: =U29*'01_가정'!F74 -> 10710 | V35: =V29*'01_가정'!G74 -> 17120.02 | W35: =W29*'01_가정'!G74 -> 43776.976 | X35: =X29*'01_가정'!G74 -> 64569.401 | Y35: =Y29*'01_가정'!G74 -> 80787.493 | Z35: =Z29*'01_가정'!G74 -> 93437.604 | AA35: =AA29*'01_가정'!G74 -> 103304.69 | AB35: =AB29*'01_가정'!G74 -> 111001.02 | AC35: =AC29*'01_가정'!G74 -> 117004.16 | AD35: =AD29*'01_가정'!G74 -> 121686.6 | AE35: =AE29*'01_가정'!G74 -> 125338.91 | AF35: =AF29*'01_가정'!G74 -> 128187.71 | AG35: =AG29*'01_가정'!G74 -> 130409.77 | AH35: =AH29*'01_가정'!H74 -> 125349.93 | AI35: =AI29*'01_가정'!H74 -> 175879.95 | AJ35: =AJ29*'01_가정'!H74 -> 216303.96 | AK35: =AK29*'01_가정'!H74 -> 248643.17 | AL35: =AL29*'01_가정'!H74 -> 274514.53 | AM35: =AM29*'01_가정'!H74 -> 295211.63 | AN35: =AN29*'01_가정'!H74 -> 311769.3 | AO35: =AO29*'01_가정'!H74 -> 325015.44 | AP35: =AP29*'01_가정'!H74 -> 335612.35 | AQ35: =AQ29*'01_가정'!H74 -> 344089.88 | AR35: =AR29*'01_가정'!H74 -> 350871.91 | AS35: =AS29*'01_가정'!H74 -> 356297.52
C36: 매출총이익 | D36: 원 | F36: =SUM(J36:U36) -> 1676869.8 | G36: =SUM(V36:AG36) -> 30796703 | H36: =SUM(AH36:AS36) -> 78768704 | J36: =J33-SUM(J34:J35) -> 0 | K36: =K33-SUM(K34:K35) -> 0 | L36: =L33-SUM(L34:L35) -> 0 | M36: =M33-SUM(M34:M35) -> 0 | N36: =N33-SUM(N34:N35) -> 0 | O36: =O33-SUM(O34:O35) -> 0 | P36: =P33-SUM(P34:P35) -> 0 | Q36: =Q33-SUM(Q34:Q35) -> 0 | ... AS36: =AS33-SUM(AS34:AS35) -> 6794155.2
C37: DTC 결제 수수료 | D37: 원 | F37: =SUM(J37:U37) -> 184212 | G37: =SUM(V37:AG37) -> 2738102.4 | H37: =SUM(AH37:AS37) -> 5851440 | J37: =J30*'01_가정'!$F$86 -> 0 | K37: =K30*'01_가정'!$F$86 -> 0 | L37: =L30*'01_가정'!$F$86 -> 0 | M37: =M30*'01_가정'!$F$86 -> 0 | N37: =N30*'01_가정'!$F$86 -> 0 | O37: =O30*'01_가정'!$F$86 -> 0 | P37: =P30*'01_가정'!$F$86 -> 0 | Q37: =Q30*'01_가정'!$F$86 -> 0 | ... AS37: =AS30*'01_가정'!$F$86 -> 487620
C38: 본체 DTC 물류비 | D38: 원 | F38: =SUM(J38:U38) -> 252000 | G38: =SUM(V38:AG38) -> 3618000 | H38: =SUM(AH38:AS38) -> 7560000 | J38: =J17*'01_가정'!$F$87 -> 0 | K38: =K17*'01_가정'!$F$87 -> 0 | L38: =L17*'01_가정'!$F$87 -> 0 | M38: =M17*'01_가정'!$F$87 -> 0 | N38: =N17*'01_가정'!$F$87 -> 0 | O38: =O17*'01_가정'!$F$87 -> 0 | P38: =P17*'01_가정'!$F$87 -> 0 | Q38: =Q17*'01_가정'!$F$87 -> 0 | ... AS38: =AS17*'01_가정'!$F$87 -> 630000
C39: 본체 반품 처리비 | D39: 원 | F39: =SUM(J39:U39) -> 50400 | G39: =SUM(V39:AG39) -> 578880 | H39: =SUM(AH39:AS39) -> 1008000 | J39: =SUM(J20,J22)*'01_가정'!$F$88 -> 0 | K39: =SUM(K20,K22)*'01_가정'!$F$88 -> 0 | L39: =SUM(L20,L22)*'01_가정'!$F$88 -> 0 | M39: =SUM(M20,M22)*'01_가정'!$F$88 -> 0 | N39: =SUM(N20,N22)*'01_가정'!$F$88 -> 0 | O39: =SUM(O20,O22)*'01_가정'!$F$88 -> 0 | P39: =SUM(P20,P22)*'01_가정'!$F$88 -> 0 | Q39: =SUM(Q20,Q22)*'01_가정'!$F$88 -> 0 | ... AS39: =SUM(AS20,AS22)*'01_가정'!$F$88 -> 84000
C40: 본체 AS 기대비용 | D40: 원 | F40: =SUM(J40:U40) -> 112000 | G40: =SUM(V40:AG40) -> 1608000 | H40: =SUM(AH40:AS40) -> 3360000 | J40: =J19*'01_가정'!$F$89 -> 0 | K40: =K19*'01_가정'!$F$89 -> 0 | L40: =L19*'01_가정'!$F$89 -> 0 | M40: =M19*'01_가정'!$F$89 -> 0 | N40: =N19*'01_가정'!$F$89 -> 0 | O40: =O19*'01_가정'!$F$89 -> 0 | P40: =P19*'01_가정'!$F$89 -> 0 | Q40: =Q19*'01_가정'!$F$89 -> 0 | ... AS40: =AS19*'01_가정'!$F$89 -> 280000
C41: 본체 변동 상담비 | D41: 원 | F41: =SUM(J41:U41) -> 56000 | G41: =SUM(V41:AG41) -> 804000 | H41: =SUM(AH41:AS41) -> 1680000 | J41: =J19*'01_가정'!$F$90 -> 0 | K41: =K19*'01_가정'!$F$90 -> 0 | L41: =L19*'01_가정'!$F$90 -> 0 | M41: =M19*'01_가정'!$F$90 -> 0 | N41: =N19*'01_가정'!$F$90 -> 0 | O41: =O19*'01_가정'!$F$90 -> 0 | P41: =P19*'01_가정'!$F$90 -> 0 | Q41: =Q19*'01_가정'!$F$90 -> 0 | ... AS41: =AS19*'01_가정'!$F$90 -> 140000
C42: 리테일 물류비 | D42: 원 | F42: =SUM(J42:U42) -> 0 | G42: =SUM(V42:AG42) -> 0 | H42: =SUM(AH42:AS42) -> 0 | J42: =J18*'01_가정'!$F$97 -> 0 | K42: =K18*'01_가정'!$F$97 -> 0 | L42: =L18*'01_가정'!$F$97 -> 0 | M42: =M18*'01_가정'!$F$97 -> 0 | N42: =N18*'01_가정'!$F$97 -> 0 | O42: =O18*'01_가정'!$F$97 -> 0 | P42: =P18*'01_가정'!$F$97 -> 0 | Q42: =Q18*'01_가정'!$F$97 -> 0 | ... AS42: =AS18*'01_가정'!$F$97 -> 0
C43: 리필 결제 수수료 | D43: 원 | F43: =SUM(J43:U43) -> 989.604 | G43: =SUM(V43:AG43) -> 76936.252 | H43: =SUM(AH43:AS43) -> 244458.35 | J43: =J32*'01_가정'!$F$92 -> 0 | K43: =K32*'01_가정'!$F$92 -> 0 | L43: =L32*'01_가정'!$F$92 -> 0 | M43: =M32*'01_가정'!$F$92 -> 0 | N43: =N32*'01_가정'!$F$92 -> 0 | O43: =O32*'01_가정'!$F$92 -> 0 | P43: =P32*'01_가정'!$F$92 -> 0 | Q43: =Q32*'01_가정'!$F$92 -> 0 | ... AS43: =AS32*'01_가정'!$F$92 -> 25925.989
C44: 리필 물류비 | D44: 원 | F44: =SUM(J44:U44) -> 10200 | G44: =SUM(V44:AG44) -> 792993.73 | H44: =SUM(AH44:AS44) -> 2519669.7 | J44: =J29*'01_가정'!$F$91 -> 0 | K44: =K29*'01_가정'!$F$91 -> 0 | L44: =L29*'01_가정'!$F$91 -> 0 | M44: =M29*'01_가정'!$F$91 -> 0 | N44: =N29*'01_가정'!$F$91 -> 0 | O44: =O29*'01_가정'!$F$91 -> 0 | P44: =P29*'01_가정'!$F$91 -> 0 | Q44: =Q29*'01_가정'!$F$91 -> 0 | ... AS44: =AS29*'01_가정'!$F$91 -> 267223.14
C45: 리필 반품 처리비 | D45: 원 | F45: =SUM(J45:U45) -> 408 | G45: =SUM(V45:AG45) -> 31719.749 | H45: =SUM(AH45:AS45) -> 100786.79 | J45: =J29*'01_가정'!$F$93*'01_가정'!$F$88 -> 0 | K45: =K29*'01_가정'!$F$93*'01_가정'!$F$88 -> 0 | L45: =L29*'01_가정'!$F$93*'01_가정'!$F$88 -> 0 | M45: =M29*'01_가정'!$F$93*'01_가정'!$F$88 -> 0 | N45: =N29*'01_가정'!$F$93*'01_가정'!$F$88 -> 0 | O45: =O29*'01_가정'!$F$93*'01_가정'!$F$88 -> 0 | P45: =P29*'01_가정'!$F$93*'01_가정'!$F$88 -> 0 | Q45: =Q29*'01_가정'!$F$93*'01_가정'!$F$88 -> 0 | ... AS45: =AS29*'01_가정'!$F$93*'01_가정'!$F$88 -> 10688.926
C46: 광고 전 공헌이익 | D46: 원 | F46: =SUM(J46:U46) -> 1010660.2 | G46: =SUM(V46:AG46) -> 20548070 | H46: =SUM(AH46:AS46) -> 56444349 | J46: =J36-SUM(J37:J45) -> 0 | K46: =K36-SUM(K37:K45) -> 0 | L46: =L36-SUM(L37:L45) -> 0 | M46: =M36-SUM(M37:M45) -> 0 | N46: =N36-SUM(N37:N45) -> 0 | O46: =O36-SUM(O37:O45) -> 0 | P46: =P36-SUM(P37:P45) -> 0 | Q46: =Q36-SUM(Q37:Q45) -> 0 | ... AS46: =AS36-SUM(AS37:AS45) -> 4868697.1
C47: 판매 광고비 | D47: 원 | F47: =SUM(J47:U47) -> 3375000 | G47: =SUM(V47:AG47) -> 36000000 | H47: =SUM(AH47:AS47) -> 60000000 | J47: =J10 -> 0 | K47: =K10 -> 0 | L47: =L10 -> 0 | M47: =M10 -> 0 | N47: =N10 -> 0 | O47: =O10 -> 0 | P47: =P10 -> 0 | Q47: =Q10 -> 0 | ... AS47: =AS10 -> 5000000
C48: 광고 후 공헌이익 | D48: 원 | F48: =SUM(J48:U48) -> -2364339.8 | G48: =SUM(V48:AG48) -> -15451930 | H48: =SUM(AH48:AS48) -> -3555650.7 | J48: =J46-J47 -> 0 | K48: =K46-K47 -> 0 | L48: =L46-L47 -> 0 | M48: =M46-M47 -> 0 | N48: =N46-N47 -> 0 | O48: =O46-O47 -> 0 | P48: =P46-P47 -> 0 | Q48: =Q46-Q47 -> 0 | ... AS48: =AS46-AS47 -> -131302.88
C49: 경제적 인건비 전액 | D49: 원 | F49: =SUM(J49:U49) -> 162000000 | G49: =SUM(V49:AG49) -> 169200000 | H49: =SUM(AH49:AS49) -> 180000000 | J49: ='01_가정'!F58*'01_가정'!F62 -> 13500000 | K49: ='01_가정'!F58*'01_가정'!F62 -> 13500000 | L49: ='01_가정'!F58*'01_가정'!F62 -> 13500000 | M49: ='01_가정'!F58*'01_가정'!F62 -> 13500000 | N49: ='01_가정'!F58*'01_가정'!F62 -> 13500000 | O49: ='01_가정'!F58*'01_가정'!F62 -> 13500000 | P49: ='01_가정'!F58*'01_가정'!F62 -> 13500000 | Q49: ='01_가정'!F58*'01_가정'!F62 -> 13500000 | R49: ='01_가정'!F58*'01_가정'!F62 -> 13500000 | S49: ='01_가정'!F58*'01_가정'!F62 -> 13500000 | T49: ='01_가정'!F58*'01_가정'!F62 -> 13500000 | U49: ='01_가정'!F58*'01_가정'!F62 -> 13500000 | V49: ='01_가정'!G58*'01_가정'!G62 -> 14100000 | W49: ='01_가정'!G58*'01_가정'!G62 -> 14100000 | X49: ='01_가정'!G58*'01_가정'!G62 -> 14100000 | Y49: ='01_가정'!G58*'01_가정'!G62 -> 14100000 | Z49: ='01_가정'!G58*'01_가정'!G62 -> 14100000 | AA49: ='01_가정'!G58*'01_가정'!G62 -> 14100000 | AB49: ='01_가정'!G58*'01_가정'!G62 -> 14100000 | AC49: ='01_가정'!G58*'01_가정'!G62 -> 14100000 | AD49: ='01_가정'!G58*'01_가정'!G62 -> 14100000 | AE49: ='01_가정'!G58*'01_가정'!G62 -> 14100000 | AF49: ='01_가정'!G58*'01_가정'!G62 -> 14100000 | AG49: ='01_가정'!G58*'01_가정'!G62 -> 14100000 | AH49: ='01_가정'!H58*'01_가정'!H62 -> 15000000 | AI49: ='01_가정'!H58*'01_가정'!H62 -> 15000000 | AJ49: ='01_가정'!H58*'01_가정'!H62 -> 15000000 | AK49: ='01_가정'!H58*'01_가정'!H62 -> 15000000 | AL49: ='01_가정'!H58*'01_가정'!H62 -> 15000000 | AM49: ='01_가정'!H58*'01_가정'!H62 -> 15000000 | AN49: ='01_가정'!H58*'01_가정'!H62 -> 15000000 | AO49: ='01_가정'!H58*'01_가정'!H62 -> 15000000 | AP49: ='01_가정'!H58*'01_가정'!H62 -> 15000000 | AQ49: ='01_가정'!H58*'01_가정'!H62 -> 15000000 | AR49: ='01_가정'!H58*'01_가정'!H62 -> 15000000 | AS49: ='01_가정'!H58*'01_가정'!H62 -> 15000000
C50: 고정 운영비 | D50: 원 | F50: =SUM(J50:U50) -> 24000000 | G50: =SUM(V50:AG50) -> 30000000 | H50: =SUM(AH50:AS50) -> 36000000 | J50: ='01_가정'!F66 -> 2000000 | K50: ='01_가정'!F66 -> 2000000 | L50: ='01_가정'!F66 -> 2000000 | M50: ='01_가정'!F66 -> 2000000 | N50: ='01_가정'!F66 -> 2000000 | O50: ='01_가정'!F66 -> 2000000 | P50: ='01_가정'!F66 -> 2000000 | Q50: ='01_가정'!F66 -> 2000000 | R50: ='01_가정'!F66 -> 2000000 | S50: ='01_가정'!F66 -> 2000000 | T50: ='01_가정'!F66 -> 2000000 | U50: ='01_가정'!F66 -> 2000000 | V50: ='01_가정'!G66 -> 2500000 | W50: ='01_가정'!G66 -> 2500000 | X50: ='01_가정'!G66 -> 2500000 | Y50: ='01_가정'!G66 -> 2500000 | Z50: ='01_가정'!G66 -> 2500000 | AA50: ='01_가정'!G66 -> 2500000 | AB50: ='01_가정'!G66 -> 2500000 | AC50: ='01_가정'!G66 -> 2500000 | AD50: ='01_가정'!G66 -> 2500000 | AE50: ='01_가정'!G66 -> 2500000 | AF50: ='01_가정'!G66 -> 2500000 | AG50: ='01_가정'!G66 -> 2500000 | AH50: ='01_가정'!H66 -> 3000000 | AI50: ='01_가정'!H66 -> 3000000 | AJ50: ='01_가정'!H66 -> 3000000 | AK50: ='01_가정'!H66 -> 3000000 | AL50: ='01_가정'!H66 -> 3000000 | AM50: ='01_가정'!H66 -> 3000000 | AN50: ='01_가정'!H66 -> 3000000 | AO50: ='01_가정'!H66 -> 3000000 | AP50: ='01_가정'!H66 -> 3000000 | AQ50: ='01_가정'!H66 -> 3000000 | AR50: ='01_가정'!H66 -> 3000000 | AS50: ='01_가정'!H66 -> 3000000
C51: 검증 및 추가 R&D 비용 | D51: 원 | F51: =SUM(J51:U51) -> 55000000 | G51: =SUM(V51:AG51) -> 18000000 | H51: =SUM(AH51:AS51) -> 18000000 | J51: ='01_가정'!$F$109*'05_100일검증'!J23 -> 2000000 | K51: ='01_가정'!$F$109*'05_100일검증'!K23 -> 3000000 | L51: ='01_가정'!$F$109*'05_100일검증'!L23 -> 3000000 | M51: ='01_가정'!$F$109*'05_100일검증'!M23+'01_가정'!$F$108 -> 17000000 | N51: ='01_가정'!$F$108 -> 15000000 | O51: ='01_가정'!$F$108 -> 15000000 | P51: =0 -> 0 | Q51: =0 -> 0 | R51: =0 -> 0 | S51: =0 -> 0 | T51: =0 -> 0 | U51: =0 -> 0 | V51: ='01_가정'!G108 -> 1500000 | W51: ='01_가정'!G108 -> 1500000 | X51: ='01_가정'!G108 -> 1500000 | Y51: ='01_가정'!G108 -> 1500000 | Z51: ='01_가정'!G108 -> 1500000 | AA51: ='01_가정'!G108 -> 1500000 | AB51: ='01_가정'!G108 -> 1500000 | AC51: ='01_가정'!G108 -> 1500000 | AD51: ='01_가정'!G108 -> 1500000 | AE51: ='01_가정'!G108 -> 1500000 | AF51: ='01_가정'!G108 -> 1500000 | AG51: ='01_가정'!G108 -> 1500000 | AH51: ='01_가정'!H108 -> 1500000 | AI51: ='01_가정'!H108 -> 1500000 | AJ51: ='01_가정'!H108 -> 1500000 | AK51: ='01_가정'!H108 -> 1500000 | AL51: ='01_가정'!H108 -> 1500000 | AM51: ='01_가정'!H108 -> 1500000 | AN51: ='01_가정'!H108 -> 1500000 | AO51: ='01_가정'!H108 -> 1500000 | AP51: ='01_가정'!H108 -> 1500000 | AQ51: ='01_가정'!H108 -> 1500000 | AR51: ='01_가정'!H108 -> 1500000 | AS51: ='01_가정'!H108 -> 1500000
C52: EBITDA | D52: 원 | F52: =SUM(J52:U52) -> -2.4336434e+08 | G52: =SUM(V52:AG52) -> -2.3265193e+08 | H52: =SUM(AH52:AS52) -> -2.3755565e+08 | J52: =J48-SUM(J49:J51) -> -17500000 | K52: =K48-SUM(K49:K51) -> -18500000 | L52: =L48-SUM(L49:L51) -> -18500000 | M52: =M48-SUM(M49:M51) -> -32500000 | N52: =N48-SUM(N49:N51) -> -30500000 | O52: =O48-SUM(O49:O51) -> -30500000 | P52: =P48-SUM(P49:P51) -> -15500000 | Q52: =Q48-SUM(Q49:Q51) -> -15500000 | ... AS52: =AS48-SUM(AS49:AS51) -> -19631303
C53: 감가상각비 | D53: 원 | F53: =SUM(J53:U53) -> 3472222.2 | G53: =SUM(V53:AG53) -> 8333333.3 | H53: =SUM(AH53:AS53) -> 8333333.3 | J53: ='04_재고현금'!J33 -> 0 | K53: ='04_재고현금'!K33 -> 0 | L53: ='04_재고현금'!L33 -> 0 | M53: ='04_재고현금'!M33 -> 0 | N53: ='04_재고현금'!N33 -> 0 | O53: ='04_재고현금'!O33 -> 0 | P53: ='04_재고현금'!P33 -> 0 | Q53: ='04_재고현금'!Q33 -> 694444.44 | ... AS53: ='04_재고현금'!AS33 -> 694444.44
C54: 영업이익 | D54: 원 | F54: =SUM(J54:U54) -> -2.4683656e+08 | G54: =SUM(V54:AG54) -> -2.4098526e+08 | H54: =SUM(AH54:AS54) -> -2.4588898e+08 | J54: =J52-J53 -> -17500000 | K54: =K52-K53 -> -18500000 | L54: =L52-L53 -> -18500000 | M54: =M52-M53 -> -32500000 | N54: =N52-N53 -> -30500000 | O54: =O52-O53 -> -30500000 | P54: =P52-P53 -> -15500000 | Q54: =Q52-Q53 -> -16194444 | ... AS54: =AS52-AS53 -> -20325747
C55: 공헌이익률 | D55: % | F55: =IF(F33>0,F48/F33,"n.a.") -> -0.421288 | G55: =IF(G33>0,G48/G33,"n.a.") -> -0.18113914 | H55: =IF(H33>0,H48/H33,"n.a.") -> -0.01924843 | J55: =IF(J33>0,J48/J33,"n.a.") -> n.a. | K55: =IF(K33>0,K48/K33,"n.a.") -> n.a. | L55: =IF(L33>0,L48/L33,"n.a.") -> n.a. | M55: =IF(M33>0,M48/M33,"n.a.") -> n.a. | N55: =IF(N33>0,N48/N33,"n.a.") -> n.a. | O55: =IF(O33>0,O48/O33,"n.a.") -> n.a. | P55: =IF(P33>0,P48/P33,"n.a.") -> n.a. | Q55: =IF(Q33>0,Q48/Q33,"n.a.") -> n.a. | ... AS55: =IF(AS33>0,AS48/AS33,"n.a.") -> -0.0084374038
C56: DTC 혼합 CAC | D56: 원 | F56: =IF(F17>0,F47/F17,"n.a.") -> 60267.857 | G56: =IF(G17>0,G47/G17,"n.a.") -> 44776.119 | H56: =IF(H17>0,H47/H17,"n.a.") -> 35714.286 | J56: =IF(J17>0,J47/J17,"n.a.") -> n.a. | K56: =IF(K17>0,K47/K17,"n.a.") -> n.a. | L56: =IF(L17>0,L47/L17,"n.a.") -> n.a. | M56: =IF(M17>0,M47/M17,"n.a.") -> n.a. | N56: =IF(N17>0,N47/N17,"n.a.") -> n.a. | O56: =IF(O17>0,O47/O17,"n.a.") -> n.a. | P56: =IF(P17>0,P47/P17,"n.a.") -> n.a. | Q56: =IF(Q17>0,Q47/Q17,"n.a.") -> n.a. | ... AS56: =IF(AS17>0,AS47/AS17,"n.a.") -> 35714.286
C57: 고정 인건비와 운영비 | D57: 원 | F57: =SUM(J57:U57) -> 186000000 | G57: =SUM(V57:AG57) -> 199200000 | H57: =SUM(AH57:AS57) -> 216000000 | J57: =SUM(J49:J50) -> 15500000 | K57: =SUM(K49:K50) -> 15500000 | L57: =SUM(L49:L50) -> 15500000 | M57: =SUM(M49:M50) -> 15500000 | N57: =SUM(N49:N50) -> 15500000 | O57: =SUM(O49:O50) -> 15500000 | P57: =SUM(P49:P50) -> 15500000 | Q57: =SUM(Q49:Q50) -> 15500000 | ... AS57: =SUM(AS49:AS50) -> 18000000
C60: 순매출은 VAT와 예상 환불 차감 후 금액입니다. 리필은 DTC 비환불 고객만 다음 달부터 참여합니다. 기대 고객 수는 소수일 수 있습니다.
C62: 인건비는 회사 지원과 관계없이 전액 반영합니다. 광고 비용과 유료 CAC를 이중 차감하지 않습니다. 매출원가는 재고 이동평균법으로 연결합니다.

Sheet 04_재고현금
C2: 발주 재고와 36개월 현금 계획
C4: 선택 시나리오 | F4: ='01_가정'!H4 -> 보수
F5: 1년차 | G5: 2년차 | H5: 3년차 | J5: =EDATE('01_가정'!$F$5,0) -> 46388 | K5: =EDATE('01_가정'!$F$5,1) -> 46419 | L5: =EDATE('01_가정'!$F$5,2) -> 46447 | M5: =EDATE('01_가정'!$F$5,3) -> 46478 | N5: =EDATE('01_가정'!$F$5,4) -> 46508 | O5: =EDATE('01_가정'!$F$5,5) -> 46539 | P5: =EDATE('01_가정'!$F$5,6) -> 46569 | Q5: =EDATE('01_가정'!$F$5,7) -> 46600 | R5: =EDATE('01_가정'!$F$5,8) -> 46631 | S5: =EDATE('01_가정'!$F$5,9) -> 46661 | T5: =EDATE('01_가정'!$F$5,10) -> 46692 | U5: =EDATE('01_가정'!$F$5,11) -> 46722 | V5: =EDATE('01_가정'!$F$5,12) -> 46753 | W5: =EDATE('01_가정'!$F$5,13) -> 46784 | X5: =EDATE('01_가정'!$F$5,14) -> 46813 | Y5: =EDATE('01_가정'!$F$5,15) -> 46844 | Z5: =EDATE('01_가정'!$F$5,16) -> 46874 | AA5: =EDATE('01_가정'!$F$5,17) -> 46905 | AB5: =EDATE('01_가정'!$F$5,18) -> 46935 | AC5: =EDATE('01_가정'!$F$5,19) -> 46966 | AD5: =EDATE('01_가정'!$F$5,20) -> 46997 | AE5: =EDATE('01_가정'!$F$5,21) -> 47027 | AF5: =EDATE('01_가정'!$F$5,22) -> 47058 | AG5: =EDATE('01_가정'!$F$5,23) -> 47088 | AH5: =EDATE('01_가정'!$F$5,24) -> 47119 | AI5: =EDATE('01_가정'!$F$5,25) -> 47150 | AJ5: =EDATE('01_가정'!$F$5,26) -> 47178 | AK5: =EDATE('01_가정'!$F$5,27) -> 47209 | AL5: =EDATE('01_가정'!$F$5,28) -> 47239 | AM5: =EDATE('01_가정'!$F$5,29) -> 47270 | AN5: =EDATE('01_가정'!$F$5,30) -> 47300 | AO5: =EDATE('01_가정'!$F$5,31) -> 47331 | AP5: =EDATE('01_가정'!$F$5,32) -> 47362 | AQ5: =EDATE('01_가정'!$F$5,33) -> 47392 | AR5: =EDATE('01_가정'!$F$5,34) -> 47423 | AS5: =EDATE('01_가정'!$F$5,35) -> 47453
J6: 1 | K6: 2 | L6: 3 | M6: 4 | N6: 5 | O6: 6 | P6: 7 | Q6: 8 | R6: 9 | S6: 10 | T6: 11 | U6: 12 | V6: 13 | W6: 14 | X6: 15 | Y6: 16 | Z6: 17 | AA6: 18 | AB6: 19 | AC6: 20 | AD6: 21 | AE6: 22 | AF6: 23 | AG6: 24 | AH6: 25 | AI6: 26 | AJ6: 27 | AK6: 28 | AL6: 29 | AM6: 30 | AN6: 31 | AO6: 32 | AP6: 33 | AQ6: 34 | AR6: 35 | AS6: 36
C8: 본체 출고 | D8: 개 | F8: =SUM(J8:U8) -> 56 | G8: =SUM(V8:AG8) -> 804 | H8: =SUM(AH8:AS8) -> 1680 | J8: ='03_월별손익'!J19 -> 0 | K8: ='03_월별손익'!K19 -> 0 | L8: ='03_월별손익'!L19 -> 0 | M8: ='03_월별손익'!M19 -> 0 | N8: ='03_월별손익'!N19 -> 0 | O8: ='03_월별손익'!O19 -> 0 | P8: ='03_월별손익'!P19 -> 0 | Q8: ='03_월별손익'!Q19 -> 0 | ... AS8: ='03_월별손익'!AS19 -> 140
C9: 기초 재고 수량 | D9: 개 | F9: =J9 -> 0 | G9: =V9 -> 244 | H9: =AH9 -> 340 | J9: =0 -> 0 | K9: =J11 -> 0 | L9: =K11 -> 0 | M9: =L11 -> 0 | N9: =M11 -> 0 | O9: =N11 -> 0 | P9: =O11 -> 0 | Q9: =P11 -> 0 | R9: =Q11 -> 0 | ... AS9: =AR11 -> 300
C10: 제품 입고 수량 | D10: 개 | F10: =SUM(J10:U10) -> 300 | G10: =SUM(V10:AG10) -> 900 | H10: =SUM(AH10:AS10) -> 1500 | J10: =IF(AND(J$6>='01_가정'!F46,MOD(J$6-'01_가정'!F46,3)=0),MAX(0,ROUNDUP((SUM('03_월별손익'!J19:L19)+'01_가정'!$F$100-J9)/'01_가정'!$F$99,0)*'01_가정'!$F$99),0) -> 0 | K10: =IF(AND(K$6>='01_가정'!F46,MOD(K$6-'01_가정'!F46,3)=0),MAX(0,ROUNDUP((SUM('03_월별손익'!K19:M19)+'01_가정'!$F$100-K9)/'01_가정'!$F$99,0)*'01_가정'!$F$99),0) -> 0 | L10: =IF(AND(L$6>='01_가정'!F46,MOD(L$6-'01_가정'!F46,3)=0),MAX(0,ROUNDUP((SUM('03_월별손익'!L19:N19)+'01_가정'!$F$100-L9)/'01_가정'!$F$99,0)*'01_가정'!$F$99),0) -> 0 | M10: =IF(AND(M$6>='01_가정'!F46,MOD(M$6-'01_가정'!F46,3)=0),MAX(0,ROUNDUP((SUM('03_월별손익'!M19:O19)+'01_가정'!$F$100-M9)/'01_가정'!$F$99,0)*'01_가정'!$F$99),0) -> 0 | N10: =IF(AND(N$6>='01_가정'!F46,MOD(N$6-'01_가정'!F46,3)=0),MAX(0,ROUNDUP((SUM('03_월별손익'!N19:P19)+'01_가정'!$F$100-N9)/'01_가정'!$F$99,0)*'01_가정'!$F$99),0) -> 0 | O10: =IF(AND(O$6>='01_가정'!F46,MOD(O$6-'01_가정'!F46,3)=0),MAX(0,ROUNDUP((SUM('03_월별손익'!O19:Q19)+'01_가정'!$F$100-O9)/'01_가정'!$F$99,0)*'01_가정'!$F$99),0) -> 0 | P10: =IF(AND(P$6>='01_가정'!F46,MOD(P$6-'01_가정'!F46,3)=0),MAX(0,ROUNDUP((SUM('03_월별손익'!P19:R19)+'01_가정'!$F$100-P9)/'01_가정'!$F$99,0)*'01_가정'!$F$99),0) -> 0 | Q10: =IF(AND(Q$6>='01_가정'!F46,MOD(Q$6-'01_가정'!F46,3)=0),MAX(0,ROUNDUP((SUM('03_월별손익'!Q19:S19)+'01_가정'!$F$100-Q9)/'01_가정'!$F$99,0)*'01_가정'!$F$99),0) -> 0 | R10: =IF(AND(R$6>='01_가정'!F46,MOD(R$6-'01_가정'!F46,3)=0),MAX(0,ROUNDUP((SUM('03_월별손익'!R19:T19)+'01_가정'!$F$100-R9)/'01_가정'!$F$99,0)*'01_가정'!$F$99),0) -> 0 | S10: =IF(AND(S$6>='01_가정'!F46,MOD(S$6-'01_가정'!F46,3)=0),MAX(0,ROUNDUP((SUM('03_월별손익'!S19:U19)+'01_가정'!$F$100-S9)/'01_가정'!$F$99,0)*'01_가정'!$F$99),0) -> 300 | T10: =IF(AND(T$6>='01_가정'!F46,MOD(T$6-'01_가정'!F46,3)=0),MAX(0,ROUNDUP((SUM('03_월별손익'!T19:V19)+'01_가정'!$F$100-T9)/'01_가정'!$F$99,0)*'01_가정'!$F$99),0) -> 0 | U10: =IF(AND(U$6>='01_가정'!F46,MOD(U$6-'01_가정'!F46,3)=0),MAX(0,ROUNDUP((SUM('03_월별손익'!U19:W19)+'01_가정'!$F$100-U9)/'01_가정'!$F$99,0)*'01_가정'!$F$99),0) -> 0 | V10: =IF(AND(V$6>='01_가정'!F46,MOD(V$6-'01_가정'!F46,3)=0),MAX(0,ROUNDUP((SUM('03_월별손익'!V19:X19)+'01_가정'!$F$100-V9)/'01_가정'!$F$99,0)*'01_가정'!$F$99),0) -> 300 | W10: =IF(AND(W$6>='01_가정'!F46,MOD(W$6-'01_가정'!F46,3)=0),MAX(0,ROUNDUP((SUM('03_월별손익'!W19:Y19)+'01_가정'!$F$100-W9)/'01_가정'!$F$99,0)*'01_가정'!$F$99),0) -> 0 | X10: =IF(AND(X$6>='01_가정'!F46,MOD(X$6-'01_가정'!F46,3)=0),MAX(0,ROUNDUP((SUM('03_월별손익'!X19:Z19)+'01_가정'!$F$100-X9)/'01_가정'!$F$99,0)*'01_가정'!$F$99),0) -> 0 | Y10: =IF(AND(Y$6>='01_가정'!F46,MOD(Y$6-'01_가정'!F46,3)=0),MAX(0,ROUNDUP((SUM('03_월별손익'!Y19:AA19)+'01_가정'!$F$100-Y9)/'01_가정'!$F$99,0)*'01_가정'!$F$99),0) -> 0 | Z10: =IF(AND(Z$6>='01_가정'!F46,MOD(Z$6-'01_가정'!F46,3)=0),MAX(0,ROUNDUP((SUM('03_월별손익'!Z19:AB19)+'01_가정'!$F$100-Z9)/'01_가정'!$F$99,0)*'01_가정'!$F$99),0) -> 0 | AA10: =IF(AND(AA$6>='01_가정'!F46,MOD(AA$6-'01_가정'!F46,3)=0),MAX(0,ROUNDUP((SUM('03_월별손익'!AA19:AC19)+'01_가정'!$F$100-AA9)/'01_가정'!$F$99,0)*'01_가정'!$F$99),0) -> 0 | AB10: =IF(AND(AB$6>='01_가정'!F46,MOD(AB$6-'01_가정'!F46,3)=0),MAX(0,ROUNDUP((SUM('03_월별손익'!AB19:AD19)+'01_가정'!$F$100-AB9)/'01_가정'!$F$99,0)*'01_가정'!$F$99),0) -> 300 | AC10: =IF(AND(AC$6>='01_가정'!F46,MOD(AC$6-'01_가정'!F46,3)=0),MAX(0,ROUNDUP((SUM('03_월별손익'!AC19:AE19)+'01_가정'!$F$100-AC9)/'01_가정'!$F$99,0)*'01_가정'!$F$99),0) -> 0 | AD10: =IF(AND(AD$6>='01_가정'!F46,MOD(AD$6-'01_가정'!F46,3)=0),MAX(0,ROUNDUP((SUM('03_월별손익'!AD19:AF19)+'01_가정'!$F$100-AD9)/'01_가정'!$F$99,0)*'01_가정'!$F$99),0) -> 0 | AE10: =IF(AND(AE$6>='01_가정'!F46,MOD(AE$6-'01_가정'!F46,3)=0),MAX(0,ROUNDUP((SUM('03_월별손익'!AE19:AG19)+'01_가정'!$F$100-AE9)/'01_가정'!$F$99,0)*'01_가정'!$F$99),0) -> 300 | AF10: =IF(AND(AF$6>='01_가정'!F46,MOD(AF$6-'01_가정'!F46,3)=0),MAX(0,ROUNDUP((SUM('03_월별손익'!AF19:AH19)+'01_가정'!$F$100-AF9)/'01_가정'!$F$99,0)*'01_가정'!$F$99),0) -> 0 | AG10: =IF(AND(AG$6>='01_가정'!F46,MOD(AG$6-'01_가정'!F46,3)=0),MAX(0,ROUNDUP((SUM('03_월별손익'!AG19:AI19)+'01_가정'!$F$100-AG9)/'01_가정'!$F$99,0)*'01_가정'!$F$99),0) -> 0 | AH10: =IF(AND(AH$6>='01_가정'!F46,MOD(AH$6-'01_가정'!F46,3)=0),MAX(0,ROUNDUP((SUM('03_월별손익'!AH19:AJ19)+'01_가정'!$F$100-AH9)/'01_가정'!$F$99,0)*'01_가정'!$F$99),0) -> 300 | AI10: =IF(AND(AI$6>='01_가정'!F46,MOD(AI$6-'01_가정'!F46,3)=0),MAX(0,ROUNDUP((SUM('03_월별손익'!AI19:AK19)+'01_가정'!$F$100-AI9)/'01_가정'!$F$99,0)*'01_가정'!$F$99),0) -> 0 | AJ10: =IF(AND(AJ$6>='01_가정'!F46,MOD(AJ$6-'01_가정'!F46,3)=0),MAX(0,ROUNDUP((SUM('03_월별손익'!AJ19:AL19)+'01_가정'!$F$100-AJ9)/'01_가정'!$F$99,0)*'01_가정'!$F$99),0) -> 0 | AK10: =IF(AND(AK$6>='01_가정'!F46,MOD(AK$6-'01_가정'!F46,3)=0),MAX(0,ROUNDUP((SUM('03_월별손익'!AK19:AM19)+'01_가정'!$F$100-AK9)/'01_가정'!$F$99,0)*'01_가정'!$F$99),0) -> 300 | AL10: =IF(AND(AL$6>='01_가정'!F46,MOD(AL$6-'01_가정'!F46,3)=0),MAX(0,ROUNDUP((SUM('03_월별손익'!AL19:AN19)+'01_가정'!$F$100-AL9)/'01_가정'!$F$99,0)*'01_가정'!$F$99),0) -> 0 | AM10: =IF(AND(AM$6>='01_가정'!F46,MOD(AM$6-'01_가정'!F46,3)=0),MAX(0,ROUNDUP((SUM('03_월별손익'!AM19:AO19)+'01_가정'!$F$100-AM9)/'01_가정'!$F$99,0)*'01_가정'!$F$99),0) -> 0 | AN10: =IF(AND(AN$6>='01_가정'!F46,MOD(AN$6-'01_가정'!F46,3)=0),MAX(0,ROUNDUP((SUM('03_월별손익'!AN19:AP19)+'01_가정'!$F$100-AN9)/'01_가정'!$F$99,0)*'01_가정'!$F$99),0) -> 600 | AO10: =IF(AND(AO$6>='01_가정'!F46,MOD(AO$6-'01_가정'!F46,3)=0),MAX(0,ROUNDUP((SUM('03_월별손익'!AO19:AQ19)+'01_가정'!$F$100-AO9)/'01_가정'!$F$99,0)*'01_가정'!$F$99),0) -> 0 | AP10: =IF(AND(AP$6>='01_가정'!F46,MOD(AP$6-'01_가정'!F46,3)=0),MAX(0,ROUNDUP((SUM('03_월별손익'!AP19:AR19)+'01_가정'!$F$100-AP9)/'01_가정'!$F$99,0)*'01_가정'!$F$99),0) -> 0 | AQ10: =IF(AND(AQ$6>='01_가정'!F46,MOD(AQ$6-'01_가정'!F46,3)=0),MAX(0,ROUNDUP((SUM('03_월별손익'!AQ19:AS19)+'01_가정'!$F$100-AQ9)/'01_가정'!$F$99,0)*'01_가정'!$F$99),0) -> 300 | AR10: =IF(AND(AR$6>='01_가정'!F46,MOD(AR$6-'01_가정'!F46,3)=0),MAX(0,ROUNDUP((SUM('03_월별손익'!AR19:AS19)+'01_가정'!$F$100-AR9)/'01_가정'!$F$99,0)*'01_가정'!$F$99),0) -> 0 | AS10: =IF(AND(AS$6>='01_가정'!F46,MOD(AS$6-'01_가정'!F46,3)=0),MAX(0,ROUNDUP((SUM('03_월별손익'!AS19:AS19)+'01_가정'!$F$100-AS9)/'01_가정'!$F$99,0)*'01_가정'!$F$99),0) -> 0
C11: 기말 재고 수량 | D11: 개 | F11: =U11 -> 244 | G11: =AG11 -> 340 | H11: =AS11 -> 160 | J11: =J9+J10-J8 -> 0 | K11: =K9+K10-K8 -> 0 | L11: =L9+L10-L8 -> 0 | M11: =M9+M10-M8 -> 0 | N11: =N9+N10-N8 -> 0 | O11: =O9+O10-O8 -> 0 | P11: =P9+P10-P8 -> 0 | Q11: =Q9+Q10-Q8 -> 0 | ... AS11: =AS9+AS10-AS8 -> 160
C12: 입고월 적용 제조단가 | D12: 원 | J12: ='01_가정'!F14 -> 70000 | K12: ='01_가정'!F14 -> 70000 | L12: ='01_가정'!F14 -> 70000 | M12: ='01_가정'!F14 -> 70000 | N12: ='01_가정'!F14 -> 70000 | O12: ='01_가정'!F14 -> 70000 | P12: ='01_가정'!F14 -> 70000 | Q12: ='01_가정'!F14 -> 70000 | R12: ='01_가정'!F14 -> 70000 | S12: ='01_가정'!F14 -> 70000 | T12: ='01_가정'!F14 -> 70000 | U12: ='01_가정'!F14 -> 70000 | V12: ='01_가정'!G14 -> 65000 | W12: ='01_가정'!G14 -> 65000 | X12: ='01_가정'!G14 -> 65000 | Y12: ='01_가정'!G14 -> 65000 | Z12: ='01_가정'!G14 -> 65000 | AA12: ='01_가정'!G14 -> 65000 | AB12: ='01_가정'!G14 -> 65000 | AC12: ='01_가정'!G14 -> 65000 | AD12: ='01_가정'!G14 -> 65000 | AE12: ='01_가정'!G14 -> 65000 | AF12: ='01_가정'!G14 -> 65000 | AG12: ='01_가정'!G14 -> 65000 | AH12: ='01_가정'!H14 -> 60000 | AI12: ='01_가정'!H14 -> 60000 | AJ12: ='01_가정'!H14 -> 60000 | AK12: ='01_가정'!H14 -> 60000 | AL12: ='01_가정'!H14 -> 60000 | AM12: ='01_가정'!H14 -> 60000 | AN12: ='01_가정'!H14 -> 60000 | AO12: ='01_가정'!H14 -> 60000 | AP12: ='01_가정'!H14 -> 60000 | AQ12: ='01_가정'!H14 -> 60000 | AR12: ='01_가정'!H14 -> 60000 | AS12: ='01_가정'!H14 -> 60000
C13: 입고 제품 공급가 합계 | D13: 원 | F13: =SUM(J13:U13) -> 21000000 | G13: =SUM(V13:AG13) -> 58500000 | H13: =SUM(AH13:AS13) -> 90000000 | J13: =J10*J12 -> 0 | K13: =K10*K12 -> 0 | L13: =L10*L12 -> 0 | M13: =M10*M12 -> 0 | N13: =N10*N12 -> 0 | O13: =O10*O12 -> 0 | P13: =P10*P12 -> 0 | Q13: =Q10*Q12 -> 0 | ... AS13: =AS10*AS12 -> 0
C14: 기초 재고 금액 | D14: 원 | F14: =J14 -> 0 | G14: =V14 -> 17080000 | H14: =AH14 -> 22209125 | J14: =0 -> 0 | K14: =J17 -> 0 | L14: =K17 -> 0 | M14: =L17 -> 0 | N14: =M17 -> 0 | O14: =N17 -> 0 | P14: =O17 -> 0 | Q14: =P17 -> 0 | R14: =Q17 -> 0 | ... AS14: =AR17 -> 18024744
C15: 이동평균 원가 | D15: 원 | J15: =IF(SUM(J9:J10)>0,(J14+J13)/SUM(J9:J10),0) -> 0 | K15: =IF(SUM(K9:K10)>0,(K14+K13)/SUM(K9:K10),0) -> 0 | L15: =IF(SUM(L9:L10)>0,(L14+L13)/SUM(L9:L10),0) -> 0 | M15: =IF(SUM(M9:M10)>0,(M14+M13)/SUM(M9:M10),0) -> 0 | N15: =IF(SUM(N9:N10)>0,(N14+N13)/SUM(N9:N10),0) -> 0 | O15: =IF(SUM(O9:O10)>0,(O14+O13)/SUM(O9:O10),0) -> 0 | P15: =IF(SUM(P9:P10)>0,(P14+P13)/SUM(P9:P10),0) -> 0 | Q15: =IF(SUM(Q9:Q10)>0,(Q14+Q13)/SUM(Q9:Q10),0) -> 0 | ... AS15: =IF(SUM(AS9:AS10)>0,(AS14+AS13)/SUM(AS9:AS10),0) -> 60082.478
C16: 출고 매출원가 | D16: 원 | F16: =SUM(J16:U16) -> 3920000 | G16: =SUM(V16:AG16) -> 53370875 | H16: =SUM(AH16:AS16) -> 1.0259593e+08 | J16: =J8*J15 -> 0 | K16: =K8*K15 -> 0 | L16: =L8*L15 -> 0 | M16: =M8*M15 -> 0 | N16: =N8*N15 -> 0 | O16: =O8*O15 -> 0 | P16: =P8*P15 -> 0 | Q16: =Q8*Q15 -> 0 | ... AS16: =AS8*AS15 -> 8411547
C17: 기말 재고 금액 | D17: 원 | F17: =U17 -> 17080000 | G17: =AG17 -> 22209125 | H17: =AS17 -> 9613196.5 | J17: =J14+J13-J16 -> 0 | K17: =K14+K13-K16 -> 0 | L17: =L14+L13-L16 -> 0 | M17: =M14+M13-M16 -> 0 | N17: =N14+N13-N16 -> 0 | O17: =O14+O13-O16 -> 0 | P17: =P14+P13-P16 -> 0 | Q17: =Q14+Q13-Q16 -> 0 | ... AS17: =AS14+AS13-AS16 -> 9613196.5
C20: 당월 신규 발주 공급가 | D20: 원 | F20: =SUM(J20:U20) -> 40500000 | G20: =SUM(V20:AG20) -> 57000000 | H20: =SUM(AH20:AS20) -> 72000000 | J20: =IF(J$6+'01_가정'!$F$101<=36,INDEX($J$13:$AS$13,1,MIN(36,J$6+'01_가정'!$F$101)),0)+IF('01_가정'!$F$101>0,SUM($J$13:INDEX($J$13:$AS$13,1,MAX(1,MIN(36,'01_가정'!$F$101)))),0) -> 0 | K20: =IF(K$6+'01_가정'!$F$101<=36,INDEX($J$13:$AS$13,1,MIN(36,K$6+'01_가정'!$F$101)),0) -> 0 | L20: =IF(L$6+'01_가정'!$F$101<=36,INDEX($J$13:$AS$13,1,MIN(36,L$6+'01_가정'!$F$101)),0) -> 0 | M20: =IF(M$6+'01_가정'!$F$101<=36,INDEX($J$13:$AS$13,1,MIN(36,M$6+'01_가정'!$F$101)),0) -> 0 | N20: =IF(N$6+'01_가정'!$F$101<=36,INDEX($J$13:$AS$13,1,MIN(36,N$6+'01_가정'!$F$101)),0) -> 0 | O20: =IF(O$6+'01_가정'!$F$101<=36,INDEX($J$13:$AS$13,1,MIN(36,O$6+'01_가정'!$F$101)),0) -> 0 | P20: =IF(P$6+'01_가정'!$F$101<=36,INDEX($J$13:$AS$13,1,MIN(36,P$6+'01_가정'!$F$101)),0) -> 0 | Q20: =IF(Q$6+'01_가정'!$F$101<=36,INDEX($J$13:$AS$13,1,MIN(36,Q$6+'01_가정'!$F$101)),0) -> 21000000 | R20: =IF(R$6+'01_가정'!$F$101<=36,INDEX($J$13:$AS$13,1,MIN(36,R$6+'01_가정'!$F$101)),0) -> 0 | ... AS20: =IF(AS$6+'01_가정'!$F$101<=36,INDEX($J$13:$AS$13,1,MIN(36,AS$6+'01_가정'!$F$101)),0) -> 0
C21: 제조 선금 지급 VAT 포함 | D21: 원 | F21: =SUM(J21:U21) -> 22275000 | G21: =SUM(V21:AG21) -> 31350000 | H21: =SUM(AH21:AS21) -> 39600000 | J21: =J20*'01_가정'!$F$102*(1+'01_가정'!$F$85) -> 0 | K21: =K20*'01_가정'!$F$102*(1+'01_가정'!$F$85) -> 0 | L21: =L20*'01_가정'!$F$102*(1+'01_가정'!$F$85) -> 0 | M21: =M20*'01_가정'!$F$102*(1+'01_가정'!$F$85) -> 0 | N21: =N20*'01_가정'!$F$102*(1+'01_가정'!$F$85) -> 0 | O21: =O20*'01_가정'!$F$102*(1+'01_가정'!$F$85) -> 0 | P21: =P20*'01_가정'!$F$102*(1+'01_가정'!$F$85) -> 0 | Q21: =Q20*'01_가정'!$F$102*(1+'01_가정'!$F$85) -> 11550000 | ... AS21: =AS20*'01_가정'!$F$102*(1+'01_가정'!$F$85) -> 0
C22: 제조 잔금 지급 VAT 포함 | D22: 원 | F22: =SUM(J22:U22) -> 11550000 | G22: =SUM(V22:AG22) -> 32175000 | H22: =SUM(AH22:AS22) -> 49500000 | J22: =J13*(1-'01_가정'!$F$102)*(1+'01_가정'!$F$85) -> 0 | K22: =K13*(1-'01_가정'!$F$102)*(1+'01_가정'!$F$85) -> 0 | L22: =L13*(1-'01_가정'!$F$102)*(1+'01_가정'!$F$85) -> 0 | M22: =M13*(1-'01_가정'!$F$102)*(1+'01_가정'!$F$85) -> 0 | N22: =N13*(1-'01_가정'!$F$102)*(1+'01_가정'!$F$85) -> 0 | O22: =O13*(1-'01_가정'!$F$102)*(1+'01_가정'!$F$85) -> 0 | P22: =P13*(1-'01_가정'!$F$102)*(1+'01_가정'!$F$85) -> 0 | Q22: =Q13*(1-'01_가정'!$F$102)*(1+'01_가정'!$F$85) -> 0 | ... AS22: =AS13*(1-'01_가정'!$F$102)*(1+'01_가정'!$F$85) -> 0
C23: 제조 현금 지급 합계 | D23: 원 | F23: =SUM(J23:U23) -> 33825000 | G23: =SUM(V23:AG23) -> 63525000 | H23: =SUM(AH23:AS23) -> 89100000 | J23: =SUM(J21:J22) -> 0 | K23: =SUM(K21:K22) -> 0 | L23: =SUM(L21:L22) -> 0 | M23: =SUM(M21:M22) -> 0 | N23: =SUM(N21:N22) -> 0 | O23: =SUM(O21:O22) -> 0 | P23: =SUM(P21:P22) -> 0 | Q23: =SUM(Q21:Q22) -> 11550000 | ... AS23: =SUM(AS21:AS22) -> 0
C24: 기말 선급금 VAT 포함 | D24: 원 | F24: =U24 -> 10725000 | G24: =AG24 -> 9900000 | H24: =AS24 -> 0 | J24: =0+J21-J13*'01_가정'!$F$102*(1+'01_가정'!$F$85) -> 0 | K24: =J24+K21-K13*'01_가정'!$F$102*(1+'01_가정'!$F$85) -> 0 | L24: =K24+L21-L13*'01_가정'!$F$102*(1+'01_가정'!$F$85) -> 0 | M24: =L24+M21-M13*'01_가정'!$F$102*(1+'01_가정'!$F$85) -> 0 | N24: =M24+N21-N13*'01_가정'!$F$102*(1+'01_가정'!$F$85) -> 0 | O24: =N24+O21-O13*'01_가정'!$F$102*(1+'01_가정'!$F$85) -> 0 | P24: =O24+P21-P13*'01_가정'!$F$102*(1+'01_가정'!$F$85) -> 0 | Q24: =P24+Q21-Q13*'01_가정'!$F$102*(1+'01_가정'!$F$85) -> 11550000 | R24: =Q24+R21-R13*'01_가정'!$F$102*(1+'01_가정'!$F$85) -> 11550000 | ... AS24: =AR24+AS21-AS13*'01_가정'!$F$102*(1+'01_가정'!$F$85) -> 0
C25: 기말 납품 매출채권 VAT 포함 | D25: 원 | F25: =U25 -> 0 | G25: =AG25 -> 0 | H25: =AS25 -> 0 | J25: =0+'03_월별손익'!J31*(1+'01_가정'!$F$85)-J27 -> 0 | K25: =J25+'03_월별손익'!K31*(1+'01_가정'!$F$85)-K27 -> 0 | L25: =K25+'03_월별손익'!L31*(1+'01_가정'!$F$85)-L27 -> 0 | M25: =L25+'03_월별손익'!M31*(1+'01_가정'!$F$85)-M27 -> 0 | N25: =M25+'03_월별손익'!N31*(1+'01_가정'!$F$85)-N27 -> 0 | O25: =N25+'03_월별손익'!O31*(1+'01_가정'!$F$85)-O27 -> 0 | P25: =O25+'03_월별손익'!P31*(1+'01_가정'!$F$85)-P27 -> 0 | Q25: =P25+'03_월별손익'!Q31*(1+'01_가정'!$F$85)-Q27 -> 0 | R25: =Q25+'03_월별손익'!R31*(1+'01_가정'!$F$85)-R27 -> 0 | ... AS25: =AR25+'03_월별손익'!AS31*(1+'01_가정'!$F$85)-AS27 -> 0
C26: DTC 본체 수금 VAT 포함 | D26: 원 | F26: =SUM(J26:U26) -> 6140400 | G26: =SUM(V26:AG26) -> 91270080 | H26: =SUM(AH26:AS26) -> 195048000 | J26: ='03_월별손익'!J30*(1+'01_가정'!$F$85) -> 0 | K26: ='03_월별손익'!K30*(1+'01_가정'!$F$85) -> 0 | L26: ='03_월별손익'!L30*(1+'01_가정'!$F$85) -> 0 | M26: ='03_월별손익'!M30*(1+'01_가정'!$F$85) -> 0 | N26: ='03_월별손익'!N30*(1+'01_가정'!$F$85) -> 0 | O26: ='03_월별손익'!O30*(1+'01_가정'!$F$85) -> 0 | P26: ='03_월별손익'!P30*(1+'01_가정'!$F$85) -> 0 | Q26: ='03_월별손익'!Q30*(1+'01_가정'!$F$85) -> 0 | ... AS26: ='03_월별손익'!AS30*(1+'01_가정'!$F$85) -> 16254000
C27: 리테일 수금 VAT 포함 | D27: 원 | F27: =SUM(J27:U27) -> 0 | G27: =SUM(V27:AG27) -> 0 | H27: =SUM(AH27:AS27) -> 0 | J27: =IF(J$6>'01_가정'!$F$96,INDEX('03_월별손익'!$J$31:$AS$31,1,MAX(1,J$6-'01_가정'!$F$96))*(1+'01_가정'!$F$85),0) -> 0 | K27: =IF(K$6>'01_가정'!$F$96,INDEX('03_월별손익'!$J$31:$AS$31,1,MAX(1,K$6-'01_가정'!$F$96))*(1+'01_가정'!$F$85),0) -> 0 | L27: =IF(L$6>'01_가정'!$F$96,INDEX('03_월별손익'!$J$31:$AS$31,1,MAX(1,L$6-'01_가정'!$F$96))*(1+'01_가정'!$F$85),0) -> 0 | M27: =IF(M$6>'01_가정'!$F$96,INDEX('03_월별손익'!$J$31:$AS$31,1,MAX(1,M$6-'01_가정'!$F$96))*(1+'01_가정'!$F$85),0) -> 0 | N27: =IF(N$6>'01_가정'!$F$96,INDEX('03_월별손익'!$J$31:$AS$31,1,MAX(1,N$6-'01_가정'!$F$96))*(1+'01_가정'!$F$85),0) -> 0 | O27: =IF(O$6>'01_가정'!$F$96,INDEX('03_월별손익'!$J$31:$AS$31,1,MAX(1,O$6-'01_가정'!$F$96))*(1+'01_가정'!$F$85),0) -> 0 | P27: =IF(P$6>'01_가정'!$F$96,INDEX('03_월별손익'!$J$31:$AS$31,1,MAX(1,P$6-'01_가정'!$F$96))*(1+'01_가정'!$F$85),0) -> 0 | Q27: =IF(Q$6>'01_가정'!$F$96,INDEX('03_월별손익'!$J$31:$AS$31,1,MAX(1,Q$6-'01_가정'!$F$96))*(1+'01_가정'!$F$85),0) -> 0 | ... AS27: =IF(AS$6>'01_가정'!$F$96,INDEX('03_월별손익'!$J$31:$AS$31,1,MAX(1,AS$6-'01_가정'!$F$96))*(1+'01_가정'!$F$85),0) -> 0
C28: 리필 수금 VAT 포함 | D28: 원 | F28: =SUM(J28:U28) -> 32986.8 | G28: =SUM(V28:AG28) -> 2564541.7 | H28: =SUM(AH28:AS28) -> 8148611.7 | J28: ='03_월별손익'!J32*(1+'01_가정'!$F$85) -> 0 | K28: ='03_월별손익'!K32*(1+'01_가정'!$F$85) -> 0 | L28: ='03_월별손익'!L32*(1+'01_가정'!$F$85) -> 0 | M28: ='03_월별손익'!M32*(1+'01_가정'!$F$85) -> 0 | N28: ='03_월별손익'!N32*(1+'01_가정'!$F$85) -> 0 | O28: ='03_월별손익'!O32*(1+'01_가정'!$F$85) -> 0 | P28: ='03_월별손익'!P32*(1+'01_가정'!$F$85) -> 0 | Q28: ='03_월별손익'!Q32*(1+'01_가정'!$F$85) -> 0 | ... AS28: ='03_월별손익'!AS32*(1+'01_가정'!$F$85) -> 864199.65
C29: 현금 수입 합계 | D29: 원 | F29: =SUM(J29:U29) -> 6173386.8 | G29: =SUM(V29:AG29) -> 93834622 | H29: =SUM(AH29:AS29) -> 2.0319661e+08 | J29: =SUM(J26:J28) -> 0 | K29: =SUM(K26:K28) -> 0 | L29: =SUM(L26:L28) -> 0 | M29: =SUM(M26:M28) -> 0 | N29: =SUM(N26:N28) -> 0 | O29: =SUM(O26:O28) -> 0 | P29: =SUM(P26:P28) -> 0 | Q29: =SUM(Q26:Q28) -> 0 | ... AS29: =SUM(AS26:AS28) -> 17118200
C30: 비인건비 운영 현금 지급 | D30: 원 | F30: =SUM(J30:U30) -> 91362161 | G30: =SUM(V30:AG30) -> 1.0492378e+08 | H30: =SUM(AH30:AS30) -> 1.5365231e+08 | J30: =SUM('03_월별손익'!J35,'03_월별손익'!J37:J45,'03_월별손익'!J47,'03_월별손익'!J50:J51)*(1+'01_가정'!$F$85) -> 4400000 | K30: =SUM('03_월별손익'!K35,'03_월별손익'!K37:K45,'03_월별손익'!K47,'03_월별손익'!K50:K51)*(1+'01_가정'!$F$85) -> 5500000 | L30: =SUM('03_월별손익'!L35,'03_월별손익'!L37:L45,'03_월별손익'!L47,'03_월별손익'!L50:L51)*(1+'01_가정'!$F$85) -> 5500000 | M30: =SUM('03_월별손익'!M35,'03_월별손익'!M37:M45,'03_월별손익'!M47,'03_월별손익'!M50:M51)*(1+'01_가정'!$F$85) -> 20900000 | N30: =SUM('03_월별손익'!N35,'03_월별손익'!N37:N45,'03_월별손익'!N47,'03_월별손익'!N50:N51)*(1+'01_가정'!$F$85) -> 18700000 | O30: =SUM('03_월별손익'!O35,'03_월별손익'!O37:O45,'03_월별손익'!O47,'03_월별손익'!O50:O51)*(1+'01_가정'!$F$85) -> 18700000 | P30: =SUM('03_월별손익'!P35,'03_월별손익'!P37:P45,'03_월별손익'!P47,'03_월별손익'!P50:P51)*(1+'01_가정'!$F$85) -> 2200000 | Q30: =SUM('03_월별손익'!Q35,'03_월별손익'!Q37:Q45,'03_월별손익'!Q47,'03_월별손익'!Q50:Q51)*(1+'01_가정'!$F$85) -> 2200000 | ... AS30: =SUM('03_월별손익'!AS35,'03_월별손익'!AS37:AS45,'03_월별손익'!AS47,'03_월별손익'!AS50:AS51)*(1+'01_가정'!$F$85) -> 12959931
C31: 인건비 현금 지급 | D31: 원 | F31: =SUM(J31:U31) -> 162000000 | G31: =SUM(V31:AG31) -> 169200000 | H31: =SUM(AH31:AS31) -> 180000000 | J31: ='03_월별손익'!J49*(1-'01_가정'!$F$107) -> 13500000 | K31: ='03_월별손익'!K49*(1-'01_가정'!$F$107) -> 13500000 | L31: ='03_월별손익'!L49*(1-'01_가정'!$F$107) -> 13500000 | M31: ='03_월별손익'!M49*(1-'01_가정'!$F$107) -> 13500000 | N31: ='03_월별손익'!N49*(1-'01_가정'!$F$107) -> 13500000 | O31: ='03_월별손익'!O49*(1-'01_가정'!$F$107) -> 13500000 | P31: ='03_월별손익'!P49*(1-'01_가정'!$F$107) -> 13500000 | Q31: ='03_월별손익'!Q49*(1-'01_가정'!$F$107) -> 13500000 | ... AS31: ='03_월별손익'!AS49*(1-'01_가정'!$F$107) -> 15000000
C32: 금형 설비 현금 지급 | D32: 원 | F32: =SUM(J32:U32) -> 27500000 | G32: =SUM(V32:AG32) -> 0 | H32: =SUM(AH32:AS32) -> 0 | J32: =IF(J$6=MAX(1,'01_가정'!F46-2),'01_가정'!$F$103*(1+'01_가정'!$F$85),0) -> 0 | K32: =IF(K$6=MAX(1,'01_가정'!F46-2),'01_가정'!$F$103*(1+'01_가정'!$F$85),0) -> 0 | L32: =IF(L$6=MAX(1,'01_가정'!F46-2),'01_가정'!$F$103*(1+'01_가정'!$F$85),0) -> 0 | M32: =IF(M$6=MAX(1,'01_가정'!F46-2),'01_가정'!$F$103*(1+'01_가정'!$F$85),0) -> 0 | N32: =IF(N$6=MAX(1,'01_가정'!F46-2),'01_가정'!$F$103*(1+'01_가정'!$F$85),0) -> 0 | O32: =IF(O$6=MAX(1,'01_가정'!F46-2),'01_가정'!$F$103*(1+'01_가정'!$F$85),0) -> 0 | P32: =IF(P$6=MAX(1,'01_가정'!F46-2),'01_가정'!$F$103*(1+'01_가정'!$F$85),0) -> 0 | Q32: =IF(Q$6=MAX(1,'01_가정'!F46-2),'01_가정'!$F$103*(1+'01_가정'!$F$85),0) -> 27500000 | R32: =IF(R$6=MAX(1,'01_가정'!F46-2),'01_가정'!$F$103*(1+'01_가정'!$F$85),0) -> 0 | S32: =IF(S$6=MAX(1,'01_가정'!F46-2),'01_가정'!$F$103*(1+'01_가정'!$F$85),0) -> 0 | T32: =IF(T$6=MAX(1,'01_가정'!F46-2),'01_가정'!$F$103*(1+'01_가정'!$F$85),0) -> 0 | U32: =IF(U$6=MAX(1,'01_가정'!F46-2),'01_가정'!$F$103*(1+'01_가정'!$F$85),0) -> 0 | V32: =IF(V$6=MAX(1,'01_가정'!F46-2),'01_가정'!$F$103*(1+'01_가정'!$F$85),0) -> 0 | W32: =IF(W$6=MAX(1,'01_가정'!F46-2),'01_가정'!$F$103*(1+'01_가정'!$F$85),0) -> 0 | X32: =IF(X$6=MAX(1,'01_가정'!F46-2),'01_가정'!$F$103*(1+'01_가정'!$F$85),0) -> 0 | Y32: =IF(Y$6=MAX(1,'01_가정'!F46-2),'01_가정'!$F$103*(1+'01_가정'!$F$85),0) -> 0 | Z32: =IF(Z$6=MAX(1,'01_가정'!F46-2),'01_가정'!$F$103*(1+'01_가정'!$F$85),0) -> 0 | AA32: =IF(AA$6=MAX(1,'01_가정'!F46-2),'01_가정'!$F$103*(1+'01_가정'!$F$85),0) -> 0 | AB32: =IF(AB$6=MAX(1,'01_가정'!F46-2),'01_가정'!$F$103*(1+'01_가정'!$F$85),0) -> 0 | AC32: =IF(AC$6=MAX(1,'01_가정'!F46-2),'01_가정'!$F$103*(1+'01_가정'!$F$85),0) -> 0 | AD32: =IF(AD$6=MAX(1,'01_가정'!F46-2),'01_가정'!$F$103*(1+'01_가정'!$F$85),0) -> 0 | AE32: =IF(AE$6=MAX(1,'01_가정'!F46-2),'01_가정'!$F$103*(1+'01_가정'!$F$85),0) -> 0 | AF32: =IF(AF$6=MAX(1,'01_가정'!F46-2),'01_가정'!$F$103*(1+'01_가정'!$F$85),0) -> 0 | AG32: =IF(AG$6=MAX(1,'01_가정'!F46-2),'01_가정'!$F$103*(1+'01_가정'!$F$85),0) -> 0 | AH32: =IF(AH$6=MAX(1,'01_가정'!F46-2),'01_가정'!$F$103*(1+'01_가정'!$F$85),0) -> 0 | AI32: =IF(AI$6=MAX(1,'01_가정'!F46-2),'01_가정'!$F$103*(1+'01_가정'!$F$85),0) -> 0 | AJ32: =IF(AJ$6=MAX(1,'01_가정'!F46-2),'01_가정'!$F$103*(1+'01_가정'!$F$85),0) -> 0 | AK32: =IF(AK$6=MAX(1,'01_가정'!F46-2),'01_가정'!$F$103*(1+'01_가정'!$F$85),0) -> 0 | AL32: =IF(AL$6=MAX(1,'01_가정'!F46-2),'01_가정'!$F$103*(1+'01_가정'!$F$85),0) -> 0 | AM32: =IF(AM$6=MAX(1,'01_가정'!F46-2),'01_가정'!$F$103*(1+'01_가정'!$F$85),0) -> 0 | AN32: =IF(AN$6=MAX(1,'01_가정'!F46-2),'01_가정'!$F$103*(1+'01_가정'!$F$85),0) -> 0 | AO32: =IF(AO$6=MAX(1,'01_가정'!F46-2),'01_가정'!$F$103*(1+'01_가정'!$F$85),0) -> 0 | AP32: =IF(AP$6=MAX(1,'01_가정'!F46-2),'01_가정'!$F$103*(1+'01_가정'!$F$85),0) -> 0 | AQ32: =IF(AQ$6=MAX(1,'01_가정'!F46-2),'01_가정'!$F$103*(1+'01_가정'!$F$85),0) -> 0 | AR32: =IF(AR$6=MAX(1,'01_가정'!F46-2),'01_가정'!$F$103*(1+'01_가정'!$F$85),0) -> 0 | AS32: =IF(AS$6=MAX(1,'01_가정'!F46-2),'01_가정'!$F$103*(1+'01_가정'!$F$85),0) -> 0
C33: 감가상각비 | D33: 원 | F33: =SUM(J33:U33) -> 3472222.2 | G33: =SUM(V33:AG33) -> 8333333.3 | H33: =SUM(AH33:AS33) -> 8333333.3 | J33: =IF(AND(J$6>=MAX(1,'01_가정'!F46-2),J$6<MAX(1,'01_가정'!F46-2)+'01_가정'!$F$104),'01_가정'!$F$103/'01_가정'!$F$104,0) -> 0 | K33: =IF(AND(K$6>=MAX(1,'01_가정'!F46-2),K$6<MAX(1,'01_가정'!F46-2)+'01_가정'!$F$104),'01_가정'!$F$103/'01_가정'!$F$104,0) -> 0 | L33: =IF(AND(L$6>=MAX(1,'01_가정'!F46-2),L$6<MAX(1,'01_가정'!F46-2)+'01_가정'!$F$104),'01_가정'!$F$103/'01_가정'!$F$104,0) -> 0 | M33: =IF(AND(M$6>=MAX(1,'01_가정'!F46-2),M$6<MAX(1,'01_가정'!F46-2)+'01_가정'!$F$104),'01_가정'!$F$103/'01_가정'!$F$104,0) -> 0 | N33: =IF(AND(N$6>=MAX(1,'01_가정'!F46-2),N$6<MAX(1,'01_가정'!F46-2)+'01_가정'!$F$104),'01_가정'!$F$103/'01_가정'!$F$104,0) -> 0 | O33: =IF(AND(O$6>=MAX(1,'01_가정'!F46-2),O$6<MAX(1,'01_가정'!F46-2)+'01_가정'!$F$104),'01_가정'!$F$103/'01_가정'!$F$104,0) -> 0 | P33: =IF(AND(P$6>=MAX(1,'01_가정'!F46-2),P$6<MAX(1,'01_가정'!F46-2)+'01_가정'!$F$104),'01_가정'!$F$103/'01_가정'!$F$104,0) -> 0 | Q33: =IF(AND(Q$6>=MAX(1,'01_가정'!F46-2),Q$6<MAX(1,'01_가정'!F46-2)+'01_가정'!$F$104),'01_가정'!$F$103/'01_가정'!$F$104,0) -> 694444.44 | R33: =IF(AND(R$6>=MAX(1,'01_가정'!F46-2),R$6<MAX(1,'01_가정'!F46-2)+'01_가정'!$F$104),'01_가정'!$F$103/'01_가정'!$F$104,0) -> 694444.44 | S33: =IF(AND(S$6>=MAX(1,'01_가정'!F46-2),S$6<MAX(1,'01_가정'!F46-2)+'01_가정'!$F$104),'01_가정'!$F$103/'01_가정'!$F$104,0) -> 694444.44 | T33: =IF(AND(T$6>=MAX(1,'01_가정'!F46-2),T$6<MAX(1,'01_가정'!F46-2)+'01_가정'!$F$104),'01_가정'!$F$103/'01_가정'!$F$104,0) -> 694444.44 | U33: =IF(AND(U$6>=MAX(1,'01_가정'!F46-2),U$6<MAX(1,'01_가정'!F46-2)+'01_가정'!$F$104),'01_가정'!$F$103/'01_가정'!$F$104,0) -> 694444.44 | V33: =IF(AND(V$6>=MAX(1,'01_가정'!F46-2),V$6<MAX(1,'01_가정'!F46-2)+'01_가정'!$F$104),'01_가정'!$F$103/'01_가정'!$F$104,0) -> 694444.44 | W33: =IF(AND(W$6>=MAX(1,'01_가정'!F46-2),W$6<MAX(1,'01_가정'!F46-2)+'01_가정'!$F$104),'01_가정'!$F$103/'01_가정'!$F$104,0) -> 694444.44 | X33: =IF(AND(X$6>=MAX(1,'01_가정'!F46-2),X$6<MAX(1,'01_가정'!F46-2)+'01_가정'!$F$104),'01_가정'!$F$103/'01_가정'!$F$104,0) -> 694444.44 | Y33: =IF(AND(Y$6>=MAX(1,'01_가정'!F46-2),Y$6<MAX(1,'01_가정'!F46-2)+'01_가정'!$F$104),'01_가정'!$F$103/'01_가정'!$F$104,0) -> 694444.44 | Z33: =IF(AND(Z$6>=MAX(1,'01_가정'!F46-2),Z$6<MAX(1,'01_가정'!F46-2)+'01_가정'!$F$104),'01_가정'!$F$103/'01_가정'!$F$104,0) -> 694444.44 | AA33: =IF(AND(AA$6>=MAX(1,'01_가정'!F46-2),AA$6<MAX(1,'01_가정'!F46-2)+'01_가정'!$F$104),'01_가정'!$F$103/'01_가정'!$F$104,0) -> 694444.44 | AB33: =IF(AND(AB$6>=MAX(1,'01_가정'!F46-2),AB$6<MAX(1,'01_가정'!F46-2)+'01_가정'!$F$104),'01_가정'!$F$103/'01_가정'!$F$104,0) -> 694444.44 | AC33: =IF(AND(AC$6>=MAX(1,'01_가정'!F46-2),AC$6<MAX(1,'01_가정'!F46-2)+'01_가정'!$F$104),'01_가정'!$F$103/'01_가정'!$F$104,0) -> 694444.44 | AD33: =IF(AND(AD$6>=MAX(1,'01_가정'!F46-2),AD$6<MAX(1,'01_가정'!F46-2)+'01_가정'!$F$104),'01_가정'!$F$103/'01_가정'!$F$104,0) -> 694444.44 | AE33: =IF(AND(AE$6>=MAX(1,'01_가정'!F46-2),AE$6<MAX(1,'01_가정'!F46-2)+'01_가정'!$F$104),'01_가정'!$F$103/'01_가정'!$F$104,0) -> 694444.44 | AF33: =IF(AND(AF$6>=MAX(1,'01_가정'!F46-2),AF$6<MAX(1,'01_가정'!F46-2)+'01_가정'!$F$104),'01_가정'!$F$103/'01_가정'!$F$104,0) -> 694444.44 | AG33: =IF(AND(AG$6>=MAX(1,'01_가정'!F46-2),AG$6<MAX(1,'01_가정'!F46-2)+'01_가정'!$F$104),'01_가정'!$F$103/'01_가정'!$F$104,0) -> 694444.44 | AH33: =IF(AND(AH$6>=MAX(1,'01_가정'!F46-2),AH$6<MAX(1,'01_가정'!F46-2)+'01_가정'!$F$104),'01_가정'!$F$103/'01_가정'!$F$104,0) -> 694444.44 | AI33: =IF(AND(AI$6>=MAX(1,'01_가정'!F46-2),AI$6<MAX(1,'01_가정'!F46-2)+'01_가정'!$F$104),'01_가정'!$F$103/'01_가정'!$F$104,0) -> 694444.44 | AJ33: =IF(AND(AJ$6>=MAX(1,'01_가정'!F46-2),AJ$6<MAX(1,'01_가정'!F46-2)+'01_가정'!$F$104),'01_가정'!$F$103/'01_가정'!$F$104,0) -> 694444.44 | AK33: =IF(AND(AK$6>=MAX(1,'01_가정'!F46-2),AK$6<MAX(1,'01_가정'!F46-2)+'01_가정'!$F$104),'01_가정'!$F$103/'01_가정'!$F$104,0) -> 694444.44 | AL33: =IF(AND(AL$6>=MAX(1,'01_가정'!F46-2),AL$6<MAX(1,'01_가정'!F46-2)+'01_가정'!$F$104),'01_가정'!$F$103/'01_가정'!$F$104,0) -> 694444.44 | AM33: =IF(AND(AM$6>=MAX(1,'01_가정'!F46-2),AM$6<MAX(1,'01_가정'!F46-2)+'01_가정'!$F$104),'01_가정'!$F$103/'01_가정'!$F$104,0) -> 694444.44 | AN33: =IF(AND(AN$6>=MAX(1,'01_가정'!F46-2),AN$6<MAX(1,'01_가정'!F46-2)+'01_가정'!$F$104),'01_가정'!$F$103/'01_가정'!$F$104,0) -> 694444.44 | AO33: =IF(AND(AO$6>=MAX(1,'01_가정'!F46-2),AO$6<MAX(1,'01_가정'!F46-2)+'01_가정'!$F$104),'01_가정'!$F$103/'01_가정'!$F$104,0) -> 694444.44 | AP33: =IF(AND(AP$6>=MAX(1,'01_가정'!F46-2),AP$6<MAX(1,'01_가정'!F46-2)+'01_가정'!$F$104),'01_가정'!$F$103/'01_가정'!$F$104,0) -> 694444.44 | AQ33: =IF(AND(AQ$6>=MAX(1,'01_가정'!F46-2),AQ$6<MAX(1,'01_가정'!F46-2)+'01_가정'!$F$104),'01_가정'!$F$103/'01_가정'!$F$104,0) -> 694444.44 | AR33: =IF(AND(AR$6>=MAX(1,'01_가정'!F46-2),AR$6<MAX(1,'01_가정'!F46-2)+'01_가정'!$F$104),'01_가정'!$F$103/'01_가정'!$F$104,0) -> 694444.44 | AS33: =IF(AND(AS$6>=MAX(1,'01_가정'!F46-2),AS$6<MAX(1,'01_가정'!F46-2)+'01_가정'!$F$104),'01_가정'!$F$103/'01_가정'!$F$104,0) -> 694444.44
C34: 매출 VAT 발생 | D34: 원 | F34: =SUM(J34:U34) -> 561216.98 | G34: =SUM(V34:AG34) -> 8530420.2 | H34: =SUM(AH34:AS34) -> 18472419 | J34: ='03_월별손익'!J33*'01_가정'!$F$85 -> 0 | K34: ='03_월별손익'!K33*'01_가정'!$F$85 -> 0 | L34: ='03_월별손익'!L33*'01_가정'!$F$85 -> 0 | M34: ='03_월별손익'!M33*'01_가정'!$F$85 -> 0 | N34: ='03_월별손익'!N33*'01_가정'!$F$85 -> 0 | O34: ='03_월별손익'!O33*'01_가정'!$F$85 -> 0 | P34: ='03_월별손익'!P33*'01_가정'!$F$85 -> 0 | Q34: ='03_월별손익'!Q33*'01_가정'!$F$85 -> 0 | ... AS34: ='03_월별손익'!AS33*'01_가정'!$F$85 -> 1556200
C35: 매입 VAT 공제 가정 | D35: 원 | F35: =SUM(J35:U35) -> 12905651 | G35: =SUM(V35:AG35) -> 15388526 | H35: =SUM(AH35:AS35) -> 22968391 | J35: =(J13+(J30+J32)/(1+'01_가정'!$F$85))*'01_가정'!$F$85 -> 400000 | K35: =(K13+(K30+K32)/(1+'01_가정'!$F$85))*'01_가정'!$F$85 -> 500000 | L35: =(L13+(L30+L32)/(1+'01_가정'!$F$85))*'01_가정'!$F$85 -> 500000 | M35: =(M13+(M30+M32)/(1+'01_가정'!$F$85))*'01_가정'!$F$85 -> 1900000 | N35: =(N13+(N30+N32)/(1+'01_가정'!$F$85))*'01_가정'!$F$85 -> 1700000 | O35: =(O13+(O30+O32)/(1+'01_가정'!$F$85))*'01_가정'!$F$85 -> 1700000 | P35: =(P13+(P30+P32)/(1+'01_가정'!$F$85))*'01_가정'!$F$85 -> 200000 | Q35: =(Q13+(Q30+Q32)/(1+'01_가정'!$F$85))*'01_가정'!$F$85 -> 2700000 | ... AS35: =(AS13+(AS30+AS32)/(1+'01_가정'!$F$85))*'01_가정'!$F$85 -> 1178175.6
C36: 기초 VAT 순부채 | D36: 원 | F36: =J36 -> 0 | G36: =V36 -> -12344434 | H36: =AH36 -> -19202539 | J36: =0 -> 0 | K36: =J38 -> -400000 | L36: =K38 -> -900000 | M36: =L38 -> -1400000 | N36: =M38 -> -3300000 | O36: =N38 -> -5000000 | P36: =O38 -> -6700000 | Q36: =P38 -> -6900000 | R36: =Q38 -> -9600000 | ... AS36: =AR38 -> -24076536
C37: 분기 후 VAT 납부 | D37: 원 | F37: =SUM(J37:U37) -> 0 | G37: =SUM(V37:AG37) -> 0 | H37: =SUM(AH37:AS37) -> 0 | J37: =IF(AND(J$6>1,MOD(MONTH(J$5)-1,3)=0),MAX(0,J36),0) -> 0 | K37: =IF(AND(K$6>1,MOD(MONTH(K$5)-1,3)=0),MAX(0,K36),0) -> 0 | L37: =IF(AND(L$6>1,MOD(MONTH(L$5)-1,3)=0),MAX(0,L36),0) -> 0 | M37: =IF(AND(M$6>1,MOD(MONTH(M$5)-1,3)=0),MAX(0,M36),0) -> 0 | N37: =IF(AND(N$6>1,MOD(MONTH(N$5)-1,3)=0),MAX(0,N36),0) -> 0 | O37: =IF(AND(O$6>1,MOD(MONTH(O$5)-1,3)=0),MAX(0,O36),0) -> 0 | P37: =IF(AND(P$6>1,MOD(MONTH(P$5)-1,3)=0),MAX(0,P36),0) -> 0 | Q37: =IF(AND(Q$6>1,MOD(MONTH(Q$5)-1,3)=0),MAX(0,Q36),0) -> 0 | ... AS37: =IF(AND(AS$6>1,MOD(MONTH(AS$5)-1,3)=0),MAX(0,AS36),0) -> 0
C38: 기말 VAT 순부채 | D38: 원 | F38: =U38 -> -12344434 | G38: =AG38 -> -19202539 | H38: =AS38 -> -23698512 | J38: =J36+J34-J35-J37 -> -400000 | K38: =K36+K34-K35-K37 -> -900000 | L38: =L36+L34-L35-L37 -> -1400000 | M38: =M36+M34-M35-M37 -> -3300000 | N38: =N36+N34-N35-N37 -> -5000000 | O38: =O36+O34-O35-O37 -> -6700000 | P38: =P36+P34-P35-P37 -> -6900000 | Q38: =Q36+Q34-Q35-Q37 -> -9600000 | ... AS38: =AS36+AS34-AS35-AS37 -> -23698512
C39: 현금 지출 합계 | D39: 원 | F39: =SUM(J39:U39) -> 3.1468716e+08 | G39: =SUM(V39:AG39) -> 3.3764878e+08 | H39: =SUM(AH39:AS39) -> 4.2275231e+08 | J39: =SUM(J23,J30:J32,J37) -> 17900000 | K39: =SUM(K23,K30:K32,K37) -> 19000000 | L39: =SUM(L23,L30:L32,L37) -> 19000000 | M39: =SUM(M23,M30:M32,M37) -> 34400000 | N39: =SUM(N23,N30:N32,N37) -> 32200000 | O39: =SUM(O23,O30:O32,O37) -> 32200000 | P39: =SUM(P23,P30:P32,P37) -> 15700000 | Q39: =SUM(Q23,Q30:Q32,Q37) -> 54750000 | ... AS39: =SUM(AS23,AS30:AS32,AS37) -> 27959931
C40: 투자 전 순현금흐름 | D40: 원 | F40: =SUM(J40:U40) -> -3.0851377e+08 | G40: =SUM(V40:AG40) -> -2.4381416e+08 | H40: =SUM(AH40:AS40) -> -2.1955569e+08 | J40: =J29-J39 -> -17900000 | K40: =K29-K39 -> -19000000 | L40: =L29-L39 -> -19000000 | M40: =M29-M39 -> -34400000 | N40: =N29-N39 -> -32200000 | O40: =O29-O39 -> -32200000 | P40: =P29-P39 -> -15700000 | Q40: =Q29-Q39 -> -54750000 | ... AS40: =AS29-AS39 -> -10841731
C41: 투자 유입 가정 | D41: 원 | F41: =SUM(J41:U41) -> 300000000 | G41: =SUM(V41:AG41) -> 0 | H41: =SUM(AH41:AS41) -> 0 | J41: ='01_가정'!$F$105 -> 300000000 | K41: =0 -> 0 | L41: =0 -> 0 | M41: =0 -> 0 | N41: =0 -> 0 | O41: =0 -> 0 | P41: =0 -> 0 | Q41: =0 -> 0 | R41: =0 -> 0 | ... AS41: =0 -> 0
C42: 기초 현금 | D42: 원 | F42: =J42 -> 0 | G42: =V42 -> -8513773.8 | H42: =AH42 -> -2.5232793e+08 | J42: =0 -> 0 | K42: =J43 -> 282100000 | L42: =K43 -> 263100000 | M42: =L43 -> 244100000 | N42: =M43 -> 209700000 | O42: =N43 -> 177500000 | P42: =O43 -> 145300000 | Q42: =P43 -> 129600000 | R42: =Q43 -> 74850000 | ... AS42: =AR43 -> -4.610419e+08
C43: 기말 현금 | D43: 원 | F43: =U43 -> -8513773.8 | G43: =AG43 -> -2.5232793e+08 | H43: =AS43 -> -4.7188363e+08 | J43: =SUM(J40:J42) -> 282100000 | K43: =SUM(K40:K42) -> 263100000 | L43: =SUM(L40:L42) -> 244100000 | M43: =SUM(M40:M42) -> 209700000 | N43: =SUM(N40:N42) -> 177500000 | O43: =SUM(O40:O42) -> 145300000 | P43: =SUM(P40:P42) -> 129600000 | Q43: =SUM(Q40:Q42) -> 74850000 | ... AS43: =SUM(AS40:AS42) -> -4.7188363e+08
C44: 최소 현금 대비 부족액 | D44: 원 | F44: =MAX(J44:U44) -> 38513774 | G44: =MAX(V44:AG44) -> 2.8232793e+08 | H44: =MAX(AH44:AS44) -> 5.0188363e+08 | J44: =MAX(0,'01_가정'!$F$106-J43) -> 0 | K44: =MAX(0,'01_가정'!$F$106-K43) -> 0 | L44: =MAX(0,'01_가정'!$F$106-L43) -> 0 | M44: =MAX(0,'01_가정'!$F$106-M43) -> 0 | N44: =MAX(0,'01_가정'!$F$106-N43) -> 0 | O44: =MAX(0,'01_가정'!$F$106-O43) -> 0 | P44: =MAX(0,'01_가정'!$F$106-P43) -> 0 | Q44: =MAX(0,'01_가정'!$F$106-Q43) -> 0 | ... AS44: =MAX(0,'01_가정'!$F$106-AS43) -> 5.0188363e+08
C46: 손익에서 환산한 현금흐름 | D46: 원 | F46: =SUM(J46:U46) -> -3.0851377e+08 | G46: =SUM(V46:AG46) -> -2.4381416e+08 | H46: =SUM(AH46:AS46) -> -2.1955569e+08 | J46: ='03_월별손익'!J52+'03_월별손익'!J49*'01_가정'!$F$107-J32/(1+'01_가정'!$F$85)-(J17-J14)-(J24-0)-(J25-0)+(J38-J36) -> -17900000 | K46: ='03_월별손익'!K52+'03_월별손익'!K49*'01_가정'!$F$107-K32/(1+'01_가정'!$F$85)-(K17-K14)-(K24-J24)-(K25-J25)+(K38-K36) -> -19000000 | L46: ='03_월별손익'!L52+'03_월별손익'!L49*'01_가정'!$F$107-L32/(1+'01_가정'!$F$85)-(L17-L14)-(L24-K24)-(L25-K25)+(L38-L36) -> -19000000 | M46: ='03_월별손익'!M52+'03_월별손익'!M49*'01_가정'!$F$107-M32/(1+'01_가정'!$F$85)-(M17-M14)-(M24-L24)-(M25-L25)+(M38-M36) -> -34400000 | N46: ='03_월별손익'!N52+'03_월별손익'!N49*'01_가정'!$F$107-N32/(1+'01_가정'!$F$85)-(N17-N14)-(N24-M24)-(N25-M25)+(N38-N36) -> -32200000 | O46: ='03_월별손익'!O52+'03_월별손익'!O49*'01_가정'!$F$107-O32/(1+'01_가정'!$F$85)-(O17-O14)-(O24-N24)-(O25-N25)+(O38-O36) -> -32200000 | P46: ='03_월별손익'!P52+'03_월별손익'!P49*'01_가정'!$F$107-P32/(1+'01_가정'!$F$85)-(P17-P14)-(P24-O24)-(P25-O25)+(P38-P36) -> -15700000 | Q46: ='03_월별손익'!Q52+'03_월별손익'!Q49*'01_가정'!$F$107-Q32/(1+'01_가정'!$F$85)-(Q17-Q14)-(Q24-P24)-(Q25-P25)+(Q38-Q36) -> -54750000 | R46: ='03_월별손익'!R52+'03_월별손익'!R49*'01_가정'!$F$107-R32/(1+'01_가정'!$F$85)-(R17-R14)-(R24-Q24)-(R25-Q25)+(R38-R36) -> -15700000 | ... AS46: ='03_월별손익'!AS52+'03_월별손익'!AS49*'01_가정'!$F$107-AS32/(1+'01_가정'!$F$85)-(AS17-AS14)-(AS24-AR24)-(AS25-AR25)+(AS38-AS36) -> -10841731
C49: 3개월 수요를 최소발주량의 배수로 매입합니다. 제조단가는 입고월 기준입니다. 선금은 선행 기간 전에, 잔금은 입고월에 지급합니다. 모델 시작 전 선금은 M1에 합산하며 조기 출시의 실제 납기 가능성은 별도 확인합니다. 리필은 월별 매입·즉시 출고 가정입니다.
C51: 현금은 법인세 전이며 추가 투자 자동 유입은 없습니다. 음수는 자금 부족입니다. VAT 공제는 제품 입고 시점, DTC 환불과 결제는 당월 처리로 단순화했습니다.

Sheet 05_100일검증
C2: 100일 동안 어떤 증거를 확보할 것인가
C4: 선택 시나리오 | F4: ='01_가정'!H4 -> 보수
C5: 100일 1,000만원은 검증 게임 조건입니다. 초기 사업 전체 인건비와 양산 예산은 포함하지 않습니다. 실집행과 통과 여부는 미입력 상태입니다.
C7: 검증 항목 | D7: 수량 | E7: 단가 | F7: 계획 예산 | G7: 실집행 | H7: 잔액 | I7: 기간 | J7: 산출물 | K7: 책임 역할
C8: 규제와 의료 자문 | D8: 1 | E8: 1500000 | F8: =D8*E8 -> 1500000 | H8: =IF(COUNT(G8)=0,"미입력",F8-G8) -> 미입력 | I8: D1~15 | J8: 사용목적과 인체시험 검토 | K8: 외부 자문
C9: 고객 심층 인터뷰 | D9: 24 | E9: 30000 | F9: =D9*E9 -> 720000 | H9: =IF(COUNT(G9)=0,"미입력",F9-G9) -> 미입력 | I9: D1~25 | J9: 문제와 기존 지출 기록 | K9: 고객개발
C10: 모집과 스크리닝 | D10: 1 | E10: 280000 | F10: =D10*E10 -> 280000 | H10: =IF(COUNT(G10)=0,"미입력",F10-G10) -> 미입력 | I10: D1~25 | J10: 동의와 모집 기록 | K10: 고객개발
C11: 경쟁 제품 구매 비교 | D11: 1 | E11: 600000 | F11: =D11*E11 -> 600000 | H11: =IF(COUNT(G11)=0,"미입력",F11-G11) -> 미입력 | I11: D10~30 | J11: 동일 과제 비교표 | K11: 제품
C12: 비가동 착용 목업 | D12: 1 | E12: 1200000 | F12: =D12*E12 -> 1200000 | H12: =IF(COUNT(G12)=0,"미입력",F12-G12) -> 미입력 | I12: D15~40 | J12: 위치와 착탈 사용성 | K12: 제품
C13: 가동 시제품과 벤치시험 | D13: 1 | E13: 1800000 | F13: =D13*E13 -> 1800000 | H13: =IF(COUNT(G13)=0,"미입력",F13-G13) -> 미입력 | I13: D25~60 | J13: 온도 압력 전력 측정 | K13: 엔지니어
C14: 감독하 사용성 관찰 | D14: 24 | E14: 50000 | F14: =D14*E14 -> 1200000 | H14: =IF(COUNT(G14)=0,"미입력",F14-G14) -> 미입력 | I14: D45~80 | J14: 착용 완수와 재사용 | K14: 제품
C15: 가격과 예약 수요 실험 | D15: 1 | E15: 1100000 | F15: =D15*E15 -> 1100000 | H15: =IF(COUNT(G15)=0,"미입력",F15-G15) -> 미입력 | I15: D45~90 | J15: 유효 방문과 예약 취소 | K15: 사업관리
C16: 공급사 견적과 IP 검토 | D16: 1 | E16: 700000 | F16: =D16*E16 -> 700000 | H16: =IF(COUNT(G16)=0,"미입력",F16-G16) -> 미입력 | I16: D20~80 | J16: 3개 견적 비교 요청 | K16: 사업관리
C17: 예비비 | D17: 1 | E17: 900000 | F17: =D17*E17 -> 900000 | H17: =IF(COUNT(G17)=0,"미입력",F17-G17) -> 미입력 | I17: 게이트 통과 후 | J17: 재실험 예비비 | K17: 팀 리드
C19: 합계 | F19: =SUM(F8:F17) -> 10000000 | G19: =IF(COUNT(G8:G17)=0,"미입력",SUM(G8:G17)) -> 미입력 | H19: =IF(COUNT(G8:G17)<10,"일부 또는 전체 미입력",F19-SUM(G8:G17)) -> 일부 또는 전체 미입력
C22: 월별 검증비 지출 배분 | J22: M1 | K22: M2 | L22: M3 | M22: M4
J23: 0.2 | K23: 0.3 | L23: 0.3 | M23: 0.2
C26: 다음 투자를 위한 판단 기준
C28: 단계 | D28: 검증 기간 | E28: 제안 기준 | H28: 현재 상태 | I28: 필수 증거
C29: G0 범위와 안전 | D29: D1~15 | E29: 사용목적 및 시험 범위 서면 검토 | H29: 미확인 | I29: 규제 분류 문의와 안전 검토 기록
C30: G1 고객 문제 | D30: D1~25 | E30: 24명 중 12명 이상 최근 행동 근거 | H30: 미확인 | I30: 최근 3개월 경험과 기존 지출
C31: G2 사용성 | D31: D25~80 | E31: 24명 중 20명 독립 착용 완수 | H31: 미확인 | I31: 착용 영상, 오류, 이상반응 기록
C32: G3 지불 행동 | D32: D45~90 | E32: 3개 가격 각 300 유효 방문 | H32: 미확인 | I32: 예약금과 취소를 별도 집계
C33: G4 생산 경제성 | D33: D20~90 | E33: 견적 3개와 MOQ 현금 계획 | H33: 미확인 | I33: BOM, 리드타임, 수율 조건
C34: G5 다음 투자 | D34: D91~100 | E34: G0 통과 후 증거별 소액 집행 | H34: 미확인 | I34: 진행 수정 중단 판단서
C37: 위 수치는 팀이 사전 합의할 운영 기준 제안이며 업계 표준이나 임상 유효성 기준이 아닙니다. G3의 예약금은 판매 매출이나 구매 CAC로 인정하지 않습니다.
C39: G2는 안전 검토 후 수행하는 사용성 관찰입니다. 47℃ 등 미검증 조건의 인체 적용을 승인하지 않으며, 효능 시험은 별도 연구 설계와 심의를 검토합니다.
C42: 원문 게임 예산 산술 정정
C44: 원문 선택 카드 합계 | D44: 원 | F44: 10400000
C45: 제외한 경쟁 제품 분석 | D45: 원 | F45: 1000000
C46: 제외 후 올바른 합계 | D46: 원 | F46: =F44-F45 -> 9400000
C47: 원문 기재 제외 후 합계 | D47: 원 | F47: 9000000
C48: 기재 차이 | D48: 원 | F48: =F46-F47 -> 400000
C50: 출처 S02. 1,040만원에서 100만원을 제외하면 940만원입니다. 실제 지출 증빙은 없으며 위 새 예산은 사업 특성을 반영한 검증 계획입니다.

Sheet 06_시장경쟁
C2: 고객의 대안과 확보 가능한 시장
C4: 선택 시나리오 | F4: ='01_가정'!H4 -> 보수
C5: 생리통 대안과 마사지 대안을 분리합니다. 동일 구조 미발견은 경쟁 부재나 특허 확보의 증거가 아닙니다. 가격 조회일 2026년 10월 26일.
C7: 기업 제품 | D7: 경쟁 관계 | E7: 기술 또는 구성 | F7: 통화 | G7: 표시가 | H7: 반복 매출 | I7: 해석 | J7: 출처
C8: Myoovi 2.0 | D8: 고객 문제 대안 | E8: 복부 TENS와 온열 | F8: GBP | G8: 79.99 | H8: 교체 패드 £13.50 | I8: 지압 대비 편의와 체감 가치를 비교 | J8: W01
C9: Livia Kit | D9: 고객 문제 대안 | E9: 착용형 전기자극과 젤패드 | F9: USD | G9: 129 | H9: $29 + 월 $8 옵션 | I9: 기기와 소모품 모델은 이미 존재 | J9: W02
C10: Beurer EM50 | D10: 고객 문제 대안 | E10: 복부 TENS와 43℃ 온열 | F10: 미확인 | H10: 교체 젤패드 | I10: 결합 기능만으로 차별화 어려움 | J10: W03
C11: 칼라세븐 우먼스트레스프리 | D11: 국내 치료 대안 | E11: 생리통용 광 기반 기기 | F11: 미확인 | H11: 확인 필요 | I11: 기업 제품 소개. 허가 범위 원문 확인 필요 | J11: W04
C12: ThermaCare Menstrual | D12: 저비용 사용 대안 | E12: 의복 부착형 일회용 온열 | F12: 미확인 | H12: 일회용 교체 | I12: 8시간 온열 표방. 사용 장면 비교 | J12: W05
C13: 풀리오 종아리 V3 | D13: 마사지 예산 경쟁 | E13: 3중 에어셀 공기압 | F13: KRW | G13: 159000 | H13: 주로 본체 판매 | I13: 종아리 마사지와 발목 필요성 비교 | J13: W06
C14: 클럭 미니 마사지기S | D14: 마사지 예산 경쟁 | E14: 부착형 마사지기와 패드 | F14: KRW | G14: 59900 | H14: 교체 패드 | I14: 작고 싼 대안 대비 차별화 확인 | J14: W07
C15: Sea Band | D15: 기계식 구조 참고 | E15: 손목 압박 돌기 밴드 | F15: 미확인 | H15: 재사용 구조 | I15: 오심용 제품. 생리 효능 근거 아님 | J15: W08
C16: Ovira Noha | D16: 과거 비교 대상 | E16: 과거 TENS 제품 | F16: 미확인 | H16: 현재 판매 확인 불충분 | I16: 현재 공식 홈은 보충제 중심. 가격 제외 | J16: W09
C19: 외화 가격은 해당 국가 표시가격입니다. 세금 배송 구성 할인 조건을 통일하지 않았으므로 원화 적정가격으로 환산하지 않습니다. 판매사 효능 문구는 독립 검증 사실이 아닙니다.
C22: 시장 규모는 아래 가정의 조건부 결과
C24: 잠재 적합고객 모수 | D24: 명 | F24: ='01_가정'!$F$110 -> 1000000
C25: 문제와 사용 상황 적합률 | D25: % | F25: ='01_가정'!$F$111 -> 0.2
C26: 적합군의 유료 수용률 | D26: % | F26: ='01_가정'!$F$112 -> 0.3
C27: 조건부 서비스 가능 고객 | D27: 명 | F27: =F24*F25*F26 -> 60000
C28: 본체 실결제가 | D28: 원 | F28: ='01_가정'!F10 -> 129000
C29: 조건부 일회 구매 잠재 GMV | D29: 원 | F29: =F27*F28 -> 7740000000
C30: 연간 신규 도입률 | D30: % | F30: ='01_가정'!$F$113 -> 0.1
C31: 연간 도입 GMV 참고 | D31: 원 | F31: =F29*F30 -> 774000000
C33: Y1 DTC 확보 목표 가정 | D33: 개 | F33: ='03_월별손익'!F17 -> 56
C34: Y1 비환불 DTC 고객 | D34: 명 | F34: ='03_월별손익'!F21 -> 47.6
C35: Y1 총 순매출 | D35: 원 | F35: ='03_월별손익'!F33 -> 5612169.8
C38: 100만명과 적합률 및 유료 수용률은 시장 통계가 아닙니다. 조건부 SAM 계산용 입력이며 확정 TAM으로 인용하지 않습니다. SOM은 광고 예산과 전환율에서 계산합니다.
C40: 원문의 글로벌 3,120억 달러와 국내 7.6조원은 원출처와 제품 범위가 확인되지 않아 채택하지 않았습니다. N91 48만명과 W케어 16만명도 실제 구매자 수가 아닙니다.
C42: 확장 조건은 원가와 CAC 검증, 고객 재사용, 유통 계약입니다. 올리브영 입점과 고객 데이터 접근을 확정 자산으로 간주하지 않습니다. 기본 재무에는 리테일 매출을 넣지 않았습니다.

Sheet 07_근거원문
C2: 원문 주장과 외부 근거의 적용 범위
C4: 선택 시나리오 | F4: ='01_가정'!H4 -> 보수
C7: ID | D7: 근거 종류 | E7: 자료명 | F7: 채택한 내용 | G7: 위치 또는 URL | H7: 해석 제한
C8: S01 | D8: 사용자 제안서 | E8: KakaoTalk20260925.txt | F8: 아이디어 타깃 수익모델 및 3억원 사용 계획 | G8: 첨부 원문 | H8: 원안의 주장과 계획이며 검증 실적이 아님
C9: S02 | D9: 사용자 면접 자료 | E9: KakaoTalk20260923.txt | F9: 100일 게임과 카드 선택 예산 | G9: 첨부 원문 | H9: 게임 선택 합계 산술 수정
C10: S03 | D10: 사용자 목업 4장 | E10: KakaoTalk_20261023 이미지 | F10: 온도 배터리 소재 및 사용 장면 | G10: 첨부 이미지 | H10: 완제품 또는 인증 증빙 아님
C11: S04 | D11: 2025년 2기 가이드 | E11: ONLYONE FRONTIER 2기 지원 가이드 | F11: 최대 3억원 및 1년 독립 추진 지원 | G11: PDF p3 p10 p11 | H11: 3기 현재 일정과 확정 지원 조건으로 전용 금지
C12: S05 | D12: 기존 계산 모델 | E12: 그날의류 면접시뮬레이션 v5 탭별결론형 | F12: 가격 149000 원가 40000 CAC 30000 출고15000 | G12: 기존 01 가정입력 | H12: 실제 제안서 수치가 아닌 종전 계산 가정
C13: W01 | D13: 회사 공식 상품 | E13: Myoovi 2.0 및 리필 | F13: £79.99 기기 £13.50 패드 | G13: https://myoovi.co.uk/collections/all | H13: 제품 기능은 회사 설명. 한국 허가와 판매량 미확인
C14: W02 | D14: 회사 공식 상품 | E14: Livia Kit | F14: 단품 $129 및 $29+월$8 옵션 | G14: https://mylivia.com/products/livia-1 | H14: 약정 해지 조건은 구매 전 별도 확인
C15: W03 | D15: 회사 공식 상품 | E15: Beurer EM50 | F15: TENS 온열 43℃ 및 교체 젤패드 | G15: https://www.beurer.com/global/p/64854/ | H15: 가격 채택 안 함. 한국 페이지는 준비중 표시
C16: W04 | D16: 기업 등록 제품 소개 | E16: 우먼스트레스프리 | F16: 생리통 치료용 광 기반 기기 | G16: https://dhnet.kodhia.or.kr/core/?cid=100&dSeq=26 | H16: 기업 소개를 사용. 허가번호와 사용목적 독립 재확인 필요
C17: W05 | D17: 회사 공식 상품 | E17: ThermaCare Menstrual | F17: 일회용 의복 부착형 온열 제품 | G17: https://www.thermacare.com/heat-wraps/menstrual-pain-therapy/ | H17: 8시간은 회사 표시 기능. 당사 효과로 전용 불가
C18: W06 | D18: 회사 공식몰 | E18: 풀리오 종아리 V3 | F18: 3중 에어셀과 표시가 159000원 | G18: https://puliodays.com/ | H18: 국내 마사지 예산 경쟁. 생리주기 치료 대안으로 표기 안 함
... C30: W18 | D30: 정부 보도 | E30: 보건복지부 N91 설명 | F30: N91은 무월경 소량 및 희발 월경 | G30: https://www.mohw.go.kr/board.es?act=view&bid=0027&list_no=305444&mid=a10503010100 | H30: 2014년 자료는 코드 의미 확인용. 최신 48만명 근거 아님
C34: 원안 주장별 현재 판단
C36: 원문 주장 | E36: 상태 | F36: 반영 조치 | G36: 출처
C37: 생리 지연과 불순 개선 | E37: 제품 직접 근거 없음 | F37: 통증 연구를 주기 개선으로 확대하지 않음 | G37: S01 W10 W11 W12
C38: 황토볼 소재 자체 우월성 | E38: 미검증 | F38: 동일 형상 다른 소재와 비교 필요 | G38: S03
C39: 37 42 47℃와 2시간 작동 | E39: 목표 사양 | F39: 열 압력 전력 실측 전 확정 안 함 | G39: S03
C40: 최초 구조와 특허 | E40: 미검증 | F40: 전시회 미발견은 선행기술 조사 아님 | G40: S01
C41: W케어 PB와 고객 데이터 | E41: 협업 제안 | F41: 입점과 데이터 이용 계약 없음 | G41: S01 W15
C42: 글로벌 3120억 달러와 국내 7.6조원 | E42: 원출처 미확인 | F42: 확정 TAM SAM 숫자에서 제외 | G42: S01
C43: N91 연간 48만명 | E43: 최신 원자료 미확인 | F43: 환자 수와 구매자 수는 다름 | G43: S01 W18
C44: W케어 누적 가입 16만명 | E44: 과거 수치 주장 | F44: 현재 획득 가능 고객으로 사용 안 함 | G44: S01
C45: 1년 투자금 3억원 | E45: 신청 계획과 과거 가이드 | F45: 당해 기수 지원 계약 확인 필요 | G45: S01 S04
C46: 현재 고객 검증과 매출 | E46: 증빙 미제공 | F46: 0명 또는 0원으로 확정하지 않음 | G46: S01 S02
C49: 제안서 투자금 원안
C51: 원안 용도 | E51: 금액 원
C52: MVP 사용자 테스트 | E52: 40000000
C53: 제품 고도화 | E53: 30000000
C54: 양산 설계 검증 | E54: 40000000
C55: 초도 생산 | E55: 80000000
C56: 시장 검증 마케팅 | E56: 40000000
C57: 디자인 운영 | E57: 20000000
C58: 예비 투자재 | E58: 50000000
C59: 원안 합계 | E59: =SUM(E52:E58) -> 300000000
C62: 외부 자료 조회일 2026년 10월 26일. 가격은 조회 당시 표시가이며 재고 또는 한국 내 허가를 보장하지 않습니다. 사업 가정 A01부터 A17은 본 보고서의 계산 입력입니다.

Sheet 08_실측입력
C2: 실제 검증 결과가 쌓이면 입력할 곳
C4: 선택 시나리오 | F4: ='01_가정'!H4 -> 보수
C5: 노란 칸은 실제 관측값만 입력합니다. 빈칸은 미관측이며 0과 다릅니다. 예약금과 제품 출고를 구분합니다. 입력해도 사업 가정을 자동으로 덮어쓰지 않습니다.
C7: 관측 항목 | D7: 단위 | F7: 입력 또는 계산 | G7: 정의
C8: 광고와 모집 지출 | D8: 원 | G8: 관측 기간 신규 고객 획득에 쓴 금액
C9: 유효 방문 수 | D9: 명 | G9: 중복과 내부 테스트 제외
C10: 환불 가능한 예약자 | D10: 명 | G10: 제품 매출로 인정하지 않음
C11: 예약 취소자 | D11: 명 | G11: 관측 기간 내 취소
C12: 실제 첫 제품 출고 | D12: 명 | G12: 주문 후 첫 출고까지 완료
C13: 제품 전액 환불 | D13: 명 | G13: 출고 집단과 같은 추적 기간
C14: 재구매 관측 대상 | D14: 명 | G14: 관측 기간을 모두 지난 적격 고객
C15: 실제 리필 재구매자 | D15: 명 | G15: 무상 증정 제외 유료 재구매
C16: 본체 실결제가 | D16: 원 | G16: VAT 포함, 프로모션 명시
C17: 검수 후 완제품 원가 | D17: 원 | G17: 견적 또는 실제 BOM 공급가
C18: 사용성 평가 참여자 | D18: 명 | G18: 안전 검토와 동의 완료
C19: 독립 착용 완수자 | D19: 명 | G19: 설정된 과제를 도움 없이 완료
C20: 보고된 안전 관련 사건 | D20: 건 | G20: 0도 직접 기록한 경우만 입력
C24: 실제 출고 CAC | D24: 원 | F24: =IF(COUNT(F8,F12)<2,"미관측",IF(F12=0,"출고 없음",F8/F12)) -> 미관측
C25: 출고 전환율 | D25: % | F25: =IF(COUNT(F9,F12)<2,"미관측",IF(F9=0,"유입 없음",F12/F9)) -> 미관측
C26: 제품 환불률 | D26: % | F26: =IF(COUNT(F12,F13)<2,"미관측",IF(F12=0,"출고 없음",F13/F12)) -> 미관측
C27: 리필 재구매율 | D27: % | F27: =IF(COUNT(F14,F15)<2,"미관측",IF(F14=0,"적격자 없음",F15/F14)) -> 미관측
C28: 독립 착용 완수율 | D28: % | F28: =IF(COUNT(F18,F19)<2,"미관측",IF(F18=0,"참여 없음",F19/F18)) -> 미관측
C29: 예약 취소율 | D29: % | F29: =IF(COUNT(F10,F11)<2,"미관측",IF(F10=0,"예약 없음",F11/F10)) -> 미관측
C31: 선택 가정의 허용 CAC | D31: 원 | F31: ='02_단위경제'!F23 -> -2007.6818
C32: CAC 비교 | D32: 판단 | F32: =IF(NOT(ISNUMBER(F24)),"실제 출고 관측 필요",IF(F24<=F31,"경제성 추가 검토 가능","가격 원가 유입 개선 필요")) -> 실제 출고 관측 필요
C36: 제품 판매 준비가 완료되기 전에는 예약 수요만 평가합니다. 예약 CAC를 위 실제 출고 CAC에 넣지 않습니다. 동일 가격과 채널 및 환불 관측 기간에서 비교하세요.
C38: 소수 표본은 추정 오차가 큽니다. 예를 들어 24명 중 20명 완수는 83%지만 모집단 83%를 보장하지 않습니다. 체험과 유효성은 별도 판단합니다.

Sheet 09_계산검증
C2: 계산과 연결 검증
C4: 선택 시나리오 | F4: ='01_가정'!H4 -> 보수
C6: 검증 항목 | D6: 단위 | F6: 최대 차이 또는 상태
C8: 재고 수량 수불 차이 | F8: =MAX(MAX(J8:AS8),-MIN(J8:AS8)) -> 0 | G8: =IF(F8<0.01,"정상","확인 필요") -> 정상 | J8: ='04_재고현금'!J9+'04_재고현금'!J10-'04_재고현금'!J8-'04_재고현금'!J11 -> 0 | K8: ='04_재고현금'!K9+'04_재고현금'!K10-'04_재고현금'!K8-'04_재고현금'!K11 -> 0 | L8: ='04_재고현금'!L9+'04_재고현금'!L10-'04_재고현금'!L8-'04_재고현금'!L11 -> 0 | M8: ='04_재고현금'!M9+'04_재고현금'!M10-'04_재고현금'!M8-'04_재고현금'!M11 -> 0 | N8: ='04_재고현금'!N9+'04_재고현금'!N10-'04_재고현금'!N8-'04_재고현금'!N11 -> 0 | O8: ='04_재고현금'!O9+'04_재고현금'!O10-'04_재고현금'!O8-'04_재고현금'!O11 -> 0 | P8: ='04_재고현금'!P9+'04_재고현금'!P10-'04_재고현금'!P8-'04_재고현금'!P11 -> 0 | Q8: ='04_재고현금'!Q9+'04_재고현금'!Q10-'04_재고현금'!Q8-'04_재고현금'!Q11 -> 0 | ... AS8: ='04_재고현금'!AS9+'04_재고현금'!AS10-'04_재고현금'!AS8-'04_재고현금'!AS11 -> 0
C9: 재고 금액 수불 차이 | F9: =MAX(MAX(J9:AS9),-MIN(J9:AS9)) -> 0 | G9: =IF(F9<0.01,"정상","확인 필요") -> 정상 | J9: ='04_재고현금'!J14+'04_재고현금'!J13-'04_재고현금'!J16-'04_재고현금'!J17 -> 0 | K9: ='04_재고현금'!K14+'04_재고현금'!K13-'04_재고현금'!K16-'04_재고현금'!K17 -> 0 | L9: ='04_재고현금'!L14+'04_재고현금'!L13-'04_재고현금'!L16-'04_재고현금'!L17 -> 0 | M9: ='04_재고현금'!M14+'04_재고현금'!M13-'04_재고현금'!M16-'04_재고현금'!M17 -> 0 | N9: ='04_재고현금'!N14+'04_재고현금'!N13-'04_재고현금'!N16-'04_재고현금'!N17 -> 0 | O9: ='04_재고현금'!O14+'04_재고현금'!O13-'04_재고현금'!O16-'04_재고현금'!O17 -> 0 | P9: ='04_재고현금'!P14+'04_재고현금'!P13-'04_재고현금'!P16-'04_재고현금'!P17 -> 0 | Q9: ='04_재고현금'!Q14+'04_재고현금'!Q13-'04_재고현금'!Q16-'04_재고현금'!Q17 -> 0 | ... AS9: ='04_재고현금'!AS14+'04_재고현금'!AS13-'04_재고현금'!AS16-'04_재고현금'!AS17 -> 0
C10: 현금 흐름 두 방식 차이 | F10: =MAX(MAX(J10:AS10),-MIN(J10:AS10)) -> 0 | G10: =IF(F10<0.01,"정상","확인 필요") -> 정상 | J10: ='04_재고현금'!J40-'04_재고현금'!J46 -> 0 | K10: ='04_재고현금'!K40-'04_재고현금'!K46 -> 0 | L10: ='04_재고현금'!L40-'04_재고현금'!L46 -> 0 | M10: ='04_재고현금'!M40-'04_재고현금'!M46 -> 0 | N10: ='04_재고현금'!N40-'04_재고현금'!N46 -> 0 | O10: ='04_재고현금'!O40-'04_재고현금'!O46 -> 0 | P10: ='04_재고현금'!P40-'04_재고현금'!P46 -> 0 | Q10: ='04_재고현금'!Q40-'04_재고현금'!Q46 -> 0 | ... AS10: ='04_재고현금'!AS40-'04_재고현금'!AS46 -> 0
C11: 현금 잔액 수불 차이 | F11: =MAX(MAX(J11:AS11),-MIN(J11:AS11)) -> 0 | G11: =IF(F11<0.01,"정상","확인 필요") -> 정상 | J11: ='04_재고현금'!J42+'04_재고현금'!J40+'04_재고현금'!J41-'04_재고현금'!J43 -> 0 | K11: ='04_재고현금'!K42+'04_재고현금'!K40+'04_재고현금'!K41-'04_재고현금'!K43 -> 0 | L11: ='04_재고현금'!L42+'04_재고현금'!L40+'04_재고현금'!L41-'04_재고현금'!L43 -> 0 | M11: ='04_재고현금'!M42+'04_재고현금'!M40+'04_재고현금'!M41-'04_재고현금'!M43 -> 0 | N11: ='04_재고현금'!N42+'04_재고현금'!N40+'04_재고현금'!N41-'04_재고현금'!N43 -> 0 | O11: ='04_재고현금'!O42+'04_재고현금'!O40+'04_재고현금'!O41-'04_재고현금'!O43 -> 0 | P11: ='04_재고현금'!P42+'04_재고현금'!P40+'04_재고현금'!P41-'04_재고현금'!P43 -> 0 | Q11: ='04_재고현금'!Q42+'04_재고현금'!Q40+'04_재고현금'!Q41-'04_재고현금'!Q43 -> 0 | ... AS11: ='04_재고현금'!AS42+'04_재고현금'!AS40+'04_재고현금'!AS41-'04_재고현금'!AS43 -> 0
C12: 매출 합계 차이 | F12: =MAX(MAX(J12:AS12),-MIN(J12:AS12)) -> 0 | G12: =IF(F12<0.01,"정상","확인 필요") -> 정상 | J12: =SUM('03_월별손익'!J30:J32)-'03_월별손익'!J33 -> 0 | K12: =SUM('03_월별손익'!K30:K32)-'03_월별손익'!K33 -> 0 | L12: =SUM('03_월별손익'!L30:L32)-'03_월별손익'!L33 -> 0 | M12: =SUM('03_월별손익'!M30:M32)-'03_월별손익'!M33 -> 0 | N12: =SUM('03_월별손익'!N30:N32)-'03_월별손익'!N33 -> 0 | O12: =SUM('03_월별손익'!O30:O32)-'03_월별손익'!O33 -> 0 | P12: =SUM('03_월별손익'!P30:P32)-'03_월별손익'!P33 -> 0 | Q12: =SUM('03_월별손익'!Q30:Q32)-'03_월별손익'!Q33 -> 0 | ... AS12: =SUM('03_월별손익'!AS30:AS32)-'03_월별손익'!AS33 -> 0
C13: 기말 재고 음수 수량 | F13: =MAX(MAX(J13:AS13),-MIN(J13:AS13)) -> 0 | G13: =IF(F13<0.01,"정상","확인 필요") -> 정상 | J13: =MIN(0,'04_재고현금'!J11) -> 0 | K13: =MIN(0,'04_재고현금'!K11) -> 0 | L13: =MIN(0,'04_재고현금'!L11) -> 0 | M13: =MIN(0,'04_재고현금'!M11) -> 0 | N13: =MIN(0,'04_재고현금'!N11) -> 0 | O13: =MIN(0,'04_재고현금'!O11) -> 0 | P13: =MIN(0,'04_재고현금'!P11) -> 0 | Q13: =MIN(0,'04_재고현금'!Q11) -> 0 | ... AS13: =MIN(0,'04_재고현금'!AS11) -> 0
C14: 리필 구매자 수불 차이 | F14: =MAX(MAX(J14:AS14),-MIN(J14:AS14)) -> 0 | G14: =IF(F14<0.01,"정상","확인 필요") -> 정상 | J14: =SUM('03_월별손익'!J26:J27)-'03_월별손익'!J28 -> 0 | K14: =SUM('03_월별손익'!K26:K27)-'03_월별손익'!K28 -> 0 | L14: =SUM('03_월별손익'!L26:L27)-'03_월별손익'!L28 -> 0 | M14: =SUM('03_월별손익'!M26:M27)-'03_월별손익'!M28 -> 0 | N14: =SUM('03_월별손익'!N26:N27)-'03_월별손익'!N28 -> 0 | O14: =SUM('03_월별손익'!O26:O27)-'03_월별손익'!O28 -> 0 | P14: =SUM('03_월별손익'!P26:P27)-'03_월별손익'!P28 -> 0 | Q14: =SUM('03_월별손익'!Q26:Q27)-'03_월별손익'!Q28 -> 0 | ... AS14: =SUM('03_월별손익'!AS26:AS27)-'03_월별손익'!AS28 -> 0
C17: 100일 예산 합계 차이 | F17: =SUM('05_100일검증'!F8:F17)-10000000 -> 0
C18: 100일 배분 비중 합계 | F18: =SUM('05_100일검증'!J23:M23)-1 -> 0
C19: 원안 투자금 합계 차이 | F19: =SUM('07_근거원문'!E52:E58)-300000000 -> 0
C20: 리테일 스위치 0일 때 매출 | F20: =IF('01_가정'!$F$95=0,SUM('03_월별손익'!J31:AS31),0) -> 0
C21: 실측 자료의 현재 상태 | F21: =IF(COUNT('08_실측입력'!F8:F20)=0,"미관측","관측값 있음") -> 미관측
C24: 계산 정상은 수요나 효능 검증을 뜻하지 않습니다. 이 탭은 결과를 관찰하며 가정과 손익 및 요약의 계산에 다시 연결하지 않습니다.

Sheet 10_린캔버스작성
C2: 그날의 류 | 린캔버스 작성·복사
C3: ① 01_가정에서 숫자 수정 → ② 이 탭의 노란색 서술 수정 → ③ 오른쪽 문안을 양식에 복사
C4: 현재 시나리오 | G4: ='01_가정'!H4 -> 보수 | K4: 시나리오 선택: 01_가정!F4 (1 보수 / 2 기준 / 3 낙관)
C6: 팀명 | F6: 그날의 류 | K6: 사업 대상 | N6: B2C
C7: 아이디어명 | F7: 그날의 류 — 발목 온열·압박 셀프케어와 교체형 패치
C9: 팀원 1 | F9: 손수민 | I9: 사업 총괄·고객 검증·유통 협의 (역할 초안)
C10: 팀원 2 | I10: 사업성·손익·현금흐름 검증 (역할 초안)
C11: 팀원 3 | I11: 제품 개발·안전성·제조 검증 (역할 초안)
C12: 팀원 이름·역할은 실제 구성에 맞춰 확정하세요. 아래 문안은 검증 전 사업계획 초안이며, 시장규모·매출·고객지표는 실적이 아닌 선택 시나리오의 가정입니다.
C15: 숫자 확인 | 금액: 백만원, 본체 출고: 개
C16: 주요 결과 | G16: 1년차 | K16: 2년차 | N16: 3년차
C17: 순매출 (VAT 제외·환불 차감) | G17: ='03_월별손익'!F33/1000000 -> 5.6121698 | K17: ='03_월별손익'!G33/1000000 -> 85.304202 | N17: ='03_월별손익'!H33/1000000 -> 184.72419
C18: 손익상 총비용 (감가상각 포함) | G18: =('03_월별손익'!F33-'03_월별손익'!F54)/1000000 -> 252.44873 | K18: =('03_월별손익'!G33-'03_월별손익'!G54)/1000000 -> 326.28946 | N18: =('03_월별손익'!H33-'03_월별손익'!H54)/1000000 -> 430.61318
C19: 영업이익 | G19: ='03_월별손익'!F54/1000000 -> -246.83656 | K19: ='03_월별손익'!G54/1000000 -> -240.98526 | N19: ='03_월별손익'!H54/1000000 -> -245.88898
C20: 기말 현금 (추가 조달 전) | G20: ='04_재고현금'!F43/1000000 -> -8.5137738 | K20: ='04_재고현금'!G43/1000000 -> -252.32793 | N20: ='04_재고현금'!H43/1000000 -> -471.88363
C21: 본체 출고 | G21: ='03_월별손익'!F19 -> 56 | K21: ='03_월별손익'!G19 -> 804 | N21: ='03_월별손익'!H19 -> 1680
C23: ="초기 투자금 "&TEXT('01_가정'!F105/100000000,"0.0")&"억원 | 36개월 최대 추가자금 필요 "&TEXT('00_투자판단'!F23/1000000,"#,##0.0")&"백만원 | 최소 현금 "&TEXT('01_가정'!F106/1000000,"#,##0.0")&"백만원 유지 기준. 초기 투자금은 자금 유입이며 손익상 비용과 다릅니다." -> 초기 투자금 3.0억원 | 36개월 최대 추가자금 필요 501.9백만원 | 최소 현금 30.0백만원 유지 기준. 초기 투자금은 자금 유입이며 손익상 비용과 다릅니다.
C25: 노란색 칸에는 설명을 수정하고, 숫자는 01_가정에서 수정하세요. 오른쪽 칸은 수식이므로 덮어쓰지 마세요. 복사할 때는 오른쪽 셀을 선택해 Ctrl+C 후 양식 입력란에 붙여넣으세요.
C28: 01 문제 (Problem)
C29: 서술 초안 | 직접 수정 | K29: 제출 문안 | 자동 연결 · 이 셀을 복사
C30: 생리 전후 불편감 때문에 온열·마사지 등 셀프케어를 하는 성인 여성 중, 손으로 발목의 같은 부위를 반복해서 누르는 방식이 번거롭고 위치·압박 강도를 일정하게 유지하기 어렵다는 고객 가설을 검증한다. 기존 대안은 손 지압, 온열팩, 저주파 기기, 일반 마사지기 등이다. 생리 지연·불순 개선은 원안의 문제의식이며, 본 제품의 효과로 입증된 사실은 아니다. | K30: =IF(LEN(C30)=0,"[작성 필요]",C30) -> 생리 전후 불편감 때문에 온열·마사지 등 셀프케어를 하는 성인 여성 중, 손으로 발목의 같은 부위를 반복해서 누르는 방식이 번거롭고 위치·압박 강도를 일정하게 유지하기 어렵다는 고객 가설을 검증한다. 기존 대안은 손 지압, 온열팩, 저주파 기기, 일반 마사지기 등이다. 생리 지연·불순 개선은 원안의 문제의식이며, 본 제품의 효과로 입증된 사실은 아니다.
C38: 작성 근거: 실제 아이디어 제안서·고객 가설. 07_근거원문 참조. 고객 인터뷰 후 표현을 수정하세요.
C41: 02 고객 세그먼트 (Customer Segments)
C42: 서술 초안 | 직접 수정 | K42: 제출 문안 | 자동 연결 · 이 셀을 복사
C43: 초기 고객은 생리 전후 불편감으로 온열·마사지 제품을 이미 사용하며, 집이나 사무실에서 앉아 있는 동안 짧은 셀프케어를 원하는 성인 여성으로 설정한다. 모든 여성을 한 번에 대상으로 삼기보다, 기존 대안에 시간·비용을 쓰고 반복 사용 의사가 있는 고객부터 검증한다. 구매자·사용자·사용 상황과 가격 수용도를 인터뷰로 구체화한다. | K43: =IF(LEN(C43)=0,"[작성 필요]",C43) -> 초기 고객은 생리 전후 불편감으로 온열·마사지 제품을 이미 사용하며, 집이나 사무실에서 앉아 있는 동안 짧은 셀프케어를 원하는 성인 여성으로 설정한다. 모든 여성을 한 번에 대상으로 삼기보다, 기존 대안에 시간·비용을 쓰고 반복 사용 의사가 있는 고객부터 검증한다. 구매자·사용자·사용 상황과 가격 수용도를 인터뷰로 구체화한다.
C50: 초기 고객은 가설입니다. 고객 범위를 좁힐수록 06_시장경쟁의 시장규모 가정도 함께 검토하세요.
C53: 03 가치 제안 (Unique Value Proposition)
C54: 서술 초안 | 직접 수정 | K54: 제출 문안 | 자동 연결 · 이 셀을 복사
C55: 손으로 계속 누르지 않아도 발목 셀프케어를 반복할 수 있도록, 착용 위치 안내와 온열·공기압 기능을 결합한 사용 경험을 제공하고자 한다. 핵심 가치는 짧은 시간 안에 간편하게 착용·사용하는 편의성이다. 생리주기 정상화나 치료 효과를 약속하지 않으며, 지불 의사와 실제 사용 편의성을 우선 확인한다. | K55: =IF(LEN(C55)=0,"[작성 필요]",C55) -> 손으로 계속 누르지 않아도 발목 셀프케어를 반복할 수 있도록, 착용 위치 안내와 온열·공기압 기능을 결합한 사용 경험을 제공하고자 한다. 핵심 가치는 짧은 시간 안에 간편하게 착용·사용하는 편의성이다. 생리주기 정상화나 치료 효과를 약속하지 않으며, 지불 의사와 실제 사용 편의성을 우선 확인한다.
C62: 차별화는 고객이 체감하고 비용을 지불하는 이유로 쓰세요. 임상 효능은 확인된 근거 범위에서만 표현하세요.
C65: 04 해결책 (Solution)
C66: 서술 초안 | 직접 수정 | K66: 제출 문안 | 자동 연결 · 이 셀을 복사
C67: 황토 반구형 교체 패치와 발목 착용형 온열·공기압 기기를 결합하는 제품을 구상한다. 원안의 SP6·KI6·KI3 위치를 참고한 부착 안내와 작동 제어를 시제품에서 검토한다. 온도·압박·사용 시간은 안전성 검증 후 확정하고, 패치 부착성·피부 반응·착용성·반복 사용성을 먼저 시험한다. 초기 검증 결과에 따라 기능과 제품 구성을 축소하거나 조정한다. | K67: =IF(LEN(C67)=0,"[작성 필요]",C67) -> 황토 반구형 교체 패치와 발목 착용형 온열·공기압 기기를 결합하는 제품을 구상한다. 원안의 SP6·KI6·KI3 위치를 참고한 부착 안내와 작동 제어를 시제품에서 검토한다. 온도·압박·사용 시간은 안전성 검증 후 확정하고, 패치 부착성·피부 반응·착용성·반복 사용성을 먼저 시험한다. 초기 검증 결과에 따라 기능과 제품 구성을 축소하거나 조정한다.
C75: 제안 사양과 확정 사양을 구분하세요. 05_100일검증에서 시제품·사용성·제조 검증 예산을 확인할 수 있습니다.
C78: 05 경쟁 우위 (Unfair Advantage)
C79: 서술 초안 | 직접 수정 | K79: 제출 문안 | 자동 연결 · 이 셀을 복사
C80: 현재 확인된 독점 특허·임상 데이터·독점 유통계약은 없다. 초기에는 착용 위치 안내, 압박·온열 제어와 안전 설계, 반복 사용·고객 피드백 데이터를 축적해 모방하기 어려운 사용 경험과 품질 관리 체계를 만드는 것이 목표다. 유통사 접점은 협의 기회로 다루며, 계약 또는 접근 가능한 고객을 이미 확보한 것으로 표현하지 않는다. | K80: =IF(LEN(C80)=0,"[작성 필요]",C80) -> 현재 확인된 독점 특허·임상 데이터·독점 유통계약은 없다. 초기에는 착용 위치 안내, 압박·온열 제어와 안전 설계, 반복 사용·고객 피드백 데이터를 축적해 모방하기 어려운 사용 경험과 품질 관리 체계를 만드는 것이 목표다. 유통사 접점은 협의 기회로 다루며, 계약 또는 접근 가능한 고객을 이미 확보한 것으로 표현하지 않는다.
C87: 보유 우위와 구축 계획을 구분했습니다. 실제 특허·계약·시험 성적이 확보되면 노란색 칸에 반영하세요.
C90: 06 수익 창출 방안 (Revenue Streams)
C91: 서술 초안 | 직접 수정 | K91: 제출 문안 | 자동 연결 · 이 셀을 복사
C92: 본체 판매와 교체 패치의 반복 구매를 수익원으로 설계한다. 초기에는 자사 온라인 판매를 우선하고, 패치 반복 구매는 별도 가정으로 검증한다. 아래 매출은 실적이나 확정 수주가 아닌 시뮬레이션이다. | K92: =IF(LEN(C92)=0,"[작성 필요]",C92)&" 선택 시나리오: "&'01_가정'!H4&". 1년차 본체 가격 "&TEXT('01_가정'!F10,"#,##0")&"원, 리필 가격 "&TEXT('01_가정'!F70,"#,##0")&"원. 1~3년차 본체 출고 "&TEXT('03_월별손익'!F19,"#,##0")&" / "&TEXT('03_월별손익'!G19,"#,##0")&" / "&TEXT('03_월별손익'!H19,"#,##0")&"개, 순매출 "&TEXT('03_월별손익'!F33/1000000,"#,##0.0")&" / "&TEXT('03_월별손익'!G33/1000000,"#,##0.0")&" / "&TEXT('03_월별손익'!H33/1000000,"#,##0.0")&"백만원을 예상한다. 순매출은 VAT 제외·환불 차감 기준이다." -> 본체 판매와 교체 패치의 반복 구매를 수익원으로 설계한다. 초기에는 자사 온라인 판매를 우선하고, 패치 반복 구매는 별도 가정으로 검증한다. 아래 매출은 실적이나 확정 수주가 아닌 시뮬레이션이다. 선택 시나리오: 보수. 1년차 본체 가격 129,000원, 리필 가격 9,900원. 1~3년차 본체 출고 56 / 804 / 1,680개, 순매출 5.6 / 85.3 / 184.7백만원을 예상한다. 순매출은 VAT 제외·환불 차감 기준이다.
C103: 가격·판매량·패치: 01_가정 → 03_월별손익. 매출은 VAT 제외·환불 차감 기준, 가격은 소비자 결제가격입니다.
C106: 07 비용 구조 (Cost Structure)
C107: 서술 초안 | 직접 수정 | K107: 제출 문안 | 자동 연결 · 이 셀을 복사
C108: 주요 비용은 본체·패치 제조원가, 배송·결제·반품·보증, 광고비, 인건비, 고정운영비, 시제품·연구개발 및 감가상각이다. 금형·설비 투자와 재고 선발주는 손익 비용과 집행 시점이 달라 현금흐름을 별도로 관리한다. | K108: =IF(LEN(C108)=0,"[작성 필요]",C108)&" 선택 시나리오의 1~3년차 손익상 총비용은 "&TEXT(G18,"#,##0.0")&" / "&TEXT(K18,"#,##0.0")&" / "&TEXT(N18,"#,##0.0")&"백만원, 영업이익은 "&TEXT(G19,"#,##0.0")&" / "&TEXT(K19,"#,##0.0")&" / "&TEXT(N19,"#,##0.0")&"백만원이다. 1년차 인건비 "&TEXT('03_월별손익'!F49/1000000,"#,##0.0")&"백만원, 금형·설비 현금지출 "&TEXT('04_재고현금'!F32/1000000,"#,##0.0")&"백만원을 반영한다. 초기 투자금 "&TEXT('01_가정'!F105/1000000,"#,##0.0")&"백만원 유입 후, 36개월 최소현금 "&TEXT('01_가정'!F106/1000000,"#,##0.0")&"백만원을 유지하기 위한 최대 추가자금 필요액은 "&TEXT('00_투자판단'!F23/1000000,"#,##0.0")&"백만원이다. 회사의 인건비 현금 부담률은 "&TEXT('01_가정'!F107,"0%")&"이며 지원을 반영해도 손익 인건비는 유지한다." -> 주요 비용은 본체·패치 제조원가, 배송·결제·반품·보증, 광고비, 인건비, 고정운영비, 시제품·연구개발 및 감가상각이다. 금형·설비 투자와 재고 선발주는 손익 비용과 집행 시점이 달라 현금흐름을 별도로 관리한다. 선택 시나리오의 1~3년차 손익상 총비용은 252.4 / 326.3 / 430.6백만원, 영업이익은 -246.8 / -241.0 / -245.9백만원이다. 1년차 인건비 162.0백만원, 금형·설비 현금지출 27.5백만원을 반영한다. 초기 투자금 300.0백만원 유입 후, 36개월 최소현금 30.0백만원을 유지하기 위한 최대 추가자금 필요액은 501.9백만원이다. 회사의 인건비 현금 부담률은 0%이며 지원을 반영해도 손익 인건비는 유지한다.
C122: 총비용 = 순매출 − 영업이익. 금형·설비는 현금지출과 감가상각을 구분합니다. 회사 인건비 지원은 01_가정!F107에서 현금에만 반영합니다.
C125: 08 채널 (Channels)
C126: 서술 초안 | 직접 수정 | K126: 제출 문안 | 자동 연결 · 이 셀을 복사
C127: 초기에는 고객 인터뷰 참여자와 자사 온라인 채널을 통해 사용성과 지불 의사를 검증하고, 콘텐츠·검색·소셜 광고에서 구매 전환을 측정한다. 이후 검증된 수익성과 제조·공급 안정성을 바탕으로 전문 유통 및 리테일 협의를 진행한다. Wcare 등 접점은 협의 후보이며 입점·물량 확정으로 간주하지 않는다. | K127: =IF(LEN(C127)=0,"[작성 필요]",C127)&IF('01_가정'!F95=0," 현재 재무 시나리오는 리테일 매출을 제외하고 DTC를 반영한다."," 현재 재무 시나리오는 DTC와 리테일 물량 가정을 반영하며, 실제 계약 여부는 별도 확인한다.") -> 초기에는 고객 인터뷰 참여자와 자사 온라인 채널을 통해 사용성과 지불 의사를 검증하고, 콘텐츠·검색·소셜 광고에서 구매 전환을 측정한다. 이후 검증된 수익성과 제조·공급 안정성을 바탕으로 전문 유통 및 리테일 협의를 진행한다. Wcare 등 접점은 협의 후보이며 입점·물량 확정으로 간주하지 않는다. 현재 재무 시나리오는 리테일 매출을 제외하고 DTC를 반영한다.
C135: 01_가정!F95는 모델의 리테일 반영 스위치입니다. 1로 바꿔도 실제 계약을 의미하지 않습니다.
C138: 09 핵심 지표 (Key Metrics)
C139: 서술 초안 | 직접 수정 | K139: 제출 문안 | 자동 연결 · 이 셀을 복사
C140: 100일 동안 고객 인터뷰, 독립 착용 가능 여부, 가격별 유료 전환, 제조 견적·안전성 자료를 확인한다. 출시 후에는 본체 출고, 환불률, 광고 고객획득비용(CAC), 광고 후 본체 공헌이익(CM2), 패치 첫 구매 참여율·잔존율, 월말 현금을 함께 관리한다. 예약·의향과 실제 결제·출고는 구분한다. | K140: =IF(LEN(C140)=0,"[작성 필요]",C140)&" 현재 1년차 가정: 본체 출고 "&TEXT('03_월별손익'!F19,"#,##0")&"개, CAC "&TEXT('02_단위경제'!F19,"#,##0")&"원, CM2 "&TEXT('02_단위경제'!F20,"#,##0")&"원/개이다. CM2 목표 "&TEXT('01_가정'!F115,"#,##0")&"원 달성을 위한 허용 CAC는 "&TEXT('02_단위경제'!F23,"#,##0")&"원이다. 환불률 "&TEXT('01_가정'!F26,"0.0%")&", 패치 첫 구매 참여율 "&TEXT('01_가정'!F30,"0.0%")&", 월 잔존율 "&TEXT('01_가정'!F34,"0.0%")&"를 가정한다. 100일 검증 계획 예산은 "&TEXT('05_100일검증'!F19/1000000,"#,##0.0")&"백만원이며 검증 완료·달성을 의미하지 않는다." -> 100일 동안 고객 인터뷰, 독립 착용 가능 여부, 가격별 유료 전환, 제조 견적·안전성 자료를 확인한다. 출시 후에는 본체 출고, 환불률, 광고 고객획득비용(CAC), 광고 후 본체 공헌이익(CM2), 패치 첫 구매 참여율·잔존율, 월말 현금을 함께 관리한다. 예약·의향과 실제 결제·출고는 구분한다. 현재 1년차 가정: 본체 출고 56개, CAC 80,000원, CM2 -62,008원/개이다. CM2 목표 20,000원 달성을 위한 허용 CAC는 -2,008원이다. 환불률 15.0%, 패치 첫 구매 참여율 10.0%, 월 잔존율 75.0%를 가정한다. 100일 검증 계획 예산은 10.0백만원이며 검증 완료·달성을 의미하지 않는다.
C153: 자동 수치는 목표·가정입니다. 실측은 08_실측입력에 기록하고 목표를 달성한 것으로 미리 표시하지 마세요.
C156: 별첨 1 핵심 컨셉
C157: 서술 초안 | 직접 수정 | K157: 제출 문안 | 자동 연결 · 이 셀을 복사
C158: 손으로 계속 누르는 번거로움을 줄이기 위해, 교체형 패치와 온열·공기압을 결합한 발목 착용형 셀프케어 제품 및 패치 반복 구매 모델. | K158: =IF(LEN(C158)=0,"[작성 필요]",C158) -> 손으로 계속 누르는 번거로움을 줄이기 위해, 교체형 패치와 온열·공기압을 결합한 발목 착용형 셀프케어 제품 및 패치 반복 구매 모델.
C163: 원안의 제품 개념을 한 문장으로 정리했습니다. 실제 검증·제조 결과에 맞춰 수정하세요.
C166: 별첨 2 첫 번째 고객
C167: 서술 초안 | 직접 수정 | K167: 제출 문안 | 자동 연결 · 이 셀을 복사
C168: 최근 생리 전후 불편감 때문에 온열·마사지 등 셀프케어에 비용을 지불했고, 집이나 사무실에서 앉아 있는 동안 손을 쓰지 않는 발목 셀프케어를 시도해 볼 의사가 있는 성인 여성. 기존 대안의 불편과 새로운 제품에 지불할 의사를 인터뷰와 실제 구매 행동으로 확인한다. | K168: =IF(LEN(C168)=0,"[작성 필요]",C168) -> 최근 생리 전후 불편감 때문에 온열·마사지 등 셀프케어에 비용을 지불했고, 집이나 사무실에서 앉아 있는 동안 손을 쓰지 않는 발목 셀프케어를 시도해 볼 의사가 있는 성인 여성. 기존 대안의 불편과 새로운 제품에 지불할 의사를 인터뷰와 실제 구매 행동으로 확인한다.
C174: 연령만으로 정의하기보다 최근 행동·지출·사용 장면을 기준으로 모집하세요.
C177: 별첨 3 시장 크기 (TAM · SAM · SOM)
C178: 서술 초안 | 직접 수정 | K178: 제출 문안 | 자동 연결 · 이 셀을 복사
C179: TAM은 제품 범주·지역·고객 정의와 공신력 있는 통계를 추가 확인한 뒤 확정한다. 광의의 여성건강 시장 전체를 본 제품의 수요로 사용하지 않는다. 아래 SAM·SOM은 외부 시장조사로 확정된 규모가 아닌 고객 수·적합도·지불 의사에 따른 상향식 가정이다. | K179: =IF(LEN(C179)=0,"[작성 필요]",C179)&" 잠재 고객 "&TEXT('06_시장경쟁'!F24,"#,##0")&"명 × 문제 적합도 "&TEXT('06_시장경쟁'!F25,"0%")&" × 지불 수용도 "&TEXT('06_시장경쟁'!F26,"0%")&" = 조건부 SAM "&TEXT('06_시장경쟁'!F27,"#,##0")&"명이다. 본체 1회 구매 기준 잠재 거래액은 "&TEXT('06_시장경쟁'!F29/100000000,"#,##0.0")&"억원(VAT 포함), 연간 도입률 "&TEXT('06_시장경쟁'!F30,"0%")&" 적용 시 "&TEXT('06_시장경쟁'!F31/100000000,"#,##0.0")&"억원이다. SOM 실행 목표는 1년차 DTC 출고 "&TEXT('06_시장경쟁'!F33,"#,##0")&"개, 전체 사업 순매출 "&TEXT('06_시장경쟁'!F35/1000000,"#,##0.0")&"백만원(VAT 제외·환불 차감)이다." -> TAM은 제품 범주·지역·고객 정의와 공신력 있는 통계를 추가 확인한 뒤 확정한다. 광의의 여성건강 시장 전체를 본 제품의 수요로 사용하지 않는다. 아래 SAM·SOM은 외부 시장조사로 확정된 규모가 아닌 고객 수·적합도·지불 의사에 따른 상향식 가정이다. 잠재 고객 1,000,000명 × 문제 적합도 20% × 지불 수용도 30% = 조건부 SAM 60,000명이다. 본체 1회 구매 기준 잠재 거래액은 77.4억원(VAT 포함), 연간 도입률 10% 적용 시 7.7억원이다. SOM 실행 목표는 1년차 DTC 출고 56개, 전체 사업 순매출 5.6백만원(VAT 제외·환불 차감)이다.
C191: 01_가정!F110:F113 → 06_시장경쟁!F24:F35. SAM 잠재 거래액과 SOM 순매출은 기준이 달라 직접 나누어 점유율로 쓰지 마세요.
C194: 별첨 4 기존 대안재
C195: 서술 초안 | 직접 수정 | K195: 제출 문안 | 자동 연결 · 이 셀을 복사
C196: 고객이 현재 선택하는 대안은 온열팩, 손 지압·마사지, 저주파 자극 기기, 일반 마사지기 등이다. 제품별로 사용 부위·목적·규제 분류가 달라 모두를 동일한 직접 경쟁사로 간주하지 않는다. 가격뿐 아니라 사용 편의, 소모품, 반복 사용 부담과 실제 지불 의사를 비교한다. | K196: =IF(LEN(C196)=0,"[작성 필요]",C196)&" 비교 후보: Myoovi·Livia·Beurer EM50(저주파), ThermaCare(온열), 풀리오·클럭(일반 마사지). 상세 비교는 별도 경쟁 분석표를 기준으로 업데이트한다." -> 고객이 현재 선택하는 대안은 온열팩, 손 지압·마사지, 저주파 자극 기기, 일반 마사지기 등이다. 제품별로 사용 부위·목적·규제 분류가 달라 모두를 동일한 직접 경쟁사로 간주하지 않는다. 가격뿐 아니라 사용 편의, 소모품, 반복 사용 부담과 실제 지불 의사를 비교한다. 비교 후보: Myoovi·Livia·Beurer EM50(저주파), ThermaCare(온열), 풀리오·클럭(일반 마사지). 상세 비교는 별도 경쟁 분석표를 기준으로 업데이트한다.
C204: 비교 근거·확인 시점: 06_시장경쟁 및 07_근거원문. 타사 효능을 본 제품의 효능으로 인용하지 마세요.
C207: 숫자 수정 위치 | 기준 시나리오를 선택한 경우
C208: 가격 / 본체 제조원가 | G208: 01_가정!F12:H12 / F16:H16 | N208: 1~3년차 가격·제조원가
C210: 광고 CPC / 구매 전환율 | G210: 01_가정!F20:H20 / F24:H24 | N210: CAC와 판매량, 수익·현금이 함께 변합니다.
C212: 광고 예산 / 자연 유입 | G212: 01_가정!F44:H44 / F40:H40 | N212: 출시 후 판매량을 결정하는 가정
C214: 패치 첫 구매 / 월 잔존율 | G214: 01_가정!F32:H32 / F36:H36 | N214: 리필 반복 매출에 반영
C216: 상근 인원 / 월 급여 | G216: 01_가정!F60:H60 / F64:H64 | N216: 손익상 비용과 현금 부담에 반영
C218: 시장 고객 수·적합도·도입률 | G218: 01_가정!F110:F113 | N218: 별첨 시장규모 문안에 반영
C221: 보수·낙관 시나리오를 선택했다면 01_가정의 해당 시나리오 입력행을 수정하세요. 활성 가정행은 수식입니다. 제출 전 팀원·역할·효능 표현·시장 근거를 확인하고, 웹 양식에 붙여넣은 뒤 줄바꿈과 숫자를 다시 확인하세요.
